Workbook
Name P: 'Mon, Aug 31'!$A$1:$M$246
Name P.: 'Tue, Sep 01'!$A$1:$M$274

Sheet Mon, Aug 31
A1: BuildCare SCHEDULE MONDAY, AUGUST 31 / 2026
A3: SUPERVISOR ON CALL NJ: Sebastian Lopez (551) 202-4443 jlopez@build-care.com
A4: CREWS ASSIGNED BY DEFAULT ON CALL: DVM - Atlas Techs / Atlas Cleaning - HG Services
A5: CREWS CONFIRMED BY THE ON CALL: ????
A6: BC MEMBERS OFF/VACATIONS:
A7: CREW MEMBERS OFF/VACATIONS: Alluda Companies Agustin Lopez / DVM Angel Davila
D10: STATE OF NEW JERSEY
D12: WATERFRONT AREA (Fort Lee - Edgewater - Cliffside Park - Fairview - North Bergen - West New York - Weehawken - North Hoboken "8th Street Up" )
D13: BC SUPERVISOR: Carlos Perez (862) 383-3884 cperez@build-care.com BC SUPERVISOR/RUNNER: Juan Zapata (551) 202-4443 jzapata@build-care.com
A15: State | B15: MANAGEMENT | C15: BC CLERK | D15: BUILDING / ADDRESS | E15: UNIT / AREA | F15: SIZE | G15: WORKSITE STATUS | H15: JOB DESCRIPTION | I15: JOB AWARDED TO: / TECHS QUANTITY: | J15: REQUEST / P.O / WTN / W.O | K15: BC WORK ORDER / BC ESTIMATE | L15: EXTRAS | M15: SPECIAL NOTES / SEQUENCE | N15: VENDORS DAILY STATUS REPORT
A16: =IFERROR(VLOOKUP(D16,'Master sheet (Clientes)'!A$6:D$747,2,0)," ") -> NJ | B16: =IFERROR(VLOOKUP(D16,'Master sheet (Clientes)'!A$6:D$747,3,0)," ") -> Vivmark Residential | C16: =IFERROR(VLOOKUP(D16,'Master sheet (Clientes)'!A$6:D$747,4,0)," ") -> N-O | D16: Avalon at Edgewater II New Building (Russell). | E16: 104 | F16: 1BDR | G16: Occupeid | H16: Continue Repair openings that were made by other after suffering leak damage -Repairs will be in the coat closet, laundry closet, living room, hallway, bedroom, and bathroom walls. In the bathroom we will have to redo the bathroom tiles area is approximately 8x10 tiles will have to be removed, and sub floor repaired before installing new tiles at 9:00am The building will provide paint Bc to provide all other materials and labor needed to complete the job. For access, please call Christian 201-705-0879 or Alex 201-713-8719 | I16: AJ Canas Solutions Vinicio | J16: Email | N16: Continue
A17: =IFERROR(VLOOKUP(D17,'Master sheet (Clientes)'!A$6:D$747,2,0)," ") -> NJ | B17: =IFERROR(VLOOKUP(D17,'Master sheet (Clientes)'!A$6:D$747,3,0)," ") -> Vivmark Residential | C17: =IFERROR(VLOOKUP(D17,'Master sheet (Clientes)'!A$6:D$747,4,0)," ") -> N-O | D17: Avalon at Edgewater I Old Building (River Mews). | E17: 426 | G17: Occupied | H17: Make opening in guest bedroom 3x3 to reinstall loose Hvac vent, close opening, spackle, sand and paint NOTE: Bc to provide carpet film, plastic drop, spackle, mesh tape, trash bags, sanding sponge, blue tape and all other materials and labor needed to complete the job. / For access, please call Christian 201-705-0879 or Alex 201-713-8719 update the scope of work. Two more openings of 2x4 were required to see where ducts weren't connected. After the ducts were taped with duct tape, there still wasn't air flow. The building asked to please just temporarily close openings so they can do their own investigation tomorrow to see where the problem is. Once they determine and fix it, they will let us know so we can close all openings properly. | I17: AJ Canas Solutions javier | J17: Email | N17: Job placed on hold waiting new date to continue
A18: =IFERROR(VLOOKUP(D18,'Master sheet (Clientes)'!A$6:D$747,2,0)," ") -> NJ | B18: =IFERROR(VLOOKUP(D18,'Master sheet (Clientes)'!A$6:D$747,3,0)," ") -> Vivmark Residential | C18: =IFERROR(VLOOKUP(D18,'Master sheet (Clientes)'!A$6:D$747,4,0)," ") -> N-O | D18: Avalon at Edgewater II New Building (Russell). | E18: 155 | G18: Occupied | H18: Left side bedroom bathroom tile floor to be demoed, sub floor fixed, install new tiles, and grout area is 9ft x 6ft. at 9am Bc to provide all materials and labor needed to complete the job. For access, please call Christian 201-705-0879 or Alex 201-713-8719 | I18: AJ Canas Solutions Ricardo / Willian Alvarez | J18: Email | N18: Continue
A19: =IFERROR(VLOOKUP(D19,'Master sheet (Clientes)'!A$6:D$747,2,0)," ") -> NJ | B19: =IFERROR(VLOOKUP(D19,'Master sheet (Clientes)'!A$6:D$747,3,0)," ") -> Vivmark Residential | C19: =IFERROR(VLOOKUP(D19,'Master sheet (Clientes)'!A$6:D$747,4,0)," ") -> A-V | D19: The Rivington Apartments 1130 Grand St, Hoboken, NJ 07030. | E19: SG 310 | F19: 2BDR | G19: Vacant | H19: Paint unit at 8:00 am | I19: AJ Canas Solutions William Diaz | J19: Email | M19: Clean 09/02 | N19: Paint done
A21: State | B21: MANAGEMENT | C21: BC CLERK | D21: BUILDING / ADDRESS | E21: UNIT / AREA | F21: SIZE | G21: WORKSITE STATUS | H21: JOB DESCRIPTION | I21: JOB AWARDED TO: / TECHS QUANTITY: | J21: REQUEST / P.O / WTN / W.O | K21: BC WORK ORDER / BC ESTIMATE | L21: EXTRAS | M21: SPECIAL NOTES / SEQUENCE | N21: VENDORS DAILY STATUS REPORT
A22: =IFERROR(VLOOKUP(D22,'Master sheet (Clientes)'!A$6:D$747,2,0)," ") -> NJ | B22: =IFERROR(VLOOKUP(D22,'Master sheet (Clientes)'!A$6:D$747,3,0)," ") -> Greystar | C22: =IFERROR(VLOOKUP(D22,'Master sheet (Clientes)'!A$6:D$747,4,0)," ") -> A-V | D22: The Grand 508 51st St, West New York, NJ 07093 | E22: 407 | F22: 1BDR | G22: Vacant | H22: Paint unit and Unit cleaning at 8:00am Note: Property will provide the paint. | I22: Atlas Javier Santiago | J22: Email | N22: Paint done
A23: =IFERROR(VLOOKUP(D23,'Master sheet (Clientes)'!A$6:D$747,2,0)," ") -> NJ | B23: =IFERROR(VLOOKUP(D23,'Master sheet (Clientes)'!A$6:D$747,3,0)," ") -> Vivmark Residential | C23: =IFERROR(VLOOKUP(D23,'Master sheet (Clientes)'!A$6:D$747,4,0)," ") -> A-V | D23: The Landings at Port Imperial Apartment 4 Ave at Port Imperial, West New York, NJ 07093. | E23: 1101 | F23: 3BDR | G23: Vacant | H23: Paint unit at 8:00 am | I23: Atlas Douglas Espinal | J23: Email | M23: Clean 09/01 | N23: Paint done
A25: State | B25: MANAGEMENT | C25: BC CLERK | D25: BUILDING / ADDRESS | E25: UNIT / AREA | F25: SIZE | G25: WORKSITE STATUS | H25: JOB DESCRIPTION | I25: JOB AWARDED TO: / TECHS QUANTITY: | J25: REQUEST / P.O / WTN / W.O | K25: BC WORK ORDER / BC ESTIMATE | L25: EXTRAS | M25: SPECIAL NOTES / SEQUENCE | N25: VENDORS DAILY STATUS REPORT
A26: =IFERROR(VLOOKUP(D26,'Master sheet (Clientes)'!A$6:D$747,2,0)," ") -> NJ | B26: =IFERROR(VLOOKUP(D26,'Master sheet (Clientes)'!A$6:D$747,3,0)," ") -> Skylight | C26: =IFERROR(VLOOKUP(D26,'Master sheet (Clientes)'!A$6:D$747,4,0)," ") -> N-O | D26: The Sterling 2055 Center Ave, Fort Lee, NJ 07024 | E26: 14A | F26: 1BDR | G26: Vacant | H26: Post Construction cleaning at 8:00am | I26: YL Cleaning | J26: Email | K26: Estimate 16258 | M26: This project is for capital projects and will be paid under the construction budget not the property | N26: Cancelled no longer needed the lceaning was made by the tenant since they moved in on 08/28
A27: =IFERROR(VLOOKUP(D27,'Master sheet (Clientes)'!A$6:D$747,2,0)," ") -> NJ | B27: =IFERROR(VLOOKUP(D27,'Master sheet (Clientes)'!A$6:D$747,3,0)," ") -> Skylight | C27: =IFERROR(VLOOKUP(D27,'Master sheet (Clientes)'!A$6:D$747,4,0)," ") -> N-O | D27: Riello 99 Gorge Rd, Edgewater, NJ 07020 | E27: 1506 | F27: 1BDR | G27: Vacant | H27: Deep Cleaning Unit at 8:00am For access, please call Tim 1 (914) 409-8866 or Chris 917-774-4548 | I27: YL Cleaning | J27: Email | N27: Done
A28: =IFERROR(VLOOKUP(D28,'Master sheet (Clientes)'!A$6:D$747,2,0)," ") -> NJ | B28: =IFERROR(VLOOKUP(D28,'Master sheet (Clientes)'!A$6:D$747,3,0)," ") -> Skylight | C28: =IFERROR(VLOOKUP(D28,'Master sheet (Clientes)'!A$6:D$747,4,0)," ") -> N-O | D28: Riello 99 Gorge Rd, Edgewater, NJ 07020 | E28: 1502 | F28: 1BDR | G28: Vacant | H28: Deep Cleaning Unit at 8:00am For access, please call Tim 1 (914) 409-8866 or Chris 917-774-4548 | I28: YL Cleaning | J28: Email | N28: Done
A29: =IFERROR(VLOOKUP(D29,'Master sheet (Clientes)'!A$6:D$747,2,0)," ") -> NJ | B29: =IFERROR(VLOOKUP(D29,'Master sheet (Clientes)'!A$6:D$747,3,0)," ") -> Skylight | C29: =IFERROR(VLOOKUP(D29,'Master sheet (Clientes)'!A$6:D$747,4,0)," ") -> N-O | D29: Riello 99 Gorge Rd, Edgewater, NJ 07020 | E29: 1503 | F29: 2BDR | G29: Vacant | H29: Deep Cleaning Unit at 8:00am For access, please call Tim 1 (914) 409-8866 or Chris 917-774-4548 | I29: YL Cleaning | J29: Email | N29: Done
A30: =IFERROR(VLOOKUP(D30,'Master sheet (Clientes)'!A$6:D$747,2,0)," ") -> NJ | B30: =IFERROR(VLOOKUP(D30,'Master sheet (Clientes)'!A$6:D$747,3,0)," ") -> Skylight | C30: =IFERROR(VLOOKUP(D30,'Master sheet (Clientes)'!A$6:D$747,4,0)," ") -> N-O | D30: Riello 99 Gorge Rd, Edgewater, NJ 07020 | E30: 1702 | F30: 1BDR | G30: Vacant | H30: Deep Cleaning Unit at 8:00am For access, please call Tim 1 (914) 409-8866 or Chris 917-774-4548 | I30: YL Cleaning | J30: Email | N30: Done
A31: =IFERROR(VLOOKUP(D31,'Master sheet (Clientes)'!A$6:D$747,2,0)," ") -> NJ | B31: =IFERROR(VLOOKUP(D31,'Master sheet (Clientes)'!A$6:D$747,3,0)," ") -> Vivmark Residential | C31: =IFERROR(VLOOKUP(D31,'Master sheet (Clientes)'!A$6:D$747,4,0)," ") -> N-O | D31: Avalon at Edgewater II New Building (Russell). | E31: 104 | F31: 1BDR | G31: Occupeid | H31: Unit Cleaning after repair / Last minute assigned by Carlos | I31: YL Cleaning | J31: Email | N31: Done
A33: State | B33: MANAGEMENT | C33: BC CLERK | D33: BUILDING / ADDRESS | E33: UNIT / AREA | F33: SIZE | G33: WORKSITE STATUS | H33: JOB DESCRIPTION | I33: JOB AWARDED TO: / TECHS QUANTITY: | J33: REQUEST / P.O / WTN / W.O | K33: BC WORK ORDER / BC ESTIMATE | L33: EXTRAS | M33: SPECIAL NOTES / SEQUENCE | N33: VENDORS DAILY STATUS REPORT
A34: =IFERROR(VLOOKUP(D34,'Master sheet (Clientes)'!A$6:D$747,2,0)," ") -> NJ | B34: =IFERROR(VLOOKUP(D34,'Master sheet (Clientes)'!A$6:D$747,3,0)," ") -> Vivmark Residential | C34: =IFERROR(VLOOKUP(D34,'Master sheet (Clientes)'!A$6:D$747,4,0)," ") -> N-O | D34: Avalon at Edgewater II New Building (Russell). | E34: Bike room | H34: Scrape damaged concrete wall refill holes with concrete once dry repaint that area with same color spec. Call Carlos Perez for further instructions | I34: MVC Cleaning | J34: Email | K34: Estimate 16730 | M34: Bike Room / This job can't be mentioned on the final invoice | N34: Done
A35: =IFERROR(VLOOKUP(D35,'Master sheet (Clientes)'!A$6:D$747,2,0)," ") -> NJ | B35: =IFERROR(VLOOKUP(D35,'Master sheet (Clientes)'!A$6:D$747,3,0)," ") -> Vivmark Residential | C35: =IFERROR(VLOOKUP(D35,'Master sheet (Clientes)'!A$6:D$747,4,0)," ") -> N-O | D35: Avalon at Edgewater I Old Building (River Mews). | E35: 419 | G35: Occupied | H35: Inspect and Repair Water leak that might be coming from the skylight - Bc to provide all materials and labor needed to complete the job. For access, please call Christian 201-705-0879 or Alex 201-713-8719 Last minute request | I35: MVC Cleaning | J35: Email | N35: Done
A37: State | B37: MANAGEMENT | C37: BC CLERK | D37: BUILDING / ADDRESS | E37: UNIT / AREA | F37: SIZE | G37: WORKSITE STATUS | H37: MEETING / INSPECTION | I37: EMPLOYEE OR TEAM ASSIGNED | J37: REQUEST / P.O / WTN / W.O | K37: BC WORK ORDER / BC ESTIMATE | L37: EXTRAS | M37: SPECIAL NOTES / SEQUENCE | N37: VENDORS DAILY STATUS REPORT
A38: =IFERROR(VLOOKUP(D38,'Master sheet (Clientes)'!A$6:D$747,2,0)," ") -> NJ | B38: =IFERROR(VLOOKUP(D38,'Master sheet (Clientes)'!A$6:D$747,3,0)," ") -> Vivmark Residential | C38: =IFERROR(VLOOKUP(D38,'Master sheet (Clientes)'!A$6:D$747,4,0)," ") -> N-O | D38: Avalon at Edgewater II New Building (Russell). | E38: 324 | G38: Occupied | H38: Bathtub reglaze NOTE: Please be on tie since this unit is occupied / For access, please call Christian 201-705-0879 or Alex 201-713-8719 | I38: Felix R Santos | J38: Email | N38: Done
A40: State | B40: MANAGEMENT | C40: BC CLERK | D40: BUILDING / ADDRESS | E40: UNIT / AREA | F40: SIZE | G40: WORKSITE STATUS | H40: JOB DESCRIPTION | I40: JOB AWARDED TO: / TECHS QUANTITY: | J40: REQUEST / P.O / WTN / W.O | K40: BC WORK ORDER / BC ESTIMATE | L40: EXTRAS | M40: SPECIAL NOTES / SEQUENCE | N40: VENDORS DAILY STATUS REPORT
A41: =IFERROR(VLOOKUP(D41,'Master sheet (Clientes)'!A$6:D$747,2,0)," ") -> NJ | B41: =IFERROR(VLOOKUP(D41,'Master sheet (Clientes)'!A$6:D$747,3,0)," ") -> Vivmark Residential | C41: =IFERROR(VLOOKUP(D41,'Master sheet (Clientes)'!A$6:D$747,4,0)," ") -> N-O | D41: Avalon at Edgewater II New Building (Russell). | E41: 104 | G41: ??? | H41: Sub-floor repair and carpet padding | I41: Excellent Carpet | J41: Email | N41: Done
D43: SOUTH HOBOKEN "7th Street down" - JERSEY CITY - BAYONNE
D44: JERSEY CITY - BC SUPERVISOR: Carlos Perez (862) 383-3884 cperez@build-care.com - BC RUNNER: Juan Sebastian Salazar (862) 394-6010 jssalazar@build-care.com
A46: State | B46: MANAGEMENT | C46: BC CLERK | D46: BUILDING / ADDRESS | E46: UNIT / AREA | F46: SIZE | G46: WORKSITE STATUS | H46: JOB DESCRIPTION | I46: JOB AWARDED TO: / TECHS QUANTITY: | J46: REQUEST / P.O / WTN / W.O | K46: BC WORK ORDER / BC ESTIMATE | L46: EXTRAS | M46: SPECIAL NOTES / SEQUENCE | N46: VENDORS DAILY STATUS REPORT
A47: =IFERROR(VLOOKUP(D47,'Master sheet (Clientes)'!A$6:D$747,2,0)," ") -> NJ | B47: =IFERROR(VLOOKUP(D47,'Master sheet (Clientes)'!A$6:D$747,3,0)," ") -> RHO | C47: =IFERROR(VLOOKUP(D47,'Master sheet (Clientes)'!A$6:D$747,4,0)," ") -> A-V | D47: Sable 200 Greene Street, Jersey City, NJ 07311. | H47: 1 Daily Handyman service everyday Until Monday 08/31 Please Report to Nate (201) 466-8357 | I47: Sanai Pliability Delfino Cuxil | J47: Email | M47: Extended until Monday 08/31 | N47: Completed
A48: =IFERROR(VLOOKUP(D48,'Master sheet (Clientes)'!A$6:D$747,2,0)," ") -> NJ | B48: =IFERROR(VLOOKUP(D48,'Master sheet (Clientes)'!A$6:D$747,3,0)," ") -> Skylight | C48: =IFERROR(VLOOKUP(D48,'Master sheet (Clientes)'!A$6:D$747,4,0)," ") -> N-O | D48: Grand Adams Apartments 300 Grand St, Hoboken, NJ 07030 | H48: 1 Daily Handyman to work with the maintenance staff 8hrs shift to cover multiple properties under the instructions of the service general manager Upon Arrival Call Orville (646) 984-3306 from 9:00am to 5:00pm Monday to Friday until further notice Starting Tuesday 02/26/2025 | I48: Cuxil Group Eduardo Garcia | J48: Email | M48: until further notice | N48: Continue
A49: =IFERROR(VLOOKUP(D49,'Master sheet (Clientes)'!A$6:D$747,2,0)," ") -> NJ | B49: =IFERROR(VLOOKUP(D49,'Master sheet (Clientes)'!A$6:D$747,3,0)," ") -> Skylight | C49: =IFERROR(VLOOKUP(D49,'Master sheet (Clientes)'!A$6:D$747,4,0)," ") -> N-O | D49: Grand Adams Apartments 300 Grand St, Hoboken, NJ 07030 | H49: 1 Daily handyman for 8hrs shift to assist the property with internal tasks from Monday to Friday until further notice NOTE: Please Report to Christina 973-776-4602 | I49: Cuxil Group Marcos Garcia | J49: Email | M49: until further notice | N49: Continue
A50: =IFERROR(VLOOKUP(D50,'Master sheet (Clientes)'!A$6:D$747,2,0)," ") -> NJ | B50: =IFERROR(VLOOKUP(D50,'Master sheet (Clientes)'!A$6:D$747,3,0)," ") -> Optimum | C50: =IFERROR(VLOOKUP(D50,'Master sheet (Clientes)'!A$6:D$747,4,0)," ") -> A-V | D50: 25 Kensington Ave Jersey City, NJ 07304 | E50: Medical Office Suite #106 | G50: Occupied | H50: Continue Repair all walls / Paint the entire commercial space Color change at 8:30am NOTE: **The reception area, the room with the file cabinet, will not be painted.** / Please contact super Eduardo for access: 551-260-0514 | I50: Sanai Pliability Eddy Cumes / Alexander Polanco | J50: Email | N50: Continue
A52: State | B52: MANAGEMENT | C52: BC CLERK | D52: BUILDING / ADDRESS | E52: UNIT / AREA | F52: SIZE | G52: WORKSITE STATUS | H52: JOB DESCRIPTION | I52: JOB AWARDED TO: / TECHS QUANTITY: | J52: REQUEST / P.O / WTN / W.O | K52: BC WORK ORDER / BC ESTIMATE | L52: EXTRAS | M52: SPECIAL NOTES / SEQUENCE | N52: VENDORS DAILY STATUS REPORT
A53: =IFERROR(VLOOKUP(D53,'Master sheet (Clientes)'!A$6:D$747,2,0)," ") -> NJ | B53: =IFERROR(VLOOKUP(D53,'Master sheet (Clientes)'!A$6:D$747,3,0)," ") -> Rose Associates | C53: =IFERROR(VLOOKUP(D53,'Master sheet (Clientes)'!A$6:D$747,4,0)," ") -> A-V | D53: VYV Apartments North and South 474 Warren St, Jersey City, NJ 07302. | H53: 1 Daily Handyman Service: Provide a full-time daily handyman to assist the property with make-ready orders from 8:00 am to 4:30 pm. 5 Days per week Monday to Friday Starting Monday 08/03/26 to Friday 10/16/2026 | I53: Atlas Alexis Gomez | J53: Email | L53: New management | M53: 5 days per week Until 10/16 | N53: Continue
A54: =IFERROR(VLOOKUP(D54,'Master sheet (Clientes)'!A$6:D$747,2,0)," ") -> NJ | B54: =IFERROR(VLOOKUP(D54,'Master sheet (Clientes)'!A$6:D$747,3,0)," ") -> Skylight | C54: =IFERROR(VLOOKUP(D54,'Master sheet (Clientes)'!A$6:D$747,4,0)," ") -> N-O | D54: Grand Adams Apartments 300 Grand St, Hoboken, NJ 07030 | E54: Fire Pump / Elevator Machine Room | H54: Continue Basement Clean Up & Vent Installation: Clean the basement area, remove all debris, and seal accessible openings with concrete to help prevent rodent intrusion \ Furnish and install an exhaust vent/fan to improve ventilation and reduce odors at 9:00am | I54: Atlas Moises Rivas / Jesua Mancilla | J54: Email | K54: Estimate 16451 | M54: Project for skylight renovations not the property. Please invoce accordingly | N54: Done
A55: =IFERROR(VLOOKUP(D55,'Master sheet (Clientes)'!A$6:D$747,2,0)," ") -> NJ | B55: =IFERROR(VLOOKUP(D55,'Master sheet (Clientes)'!A$6:D$747,3,0)," ") -> Vivmark Residential | C55: =IFERROR(VLOOKUP(D55,'Master sheet (Clientes)'!A$6:D$747,4,0)," ") -> A-V | D55: Portside Towers Apartments 155 Washington St, Jersey City, NJ 07302. | E55: 1408W | F55: 1BDR | G55: Vacant | H55: Paint unit at 8:00 am | I55: Atlas Armando Gaona | J55: WTN 86394548 | M55: Cleaning 09/02 | N55: Paint done
A56: =IFERROR(VLOOKUP(D56,'Master sheet (Clientes)'!A$6:D$747,2,0)," ") -> NJ | B56: =IFERROR(VLOOKUP(D56,'Master sheet (Clientes)'!A$6:D$747,3,0)," ") -> Bozzuto | C56: =IFERROR(VLOOKUP(D56,'Master sheet (Clientes)'!A$6:D$747,4,0)," ") -> N-O | D56: Edge Avenue F 170 Avenue F, Bayonne, NJ 07002 | E56: 442 | F56: 2BDR | G56: Vacant | H56: Paint unit and Unit cleaning at 8:00am NOTE: Move-ins 09/03 | I56: Atlas Jesus Alvarado | J56: Email | N56: Paint done
A57: =IFERROR(VLOOKUP(D57,'Master sheet (Clientes)'!A$6:D$747,2,0)," ") -> NJ | B57: =IFERROR(VLOOKUP(D57,'Master sheet (Clientes)'!A$6:D$747,3,0)," ") -> Bozzuto | C57: =IFERROR(VLOOKUP(D57,'Master sheet (Clientes)'!A$6:D$747,4,0)," ") -> N-O | D57: Vantage Collection 1 Park View Ave, Jersey City, NJ 07302 | E57: PH38 | F57: 2BDR | G57: Vacant | H57: Paint unit at 8:00 am | I57: Atlas Elder Velasquez | J57: Email | N57: Rescheduled Thursday 09/03
A59: State | B59: MANAGEMENT | C59: BC CLERK | D59: BUILDING / ADDRESS | E59: UNIT / AREA | F59: SIZE | G59: WORKSITE STATUS | H59: JOB DESCRIPTION | I59: JOB AWARDED TO: / TECHS QUANTITY: | J59: REQUEST / P.O / WTN / W.O | K59: BC WORK ORDER / BC ESTIMATE | L59: EXTRAS | M59: SPECIAL NOTES / SEQUENCE | N59: VENDORS DAILY STATUS REPORT
A60: =IFERROR(VLOOKUP(D60,'Master sheet (Clientes)'!A$6:D$747,2,0)," ") -> NJ | B60: =IFERROR(VLOOKUP(D60,'Master sheet (Clientes)'!A$6:D$747,3,0)," ") -> Greystar | C60: =IFERROR(VLOOKUP(D60,'Master sheet (Clientes)'!A$6:D$747,4,0)," ") -> A-V | D60: BELA 74 Maple St, Jersey City, NJ 07304 | E60: 701 | F60: 2BDR + Den | G60: Vacant | H60: Paint unit and Unit cleaning at 8:00am | I60: Alluda Arturo Lopez | J60: Email | M60: The tenat did not move out | N60: Cancelled
A61: =IFERROR(VLOOKUP(D61,'Master sheet (Clientes)'!A$6:D$747,2,0)," ") -> NJ | B61: =IFERROR(VLOOKUP(D61,'Master sheet (Clientes)'!A$6:D$747,3,0)," ") -> Greystar | C61: =IFERROR(VLOOKUP(D61,'Master sheet (Clientes)'!A$6:D$747,4,0)," ") -> A-V | D61: The Bedford 374 Communipaw Ave, Jersey City, NJ 07304 | E61: 410 | F61: 2BDR | G61: Vacant | H61: Paint unit and Unit cleaning at 8:00am The building will provide the paint. For access, please contact Rob 732-570-9820 / Last Minute Request Job Assigned by Carlos | I61: Alluda Arturo Lopez | J61: Email | N61: Paint done
A62: =IFERROR(VLOOKUP(D62,'Master sheet (Clientes)'!A$6:D$747,2,0)," ") -> NJ | B62: =IFERROR(VLOOKUP(D62,'Master sheet (Clientes)'!A$6:D$747,3,0)," ") -> Greystar | C62: =IFERROR(VLOOKUP(D62,'Master sheet (Clientes)'!A$6:D$747,4,0)," ") -> A-V | D62: BELA 74 Maple St, Jersey City, NJ 07304 | E62: 316 | F62: 2BDR | G62: Vacant | H62: Paint unit and Unit cleaning at 8:00am | I62: Alluda Fabian Munoz | J62: Email | N62: Paint done
A63: =IFERROR(VLOOKUP(D63,'Master sheet (Clientes)'!A$6:D$747,2,0)," ") -> NJ | B63: =IFERROR(VLOOKUP(D63,'Master sheet (Clientes)'!A$6:D$747,3,0)," ") -> Greystar | C63: =IFERROR(VLOOKUP(D63,'Master sheet (Clientes)'!A$6:D$747,4,0)," ") -> A-V | D63: BELA 74 Maple St, Jersey City, NJ 07304 | E63: 801 | F63: 2BDR | G63: Vacant | H63: Paint unit and Unit cleaning at 8:00am | I63: Alluda Horacio Lopez | J63: Email | M63: Reglaze 09/02 | N63: Paint done
A64: =IFERROR(VLOOKUP(D64,'Master sheet (Clientes)'!A$6:D$747,2,0)," ") -> NJ | B64: =IFERROR(VLOOKUP(D64,'Master sheet (Clientes)'!A$6:D$747,3,0)," ") -> Bozzuto | C64: =IFERROR(VLOOKUP(D64,'Master sheet (Clientes)'!A$6:D$747,4,0)," ") -> N-O | D64: Vantage Collection 1 Park View Ave, Jersey City, NJ 07302 | E64: PH38 | G64: Occupied | H64: Door and shelving Installation: Remove and demo the existing pocket door, including the frame. \ Perform all necessary repairs required to install a Buildcare-provided 36" x 80" metal frame. \ Install the property-provided door. \ Install Buildcare-provided door hardware. \ Paint the wall, door, and frame using property-provided paint. \ Install the Buildcare-provided closet shelving system that was previously removed by the client. | I64: Alluda Anibal Yojero / Misael Yojero | J64: Email | K64: Estimate 15942 | M64: 4 Handys quoted | N64: Continue
A66: State | B66: MANAGEMENT | C66: BC CLERK | D66: BUILDING / ADDRESS | E66: UNIT / AREA | F66: SIZE | G66: WORKSITE STATUS | H66: JOB DESCRIPTION | I66: JOB AWARDED TO: / TECHS QUANTITY: | J66: REQUEST / P.O / WTN / W.O | K66: BC WORK ORDER / BC ESTIMATE | L66: EXTRAS | M66: SPECIAL NOTES / SEQUENCE | N66: VENDORS DAILY STATUS REPORT
A67: =IFERROR(VLOOKUP(D67,'Master sheet (Clientes)'!A$6:D$747,2,0)," ") -> NJ | B67: =IFERROR(VLOOKUP(D67,'Master sheet (Clientes)'!A$6:D$747,3,0)," ") -> Bozzuto | C67: =IFERROR(VLOOKUP(D67,'Master sheet (Clientes)'!A$6:D$747,4,0)," ") -> N-O | D67: Edge Avenue G 100 Avenue G, Bayonne, NJ 07002 | E67: 374 | F67: 1BDR | G67: Vacant | H67: Paint unit and Unit cleaning at 8:00am NOTE: Move-ins 09/03 | I67: DVM Ignacio Luc | J67: Email | N67: Paint done
A68: =IFERROR(VLOOKUP(D68,'Master sheet (Clientes)'!A$6:D$747,2,0)," ") -> NJ | B68: =IFERROR(VLOOKUP(D68,'Master sheet (Clientes)'!A$6:D$747,3,0)," ") -> Bozzuto | C68: =IFERROR(VLOOKUP(D68,'Master sheet (Clientes)'!A$6:D$747,4,0)," ") -> N-O | D68: Edge Avenue G 100 Avenue G, Bayonne, NJ 07002 | E68: 466 | F68: 1BDR | G68: Vacant | H68: Paint unit and Unit cleaning at 8:00am NOTE: Move-ins 09/03 | I68: DVM Celestino Luc | J68: Email | N68: Paint done
A70: State | B70: MANAGEMENT | C70: BC CLERK | D70: BUILDING / ADDRESS | E70: UNIT / AREA | F70: SIZE | G70: WORKSITE STATUS | H70: JOB DESCRIPTION | I70: JOB AWARDED TO: / TECHS QUANTITY: | J70: REQUEST / P.O / WTN / W.O | K70: BC WORK ORDER / BC ESTIMATE | L70: EXTRAS | M70: SPECIAL NOTES / SEQUENCE | N70: VENDORS DAILY STATUS REPORT
A71: =IFERROR(VLOOKUP(D71,'Master sheet (Clientes)'!A$6:D$747,2,0)," ") -> NJ | B71: =IFERROR(VLOOKUP(D71,'Master sheet (Clientes)'!A$6:D$747,3,0)," ") -> Rose Associates | C71: =IFERROR(VLOOKUP(D71,'Master sheet (Clientes)'!A$6:D$747,4,0)," ") -> A-V | D71: 39 High Street 39 High Street Jersey City, NJ 07306 | E71: 201 | G71: Vacant | H71: Drywall Repairs: Repair the damaged drywall at the bedroom soffit, approximately 2 ft x 9 ft \ Provide and install the necessary framing support \ Install approximately 1 linear ft of 1x2 lumber at the wall as needed for proper drywall support \ Provide and install missing drywall in the hallway in the following approximate areas: 2 ft x 5 ft and 2 ft x 4 ft \ Tape, apply joint compound, and finish all drywall seams and repaired areas \ Sand all repaired surfaces to achieve a smooth and even finish \ Prime all repaired areas and leave them ready for paint. | I71: AJ Canas Solutions Carlos / Alberto | J71: Email | K71: Estimate 16927 | M71: 3 handys quoted | N71: Continue
A73: State | B73: MANAGEMENT | C73: BC CLERK | D73: BUILDING / ADDRESS | E73: UNIT / AREA | F73: SIZE | G73: WORKSITE STATUS | H73: JOB DESCRIPTION | I73: JOB AWARDED TO: / TECHS QUANTITY: | J73: REQUEST / P.O / WTN / W.O | K73: BC WORK ORDER / BC ESTIMATE | L73: EXTRAS | M73: SPECIAL NOTES / SEQUENCE | N73: VENDORS DAILY STATUS REPORT
A74: =IFERROR(VLOOKUP(D74,'Master sheet (Clientes)'!A$6:D$747,2,0)," ") -> NJ | B74: =IFERROR(VLOOKUP(D74,'Master sheet (Clientes)'!A$6:D$747,3,0)," ") -> Greystar | C74: =IFERROR(VLOOKUP(D74,'Master sheet (Clientes)'!A$6:D$747,4,0)," ") -> A-V | D74: One Grove 215 Grove St, Jersey City, NJ 07302 | E74: 1110 | F74: 3BDR | G74: Vacant | H74: Unit cleaning at 8:00am NOTE: For access, please call Andrew 347-912-2434 | I74: YL Cleaning | J74: Email | N74: Done
A75: =IFERROR(VLOOKUP(D75,'Master sheet (Clientes)'!A$6:D$747,2,0)," ") -> NJ | B75: =IFERROR(VLOOKUP(D75,'Master sheet (Clientes)'!A$6:D$747,3,0)," ") -> Greystar | C75: =IFERROR(VLOOKUP(D75,'Master sheet (Clientes)'!A$6:D$747,4,0)," ") -> A-V | D75: One Grove 215 Grove St, Jersey City, NJ 07302 | E75: PH 11 | F75: 1BDR | G75: Vacant | H75: Unit cleaning at 8:00am NOTE: For access, please call Andrew 347-912-2434 | I75: YL Cleaning | J75: Email | N75: Done
A76: =IFERROR(VLOOKUP(D76,'Master sheet (Clientes)'!A$6:D$747,2,0)," ") -> NJ | B76: =IFERROR(VLOOKUP(D76,'Master sheet (Clientes)'!A$6:D$747,3,0)," ") -> Greystar | C76: =IFERROR(VLOOKUP(D76,'Master sheet (Clientes)'!A$6:D$747,4,0)," ") -> A-V | D76: One Grove 215 Grove St, Jersey City, NJ 07302 | E76: 713 | F76: 1BDR | G76: Vacant | H76: Touch-up cleaning at 8:00am NOTE: For access, please call Andrew 347-912-2434 | I76: YL Cleaning | J76: Email | N76: Done
A77: =IFERROR(VLOOKUP(D77,'Master sheet (Clientes)'!A$6:D$747,2,0)," ") -> NJ | B77: =IFERROR(VLOOKUP(D77,'Master sheet (Clientes)'!A$6:D$747,3,0)," ") -> Greystar | C77: =IFERROR(VLOOKUP(D77,'Master sheet (Clientes)'!A$6:D$747,4,0)," ") -> A-V | D77: One Grove 215 Grove St, Jersey City, NJ 07302 | E77: 711 | F77: 1BDR | G77: Vacant | H77: Touch-up cleaning at 8:00am NOTE: For access, please call Andrew 347-912-2434 | I77: YL Cleaning | J77: Email | N77: Done
A78: =IFERROR(VLOOKUP(D78,'Master sheet (Clientes)'!A$6:D$747,2,0)," ") -> NJ | B78: =IFERROR(VLOOKUP(D78,'Master sheet (Clientes)'!A$6:D$747,3,0)," ") -> Vivmark Residential | C78: =IFERROR(VLOOKUP(D78,'Master sheet (Clientes)'!A$6:D$747,4,0)," ") -> A-V | D78: 70 Greene Apartments 70 Greene St, Jersey City, NJ 07302. | E78: 4210 | F78: Studio | G78: Vacant | H78: Unit cleaning at 8:00 am | I78: YL Cleaning | J78: WTN 85887899 | N78: Done
A79: =IFERROR(VLOOKUP(D79,'Master sheet (Clientes)'!A$6:D$747,2,0)," ") -> NJ | B79: =IFERROR(VLOOKUP(D79,'Master sheet (Clientes)'!A$6:D$747,3,0)," ") -> Vivmark Residential | C79: =IFERROR(VLOOKUP(D79,'Master sheet (Clientes)'!A$6:D$747,4,0)," ") -> A-V | D79: Portside Towers Apartments 155 Washington St, Jersey City, NJ 07302. | E79: 1102W | F79: 2BDR | G79: Vacant | H79: Unit cleaning at 8:00 am | I79: YL Cleaning | J79: WTN 86393684 | N79: Done
A81: State | B81: MANAGEMENT | C81: BC CLERK | D81: BUILDING / ADDRESS | E81: UNIT / AREA | F81: SIZE | G81: WORKSITE STATUS | H81: JOB DESCRIPTION | I81: JOB AWARDED TO: / TECHS QUANTITY: | J81: REQUEST / P.O / WTN / W.O | K81: BC WORK ORDER / BC ESTIMATE | L81: EXTRAS | M81: SPECIAL NOTES / SEQUENCE | N81: VENDORS DAILY STATUS REPORT
A82: =IFERROR(VLOOKUP(D82,'Master sheet (Clientes)'!A$6:D$747,2,0)," ") -> NJ | B82: =IFERROR(VLOOKUP(D82,'Master sheet (Clientes)'!A$6:D$747,3,0)," ") -> Two Coast Living | C82: =IFERROR(VLOOKUP(D82,'Master sheet (Clientes)'!A$6:D$747,4,0)," ") -> N-O | D82: 77 Park Avenue Apartments 77 Park Ave, Hoboken, NJ 07030 | E82: 404 | F82: 1BDR | G82: Vacant | H82: Unit Cleaning at 8:00am | I82: Atlas Way Cleaning | J82: PO#568511 | N82: Done
A83: =IFERROR(VLOOKUP(D83,'Master sheet (Clientes)'!A$6:D$747,2,0)," ") -> NJ | B83: =IFERROR(VLOOKUP(D83,'Master sheet (Clientes)'!A$6:D$747,3,0)," ") -> Two Coast Living | C83: =IFERROR(VLOOKUP(D83,'Master sheet (Clientes)'!A$6:D$747,4,0)," ") -> N-O | D83: 77 Park Avenue Apartments 77 Park Ave, Hoboken, NJ 07030 | E83: 907 | F83: 1BDR | G83: Vacant | H83: Unit Cleaning at 8:00am | I83: Atlas Way Cleaning | J83: PO#569273 | N83: Done
A85: State | B85: MANAGEMENT | C85: BC CLERK | D85: BUILDING / ADDRESS | E85: UNIT / AREA | F85: SIZE | G85: WORKSITE STATUS | H85: JOB DESCRIPTION | I85: JOB AWARDED TO: / TECHS QUANTITY: | J85: REQUEST / P.O / WTN / W.O | K85: BC WORK ORDER / BC ESTIMATE | L85: EXTRAS | M85: SPECIAL NOTES / SEQUENCE | N85: VENDORS DAILY STATUS REPORT
A86: =IFERROR(VLOOKUP(D86,'Master sheet (Clientes)'!A$6:D$747,2,0)," ") -> NJ | B86: =IFERROR(VLOOKUP(D86,'Master sheet (Clientes)'!A$6:D$747,3,0)," ") -> Optimum | C86: =IFERROR(VLOOKUP(D86,'Master sheet (Clientes)'!A$6:D$747,4,0)," ") -> A-V | D86: 19 Kensington Ave Jersey City, NJ 07304 | E86: 301 | G86: Occupied | H86: Tub glaze and tiles as well for the whole bathroom to be reglazed At 9:00am This is an older unit, the tiles I believe have been glazed before but now are peeling. | I86: Felix R Santos | J86: Email | N86: Done
A87: =IFERROR(VLOOKUP(D87,'Master sheet (Clientes)'!A$6:D$747,2,0)," ") -> NJ | B87: =IFERROR(VLOOKUP(D87,'Master sheet (Clientes)'!A$6:D$747,3,0)," ") -> C/O Realty | C87: =IFERROR(VLOOKUP(D87,'Master sheet (Clientes)'!A$6:D$747,4,0)," ") -> N-O | D87: Southampton at Newport 20 River Ct, Jersey City, NJ 07310 | E87: 1909 | G87: Vacant | H87: Bathtub reglaze at 8:00am | I87: Felix R Santos | J87: Email | N87: Done
A88: =IFERROR(VLOOKUP(D88,'Master sheet (Clientes)'!A$6:D$747,2,0)," ") -> NJ | B88: =IFERROR(VLOOKUP(D88,'Master sheet (Clientes)'!A$6:D$747,3,0)," ") -> C/O Realty | C88: =IFERROR(VLOOKUP(D88,'Master sheet (Clientes)'!A$6:D$747,4,0)," ") -> N-O | D88: Southampton at Newport 20 River Ct, Jersey City, NJ 07310 | E88: 1006 | G88: Vacant | H88: Bathtub reglaze at 8:00am | I88: Felix R Santos | J88: Email | N88: Done
A90: State | B90: MANAGEMENT | C90: BC CLERK | D90: BUILDING / ADDRESS | E90: UNIT / AREA | F90: SIZE | G90: WORKSITE STATUS | H90: JOB DESCRIPTION | I90: JOB AWARDED TO: / TECHS QUANTITY: | J90: REQUEST / P.O / WTN / W.O | K90: BC WORK ORDER / BC ESTIMATE | L90: EXTRAS | M90: SPECIAL NOTES / SEQUENCE | N90: VENDORS DAILY STATUS REPORT
A91: =IFERROR(VLOOKUP(D91,'Master sheet (Clientes)'!A$6:D$747,2,0)," ") -> NJ | B91: =IFERROR(VLOOKUP(D91,'Master sheet (Clientes)'!A$6:D$747,3,0)," ") -> Bozzuto | C91: =IFERROR(VLOOKUP(D91,'Master sheet (Clientes)'!A$6:D$747,4,0)," ") -> N-O | D91: Edge Avenue F 170 Avenue F, Bayonne, NJ 07002 | E91: 426 | H91: Exterior Window Sealing: Inspect the bedroom window to identify potential water-entry points. \ Remove any loose or deteriorated sealant around the window. \ Clean and prepare the affected areas, then apply exterior waterproof sealant as needed around the window frame and building façade to prevent future water intrusion. \ Test the repaired areas for proper sealing. | I91: MVC Cleaning | J91: Email | K91: Estimate 17348 | N91: Done
A92: =IFERROR(VLOOKUP(D92,'Master sheet (Clientes)'!A$6:D$747,2,0)," ") -> NJ | B92: =IFERROR(VLOOKUP(D92,'Master sheet (Clientes)'!A$6:D$747,3,0)," ") -> Skylight | C92: =IFERROR(VLOOKUP(D92,'Master sheet (Clientes)'!A$6:D$747,4,0)," ") -> N-O | D92: The Ashton 2 Ash Street, Jersey City | E92: 414 | G92: Occupied | H92: Preform exterior window seal to Bedroom windows at 9:00am For access, please call Brian 347-235-9152 or Camilio 917-615-6183 | I92: MVC Cleaning | J92: Email | N92: Done
D94: NEWPORT
D95: BC SUPERVISOR: Jhonatan Perez (201) 800-5601 jperez@build-care.com / BC RUNNER: Eduard Bonifacio (551) 242-5958 purchases@build-care.com
A97: State | B97: MANAGEMENT | C97: BC CLERK | D97: BUILDING / ADDRESS | E97: UNIT / AREA | F97: SIZE | G97: WORKSITE STATUS | H97: JOB DESCRIPTION | I97: JOB AWARDED TO: / TECHS QUANTITY: | J97: REQUEST / P.O / WTN / W.O | K97: BC WORK ORDER / BC ESTIMATE | L97: EXTRAS | M97: SPECIAL NOTES / SEQUENCE | N97: VENDORS DAILY STATUS REPORT
A98: =IFERROR(VLOOKUP(D98,'Master sheet (Clientes)'!A$6:D$747,2,0)," ") -> NJ | B98: =IFERROR(VLOOKUP(D98,'Master sheet (Clientes)'!A$6:D$747,3,0)," ") -> C/O Realty | C98: =IFERROR(VLOOKUP(D98,'Master sheet (Clientes)'!A$6:D$747,4,0)," ") -> N-O | D98: Pacific at Newport 25 River Dr S, Jersey City, NJ 07310 | H98: 1 handyman for 5 days Assist the property with handyman tasks work orders / make ready from Monday 08/31/26 through Friday 09/04/26 at 8am Note: send Othoniel Gonzalez | I98: Cuxil Group Ottoniel Gonzales | J98: PO Pending | K98: Estimate 17341 | M98: Until Friday 09/04 | N98: Continue
A99: =IFERROR(VLOOKUP(D99,'Master sheet (Clientes)'!A$6:D$747,2,0)," ") -> NJ | B99: =IFERROR(VLOOKUP(D99,'Master sheet (Clientes)'!A$6:D$747,3,0)," ") -> C/O Realty | C99: =IFERROR(VLOOKUP(D99,'Master sheet (Clientes)'!A$6:D$747,4,0)," ") -> N-O | D99: Pacific at Newport 25 River Dr S, Jersey City, NJ 07310 | H99: 2 daily painters for 6 days Assist the property with painter tasks from Saturday 08/28/26 and Monday 08/31/26 through Friday 09/04/26 at 8am Note: property will provide all the materials and supervision | I99: Cuxil Group David Pineda / Sanai Pliability Luis Garcia | J99: PO Pending | K99: Estimate 17343 | M99: Until Friday 09/04 | N99: Continue
A100: =IFERROR(VLOOKUP(D100,'Master sheet (Clientes)'!A$6:D$747,2,0)," ") -> NJ | B100: =IFERROR(VLOOKUP(D100,'Master sheet (Clientes)'!A$6:D$747,3,0)," ") -> C/O Realty | C100: =IFERROR(VLOOKUP(D100,'Master sheet (Clientes)'!A$6:D$747,4,0)," ") -> N-O | D100: Pacific at Newport 25 River Dr S, Jersey City, NJ 07310 | E100: 610 | F100: 2BDR | G100: Vacant | H100: Continue Renovation: Popcorn ceiling removal / renovation Bathroom / install kitchen backsplash / Paint entire unit incluiding ceiling | I100: Cuxil Group / Sanai Piability | J100: PO Pending | N100: Continue After Flooring
A101: =IFERROR(VLOOKUP(D101,'Master sheet (Clientes)'!A$6:D$747,2,0)," ") -> NJ | B101: =IFERROR(VLOOKUP(D101,'Master sheet (Clientes)'!A$6:D$747,3,0)," ") -> C/O Realty | C101: =IFERROR(VLOOKUP(D101,'Master sheet (Clientes)'!A$6:D$747,4,0)," ") -> N-O | D101: Pacific at Newport 25 River Dr S, Jersey City, NJ 07310 | E101: 610 | F101: 2BDR | G101: Vacant | H101: Continue Full Laundry build-up: Framing | I101: Cuxil Group / Sanai Piability | J101: PO Pending | K101: Estimate 17172 | N101: Continue After Flooring
A102: =IFERROR(VLOOKUP(D102,'Master sheet (Clientes)'!A$6:D$747,2,0)," ") -> NJ | B102: =IFERROR(VLOOKUP(D102,'Master sheet (Clientes)'!A$6:D$747,3,0)," ") -> C/O Realty | C102: =IFERROR(VLOOKUP(D102,'Master sheet (Clientes)'!A$6:D$747,4,0)," ") -> N-O | D102: Pacific at Newport 25 River Dr S, Jersey City, NJ 07310 | E102: 1907 | F102: 1BDR | G102: Vacant | H102: Full laundry room build-up: Framing | I102: Cuxil Group / Sanai Piability Extra de: Jairo Cuxil | J102: PO Pending | K102: Estimate 17168 | N102: Continue After Electrical and Plumber
A103: =IFERROR(VLOOKUP(D103,'Master sheet (Clientes)'!A$6:D$747,2,0)," ") -> NJ | B103: =IFERROR(VLOOKUP(D103,'Master sheet (Clientes)'!A$6:D$747,3,0)," ") -> C/O Realty | C103: =IFERROR(VLOOKUP(D103,'Master sheet (Clientes)'!A$6:D$747,4,0)," ") -> N-O | D103: Atlantic at Newport 31 River Ct, Jersey City, NJ 07310 | E103: 3406 | F103: 1BDR | G103: Vacant | H103: Continue Full laundry build-up: Metal framing | I103: Cuxil Group Demetrio Semeya | J103: PO Pending | K103: Estimate 17368 | N103: Done
A104: =IFERROR(VLOOKUP(D104,'Master sheet (Clientes)'!A$6:D$747,2,0)," ") -> NJ | B104: =IFERROR(VLOOKUP(D104,'Master sheet (Clientes)'!A$6:D$747,3,0)," ") -> C/O Realty | C104: =IFERROR(VLOOKUP(D104,'Master sheet (Clientes)'!A$6:D$747,4,0)," ") -> N-O | D104: Atlantic at Newport 31 River Ct, Jersey City, NJ 07310 | E104: 2707 | F104: 1BDR | G104: Vacant | H104: 1 handyman make ready at 8:00am Note: The reglaze is scheduled in the late afternoon | I104: Sanai Pliability Lorenzo Vaquiax | J104: PO Pending | M104: reglaze same day | N104: Done
A105: =IFERROR(VLOOKUP(D105,'Master sheet (Clientes)'!A$6:D$747,2,0)," ") -> NJ | B105: =IFERROR(VLOOKUP(D105,'Master sheet (Clientes)'!A$6:D$747,3,0)," ") -> C/O Realty | C105: =IFERROR(VLOOKUP(D105,'Master sheet (Clientes)'!A$6:D$747,4,0)," ") -> N-O | D105: Atlantic at Newport 31 River Ct, Jersey City, NJ 07310 | E105: 2609 | F105: 3BDR | G105: Vacant | H105: 1 handyman make ready at 8:00am Note: The reglaze is scheduled in the late afternoon | I105: Sanai Pliability Sergio Chex | J105: PO Pending | M105: reglaze same day | N105: Done
A106: =IFERROR(VLOOKUP(D106,'Master sheet (Clientes)'!A$6:D$747,2,0)," ") -> NJ | B106: =IFERROR(VLOOKUP(D106,'Master sheet (Clientes)'!A$6:D$747,3,0)," ") -> C/O Realty | C106: =IFERROR(VLOOKUP(D106,'Master sheet (Clientes)'!A$6:D$747,4,0)," ") -> N-O | D106: Parkside West at Newport 40 Newport Parkway, Jersey City, NJ | H106: 1 handyman for 20 days Job: assist the property with handyman work work orders / make ready Schedule from Tuesday 08/25/26 through Saturday 08/29/26 Monday 08/31/26 through Friday 09/04/26 Tuesday 09/08/26 through Saturday 09/12/26 Monday 09/14/26 through Friday 09/18/26 at 8am Note: send Geovanny Saldivar Note: handyman will not work Monday 09/07/26 due to Labor Day holiday | I106: Cuxil Group Giovanny Saldivar | J106: PO Pending | M106: Until Fri 09/18 | N106: Continue
A107: =IFERROR(VLOOKUP(D107,'Master sheet (Clientes)'!A$6:D$747,2,0)," ") -> NJ | B107: =IFERROR(VLOOKUP(D107,'Master sheet (Clientes)'!A$6:D$747,3,0)," ") -> C/O Realty | C107: =IFERROR(VLOOKUP(D107,'Master sheet (Clientes)'!A$6:D$747,4,0)," ") -> N-O | D107: Parkside East at Newport 30 Newport Parkway, Jersey City, NJ | H107: 1 handyman for 20 days Job: assist the property with handyman work work orders / make ready Schedule from Tuesday 08/25/26 through Saturday 08/29/26 Monday 08/31/26 through Friday 09/04/26 Tuesday 09/08/26 through Saturday 09/12/26 Monday 09/14/26 through Friday 09/18/26 at 8am Note: send Oscar Monasterio Note: handyman will not work Monday 09/07/26 due to Labor Day holiday | I107: Cuxil Group Oscar Monasterio | J107: PO Pending | M107: Until Fri 09/18 | N107: Continue
A108: =IFERROR(VLOOKUP(D108,'Master sheet (Clientes)'!A$6:D$747,2,0)," ") -> NJ | B108: =IFERROR(VLOOKUP(D108,'Master sheet (Clientes)'!A$6:D$747,3,0)," ") -> C/O Realty | C108: =IFERROR(VLOOKUP(D108,'Master sheet (Clientes)'!A$6:D$747,4,0)," ") -> N-O | D108: East Hampton at Newport 30 River Ct, Jersey City, NJ 07310 | E108: 1212 | F108: 1BDR | G108: Vacant | H108: Continue Laundry room build-up ONLY | I108: Cuxil Group Oscar Monasterio | J108: PO Pending | K108: Estimate 17170 | N108: Continue
A109: =IFERROR(VLOOKUP(D109,'Master sheet (Clientes)'!A$6:D$747,2,0)," ") -> NJ | B109: =IFERROR(VLOOKUP(D109,'Master sheet (Clientes)'!A$6:D$747,3,0)," ") -> C/O Realty | C109: =IFERROR(VLOOKUP(D109,'Master sheet (Clientes)'!A$6:D$747,4,0)," ") -> N-O | D109: East Hampton at Newport 30 River Ct, Jersey City, NJ 07310 | E109: 1705 | F109: 2BDR | G109: Vacant | H109: 1 handyman for 2 days make ready - Monday and Tuesday 08/31-09/01 | I109: Cuxil Group Juan Garcia | J109: PO Pending | N109: Continue
A110: =IFERROR(VLOOKUP(D110,'Master sheet (Clientes)'!A$6:D$747,2,0)," ") -> NJ | B110: =IFERROR(VLOOKUP(D110,'Master sheet (Clientes)'!A$6:D$747,3,0)," ") -> C/O Realty | C110: =IFERROR(VLOOKUP(D110,'Master sheet (Clientes)'!A$6:D$747,4,0)," ") -> N-O | D110: East Hampton at Newport 30 River Ct, Jersey City, NJ 07310 | E110: 1414 | G110: Vacant | H110: Bathroom Ceramic Tile Repair: Demo and discard (5) damaged ceramic tiles located on the bathroom floor.\ Prep and perform minor subfloor repairs prior to new ceramic tile installation.\ Provide and install (5) new 13 in. x 13 in. ceramic tiles.\ Apply grout to newly installed tiles. / Last minute request assigned by Casey | I110: Cuxil Group / Sanai Pliability | J110: PO Pending | K110: Estimate 17374 | N110: Continue
A111: =IFERROR(VLOOKUP(D111,'Master sheet (Clientes)'!A$6:D$747,2,0)," ") -> NJ | B111: =IFERROR(VLOOKUP(D111,'Master sheet (Clientes)'!A$6:D$747,3,0)," ") -> C/O Realty | C111: =IFERROR(VLOOKUP(D111,'Master sheet (Clientes)'!A$6:D$747,4,0)," ") -> N-O | D111: Waterside Square South at Newport 35 River Dr S, Jersey City, NJ 07310 | E111: Garage 1st Floor | H111: Walls Painting: Remove and discard 2 signs from walls \ Perform minor scraping of existing peeling paint \ Apply two (2) coats of paint using Iron Mountain by Benjamin Moore in semi-gloss \ Size of the walls: 8 ft x 9 ft high \ 9 ft x 9 ft high \ 8 ft x 9 ft high \ Top: 9 ft x 4 ft. | I111: Cuxil Group Edgar Lool / Sanai Pliability Santiago Chanchavac | J111: PO Pending | K111: Estimate 17041 | N111: Done
A112: =IFERROR(VLOOKUP(D112,'Master sheet (Clientes)'!A$6:D$747,2,0)," ") -> NJ | B112: =IFERROR(VLOOKUP(D112,'Master sheet (Clientes)'!A$6:D$747,3,0)," ") -> C/O Realty | C112: =IFERROR(VLOOKUP(D112,'Master sheet (Clientes)'!A$6:D$747,4,0)," ") -> N-O | D112: Aquablu at Newport 110 River Dr S, Jersey City, NJ 07310 | E112: 903 | G112: Vacant | H112: Kitchen countertop reduction | I112: Cuxil Group Edgar Cuxil / Sanai Pliability Jairo Cuxil | J112: PO Pending | K112: Estimate 17364 | N112: Done
A113: =IFERROR(VLOOKUP(D113,'Master sheet (Clientes)'!A$6:D$747,2,0)," ") -> NJ | B113: =IFERROR(VLOOKUP(D113,'Master sheet (Clientes)'!A$6:D$747,3,0)," ") -> C/O Realty | C113: =IFERROR(VLOOKUP(D113,'Master sheet (Clientes)'!A$6:D$747,4,0)," ") -> N-O | D113: Riverside at Newport 1 River Ct, Jersey City, NJ 07310 | E113: 2905 | F113: 2BDR | G113: Vacant | H113: 1 handyman for 2 days make ready - Monday and Tuesday 08/31-09/01 | I113: Sanai Pliability Elmer Morales | J113: PO Pending | N113: Continue
A114: =IFERROR(VLOOKUP(D114,'Master sheet (Clientes)'!A$6:D$747,2,0)," ") -> NJ | B114: =IFERROR(VLOOKUP(D114,'Master sheet (Clientes)'!A$6:D$747,3,0)," ") -> C/O Realty | C114: =IFERROR(VLOOKUP(D114,'Master sheet (Clientes)'!A$6:D$747,4,0)," ") -> N-O | D114: Riverside at Newport 1 River Ct, Jersey City, NJ 07310 | E114: Garage 2nd floor | H114: 1 handyman for 10 days Assist the property with bathroom vanities repair from Monday 08/24/26 through Friday 08/28/26 - Monday 08/31/26 through Friday 09/04/26 at 8:30am Note: property to provide all materials and supervision Note: send David Pineda Must contact Karan upon arrival | I114: Cuxil Group / Sanai Pliability | J114: PO Pending | M114: Until Fri 09/04 | N114: rescheduled starting Tuesday
A115: =IFERROR(VLOOKUP(D115,'Master sheet (Clientes)'!A$6:D$747,2,0)," ") -> NJ | B115: =IFERROR(VLOOKUP(D115,'Master sheet (Clientes)'!A$6:D$747,3,0)," ") -> C/O Realty | C115: =IFERROR(VLOOKUP(D115,'Master sheet (Clientes)'!A$6:D$747,4,0)," ") -> N-O | D115: Riverside at Newport 1 River Ct, Jersey City, NJ 07310 | E115: Hallways | H115: Provide (2) full-time painters for (2) day to assist the property with painter's tasks Monday and Tuesday. 08/31/26-09/01/26 | I115: Cuxil Group Yovanny Olgadez / Sanai Pliability Josue Olgadez | J115: PO Pending | K115: Estimate 17304 | M115: Until Tues 09/01 | N115: Continue
A116: =IFERROR(VLOOKUP(D116,'Master sheet (Clientes)'!A$6:D$747,2,0)," ") -> NJ | B116: =IFERROR(VLOOKUP(D116,'Master sheet (Clientes)'!A$6:D$747,3,0)," ") -> C/O Realty | C116: =IFERROR(VLOOKUP(D116,'Master sheet (Clientes)'!A$6:D$747,4,0)," ") -> N-O | D116: Riverside at Newport 1 River Ct, Jersey City, NJ 07310 | E116: Storage Room | H116: Continue Repair: Install new property provided ptac unit -Build drain line for back of the ptac unit, to allow water to travel away from the wall -Replace approximately 10 gfci outlets and 4 light switches (Property to provide materials) -Install new property provided outlet and switch covers -Install property provided appliances, toilet, and bathtub on wooden dollies -Paint exterior wall of the training room using white semigloss paint Wall: 35ft long x 8ft high -Purchase and install a tv mounting bracket for a 40” tv -Install a 40” property provided tv. -Build two dollies for washer/dryer machines 26”x24” with plywood and 4 wheels each. -Build drainage with pvc pipes for training purposes for - showerpan - toilet - vanity sink - install copper including pipes for hot and cold water for training purposes only Note: all the pipe installations will not be connected to any water or drainage lines Notes: *Property to provide appliances, electrical outlets, switches, and covers *Debris to be disposed of in property provided dumpster. | I116: Cuxil Group / Sanai Pliability | J116: PO Pending | K116: Estimate 16991 | N116: rescheduled starting Tuesday
A117: =IFERROR(VLOOKUP(D117,'Master sheet (Clientes)'!A$6:D$747,2,0)," ") -> NJ | B117: =IFERROR(VLOOKUP(D117,'Master sheet (Clientes)'!A$6:D$747,3,0)," ") -> C/O Realty | C117: =IFERROR(VLOOKUP(D117,'Master sheet (Clientes)'!A$6:D$747,4,0)," ") -> N-O | D117: Bisby at Newport 30 Park Lane North Jersey City, NJ 07310 | E117: 211 | G117: Occupied | H117: Drywall Repair: -Install new drywall to seal demo areas located on bathroom ceiling and closet wall. -Tape, spackle, sand, and prime newly installed drywall. -Perform plaster repairs to one scratch located on closet wall (right side) -Paint repaired ceiling areas using paint, matching property specs. at 11AM as per tenant's request. | I117: Cuxil Group Demetrio Semeya | J117: PO Pending | K117: Estimate 17363 | N117: Done
A118: =IFERROR(VLOOKUP(D118,'Master sheet (Clientes)'!A$6:D$747,2,0)," ") -> NJ | B118: =IFERROR(VLOOKUP(D118,'Master sheet (Clientes)'!A$6:D$747,3,0)," ") -> C/O Realty | C118: =IFERROR(VLOOKUP(D118,'Master sheet (Clientes)'!A$6:D$747,4,0)," ") -> N-O | D118: Roosevelt House at Hamilton Park 180 10th St, Jersey City, NJ 07302 | E118: 607 | G118: Occupied | H118: Glass Window Replacement: Seal the window opening with plywood as needed while repairs are being performed Note: To Work with Pereira Glass (Joshua) | I118: Sanai Pliability Wilber Ramirez | J118: PO Pending | K118: Estimate 17291 | M118: Technician was onsite to assist pereira glass but no plywood installation was needed. | N118: Done
A119: =IFERROR(VLOOKUP(D119,'Master sheet (Clientes)'!A$6:D$747,2,0)," ") -> NJ | B119: =IFERROR(VLOOKUP(D119,'Master sheet (Clientes)'!A$6:D$747,3,0)," ") -> C/O Realty | C119: =IFERROR(VLOOKUP(D119,'Master sheet (Clientes)'!A$6:D$747,4,0)," ") -> N-O | D119: Roosevelt House at Hamilton Park 180 10th St, Jersey City, NJ 07302 | H119: 1 handyman work for 15 days Assist the property with handyman tasks - work order / turns Sunday 08/16/26 through Thursday 08/20/26 - Sunday 08/23/26 through Thursday 08/27/26 Sunday 08/30/26 through Thursday 09/03/26 from 9am to 5:30pm Note: send Michael Garcia | I119: Sanai pliability Mayco Garcia | J119: PO Pending | K119: Estimate 17232 | M119: Until Thu 09/03 | N119: Continue
A121: State | B121: MANAGEMENT | C121: BC CLERK | D121: BUILDING / ADDRESS | E121: UNIT / AREA | F121: SIZE | G121: WORKSITE STATUS | H121: JOB DESCRIPTION | I121: JOB AWARDED TO: / TECHS QUANTITY: | J121: REQUEST / P.O / WTN / W.O | K121: BC WORK ORDER / BC ESTIMATE | L121: EXTRAS | M121: SPECIAL NOTES / SEQUENCE | N121: VENDORS DAILY STATUS REPORT
A122: =IFERROR(VLOOKUP(D122,'Master sheet (Clientes)'!A$6:D$747,2,0)," ") -> NJ | B122: =IFERROR(VLOOKUP(D122,'Master sheet (Clientes)'!A$6:D$747,3,0)," ") -> C/O Realty | C122: =IFERROR(VLOOKUP(D122,'Master sheet (Clientes)'!A$6:D$747,4,0)," ") -> N-O | D122: Pacific at Newport 25 River Dr S, Jersey City, NJ 07310 | E122: 1907 | F122: 1BDR | G122: Vacant | H122: Full laundry room build-up: Electric work | I122: Cuxil Group electricity | J122: PO Pending | K122: Estimate 17168
A124: State | B124: MANAGEMENT | C124: BC CLERK | D124: BUILDING / ADDRESS | E124: UNIT / AREA | F124: SIZE | G124: WORKSITE STATUS | H124: JOB DESCRIPTION | I124: JOB AWARDED TO: / TECHS QUANTITY: | J124: REQUEST / P.O / WTN / W.O | K124: BC WORK ORDER / BC ESTIMATE | L124: EXTRAS | M124: SPECIAL NOTES / SEQUENCE | N124: VENDORS DAILY STATUS REPORT
...

Sheet Tue, Sep 01
A1: BuildCare SCHEDULE TUESDAY, SEPTEMBER 01 / 2026
A3: SUPERVISOR ON CALL NJ: Sebastian Lopez (551) 202-4443 jlopez@build-care.com
A4: CREWS ASSIGNED BY DEFAULT ON CALL: DVM - Atlas Techs / Atlas Cleaning - HG Services
A5: CREWS CONFIRMED BY THE ON CALL: ????
A6: BC MEMBERS OFF/VACATIONS:
D9: STATE OF NEW JERSEY
D11: WATERFRONT AREA (Fort Lee - Edgewater - Cliffside Park - Fairview - North Bergen - West New York - Weehawken - North Hoboken "8th Street Up" )
D12: BC SUPERVISOR: Carlos Perez (862) 383-3884 cperez@build-care.com BC SUPERVISOR/RUNNER: Juan Zapata (551) 202-4443 jzapata@build-care.com
A14: State | B14: MANAGEMENT | C14: BC CLERK | D14: BUILDING / ADDRESS | E14: UNIT / AREA | F14: SIZE | G14: WORKSITE STATUS | H14: JOB DESCRIPTION | I14: JOB AWARDED TO: / TECHS QUANTITY: | J14: REQUEST / P.O / WTN / W.O | K14: BC WORK ORDER / BC ESTIMATE | L14: EXTRAS | M14: SPECIAL NOTES / SEQUENCE | N14: VENDORS DAILY STATUS REPORT
A15: =IFERROR(VLOOKUP(D15,'Master sheet (Clientes)'!A$6:D$747,2,0)," ") -> NJ | B15: =IFERROR(VLOOKUP(D15,'Master sheet (Clientes)'!A$6:D$747,3,0)," ") -> Vivmark Residential | C15: =IFERROR(VLOOKUP(D15,'Master sheet (Clientes)'!A$6:D$747,4,0)," ") -> N-O | D15: Avalon at Edgewater II New Building (Russell). | E15: 104 | F15: 1BDR | G15: Occupeid | H15: Continue Repair openings that were made by other after suffering leak damage -Repairs will be in the coat closet, laundry closet, living room, hallway, bedroom, and bathroom walls. In the bathroom we will have to redo the bathroom tiles area is approximately 8x10 tiles will have to be removed, and sub floor repaired before installing new tiles at 9:00am The building will provide paint Bc to provide all other materials and labor needed to complete the job. For access, please call Christian 201-705-0879 or Alex 201-713-8719 | I15: AJ Canas Solutions Willian Alvarez / Marlon | J15: Email | N15: Continue
A16: =IFERROR(VLOOKUP(D16,'Master sheet (Clientes)'!A$6:D$747,2,0)," ") -> NJ | B16: =IFERROR(VLOOKUP(D16,'Master sheet (Clientes)'!A$6:D$747,3,0)," ") -> Vivmark Residential | C16: =IFERROR(VLOOKUP(D16,'Master sheet (Clientes)'!A$6:D$747,4,0)," ") -> N-O | D16: Avalon at Edgewater II New Building (Russell). | E16: 155 | G16: Occupied | H16: Continue Left side bedroom bathroom tile floor to be demoed, sub floor fixed, install new tiles, and grout area is 9ft x 6ft. at 9am Bc to provide all materials and labor needed to complete the job. For access, please call Christian 201-705-0879 or Alex 201-713-8719 | I16: AJ Canas Solutions Ricardo / Carlos | J16: Email | N16: Continue
A17: =IFERROR(VLOOKUP(D17,'Master sheet (Clientes)'!A$6:D$747,2,0)," ") -> NJ | B17: =IFERROR(VLOOKUP(D17,'Master sheet (Clientes)'!A$6:D$747,3,0)," ") -> Vivmark Residential | C17: =IFERROR(VLOOKUP(D17,'Master sheet (Clientes)'!A$6:D$747,4,0)," ") -> N-O | D17: Avalon at Edgewater II New Building (Russell). | E17: 242 | G17: Occupied | H17: Repair bathroom ceiling from opening made by others at 9am The building will provide the paint. Bc to provide all materials and labor needed to complete the job. For access, please call Christian 201-705-0879 or Alex 201-713-8719 | I17: AJ Canas Solutions Javier | J17: Email | N17: Done
A18: =IFERROR(VLOOKUP(D18,'Master sheet (Clientes)'!A$6:D$747,2,0)," ") -> NJ | B18: =IFERROR(VLOOKUP(D18,'Master sheet (Clientes)'!A$6:D$747,3,0)," ") -> Skylight | C18: =IFERROR(VLOOKUP(D18,'Master sheet (Clientes)'!A$6:D$747,4,0)," ") -> N-O | D18: The Sterling 2055 Center Ave, Fort Lee, NJ 07024 | E18: 5D | G18: Occupied | H18: Repair opening made by others and install missing parquet NOTE: BC to provide plastic drop, spackle, rosin paper, wall paint, blue tape, metal for framing, drywall, primer grip, sanding sponge, floor trim and other materials and labor needed to complete the job. / For access, please call Steve (646) 299-5888 or Jeffery 929-218-9732 | I18: AJ Canas Solutions William dias. | J18: Email | N18: Continue
A20: State | B20: MANAGEMENT | C20: BC CLERK | D20: BUILDING / ADDRESS | E20: UNIT / AREA | F20: SIZE | G20: WORKSITE STATUS | H20: JOB DESCRIPTION | I20: JOB AWARDED TO: / TECHS QUANTITY: | J20: REQUEST / P.O / WTN / W.O | K20: BC WORK ORDER / BC ESTIMATE | L20: EXTRAS | M20: SPECIAL NOTES / SEQUENCE | N20: VENDORS DAILY STATUS REPORT
A21: =IFERROR(VLOOKUP(D21,'Master sheet (Clientes)'!A$6:D$747,2,0)," ") -> NJ | B21: =IFERROR(VLOOKUP(D21,'Master sheet (Clientes)'!A$6:D$747,3,0)," ") -> Skylight | C21: =IFERROR(VLOOKUP(D21,'Master sheet (Clientes)'!A$6:D$747,4,0)," ") -> N-O | D21: Infinity at Edgewater 340 Old River Rd, Edgewater, NJ 07020 | E21: 609 | F21: 1BDR | G21: Vacant | H21: Second Request: Paint Unit (apply scent, including all ceilings; cover carpets and floors) and Unit Cleaning at 8:00am | I21: Atlas Douglas Espinal - Jesus Alvarado | J21: Email | N21: Paint done
A23: State | B23: MANAGEMENT | C23: BC CLERK | D23: BUILDING / ADDRESS | E23: UNIT / AREA | F23: SIZE | G23: WORKSITE STATUS | H23: JOB DESCRIPTION | I23: JOB AWARDED TO: / TECHS QUANTITY: | J23: REQUEST / P.O / WTN / W.O | K23: BC WORK ORDER / BC ESTIMATE | L23: EXTRAS | M23: SPECIAL NOTES / SEQUENCE | N23: VENDORS DAILY STATUS REPORT
A24: =IFERROR(VLOOKUP(D24,'Master sheet (Clientes)'!A$6:D$747,2,0)," ") -> NJ | B24: =IFERROR(VLOOKUP(D24,'Master sheet (Clientes)'!A$6:D$747,3,0)," ") -> No Charge / Courtesy Job | C24: =IFERROR(VLOOKUP(D24,'Master sheet (Clientes)'!A$6:D$747,4,0)," ") -> N/A | D24: 1114 92nd St North Bergen, NJ 07047 | H24: Continue demolish the kitchen countertops on the 1st floor the top row above the ones demolished by mistake including the soffit. | I24: Sanai Pliability Elmer Morales / Delfino Cuxil | J24: Email | M24: No Charge / Courtesy job for Christian Glaser | N24: Continue
A26: State | B26: MANAGEMENT | C26: BC CLERK | D26: BUILDING / ADDRESS | E26: UNIT / AREA | F26: SIZE | G26: WORKSITE STATUS | H26: JOB DESCRIPTION | I26: JOB AWARDED TO: / TECHS QUANTITY: | J26: REQUEST / P.O / WTN / W.O | K26: BC WORK ORDER / BC ESTIMATE | L26: EXTRAS | M26: SPECIAL NOTES / SEQUENCE | N26: VENDORS DAILY STATUS REPORT
A27: =IFERROR(VLOOKUP(D27,'Master sheet (Clientes)'!A$6:D$747,2,0)," ") -> NJ | B27: =IFERROR(VLOOKUP(D27,'Master sheet (Clientes)'!A$6:D$747,3,0)," ") -> Vivmark Residential | C27: =IFERROR(VLOOKUP(D27,'Master sheet (Clientes)'!A$6:D$747,4,0)," ") -> A-V | D27: The Landings at Port Imperial Apartment 4 Ave at Port Imperial, West New York, NJ 07093. | E27: 1101 | F27: 3BDR | G27: Vacant | H27: Unit cleaning at 8:00 am | I27: YL Cleaning | J27: Email | N27: Done
A28: =IFERROR(VLOOKUP(D28,'Master sheet (Clientes)'!A$6:D$747,2,0)," ") -> NJ | B28: =IFERROR(VLOOKUP(D28,'Master sheet (Clientes)'!A$6:D$747,3,0)," ") -> Greystar | C28: =IFERROR(VLOOKUP(D28,'Master sheet (Clientes)'!A$6:D$747,4,0)," ") -> A-V | D28: The Grand 508 51st St, West New York, NJ 07093 | E28: 407 | F28: 1BDR | G28: Vacant | H28: Unit cleaning at 8:00 am | I28: YL Cleaning | J28: Email | N28: Done
A29: =IFERROR(VLOOKUP(D29,'Master sheet (Clientes)'!A$6:D$747,2,0)," ") -> NJ | B29: =IFERROR(VLOOKUP(D29,'Master sheet (Clientes)'!A$6:D$747,3,0)," ") -> Vivmark Residential | C29: =IFERROR(VLOOKUP(D29,'Master sheet (Clientes)'!A$6:D$747,4,0)," ") -> N-O | D29: Avalon at Edgewater II New Building (Russell). | E29: 104 | F29: 1BDR | G29: Occupeid | H29: Unit Cleaning after repair / Last minute assigned by Carlos | I29: YL Cleaning | J29: Email | N29: Done
D31: SOUTH HOBOKEN "7th Street down" - JERSEY CITY - BAYONNE
D32: JERSEY CITY - BC SUPERVISOR: Carlos Perez (862) 383-3884 cperez@build-care.com - BC RUNNER: Juan Sebastian Salazar (862) 394-6010 jssalazar@build-care.com
A34: State | B34: MANAGEMENT | C34: BC CLERK | D34: BUILDING / ADDRESS | E34: UNIT / AREA | F34: SIZE | G34: WORKSITE STATUS | H34: JOB DESCRIPTION | I34: JOB AWARDED TO: / TECHS QUANTITY: | J34: REQUEST / P.O / WTN / W.O | K34: BC WORK ORDER / BC ESTIMATE | L34: EXTRAS | M34: SPECIAL NOTES / SEQUENCE | N34: VENDORS DAILY STATUS REPORT
A35: =IFERROR(VLOOKUP(D35,'Master sheet (Clientes)'!A$6:D$747,2,0)," ") -> NJ | B35: =IFERROR(VLOOKUP(D35,'Master sheet (Clientes)'!A$6:D$747,3,0)," ") -> Skylight | C35: =IFERROR(VLOOKUP(D35,'Master sheet (Clientes)'!A$6:D$747,4,0)," ") -> N-O | D35: Grand Adams Apartments 300 Grand St, Hoboken, NJ 07030 | H35: 1 Daily Handyman to work with the maintenance staff 8hrs shift to cover multiple properties under the instructions of the service general manager Upon Arrival Call Orville (646) 984-3306 from 9:00am to 5:00pm Monday to Friday until further notice Starting Tuesday 02/26/2025 | I35: Cuxil Group Eduardo Garcia | J35: Email | M35: until further notice | N35: Continue
A36: =IFERROR(VLOOKUP(D36,'Master sheet (Clientes)'!A$6:D$747,2,0)," ") -> NJ | B36: =IFERROR(VLOOKUP(D36,'Master sheet (Clientes)'!A$6:D$747,3,0)," ") -> Skylight | C36: =IFERROR(VLOOKUP(D36,'Master sheet (Clientes)'!A$6:D$747,4,0)," ") -> N-O | D36: Grand Adams Apartments 300 Grand St, Hoboken, NJ 07030 | H36: 1 Daily handyman for 8hrs shift to assist the property with internal tasks from Monday to Friday until further notice NOTE: Please Report to Christina 973-776-4602 | I36: Cuxil Group Marcos Garcia | J36: Email | M36: until further notice | N36: Continue
A37: =IFERROR(VLOOKUP(D37,'Master sheet (Clientes)'!A$6:D$747,2,0)," ") -> NJ | B37: =IFERROR(VLOOKUP(D37,'Master sheet (Clientes)'!A$6:D$747,3,0)," ") -> Optimum | C37: =IFERROR(VLOOKUP(D37,'Master sheet (Clientes)'!A$6:D$747,4,0)," ") -> A-V | D37: 25 Kensington Ave Jersey City, NJ 07304 | E37: Medical Office Suite #106 | G37: Occupied | H37: Continue Repair all walls / Paint the entire commercial space Color change at 8:30am NOTE: **The reception area, the room with the file cabinet, will not be painted.** / Please contact super Eduardo for access: 551-260-0514 | I37: Sanai Pliability Eddy Cumes / Alexander Polanco | J37: Email | N37: Done
A39: State | B39: MANAGEMENT | C39: BC CLERK | D39: BUILDING / ADDRESS | E39: UNIT / AREA | F39: SIZE | G39: WORKSITE STATUS | H39: JOB DESCRIPTION | I39: JOB AWARDED TO: / TECHS QUANTITY: | J39: REQUEST / P.O / WTN / W.O | K39: BC WORK ORDER / BC ESTIMATE | L39: EXTRAS | M39: SPECIAL NOTES / SEQUENCE | N39: VENDORS DAILY STATUS REPORT
A40: =IFERROR(VLOOKUP(D40,'Master sheet (Clientes)'!A$6:D$747,2,0)," ") -> NJ | B40: =IFERROR(VLOOKUP(D40,'Master sheet (Clientes)'!A$6:D$747,3,0)," ") -> Rose Associates | C40: =IFERROR(VLOOKUP(D40,'Master sheet (Clientes)'!A$6:D$747,4,0)," ") -> A-V | D40: VYV Apartments North and South 474 Warren St, Jersey City, NJ 07302. | H40: 1 Daily Handyman Service: Provide a full-time daily handyman to assist the property with make-ready orders from 8:00 am to 4:30 pm. 5 Days per week Monday to Friday Starting Monday 08/03/26 to Friday 10/16/2026 | I40: Atlas Alexis Gomez | J40: Email | M40: 5 days per week Until 10/16 | N40: Continue
A41: =IFERROR(VLOOKUP(D41,'Master sheet (Clientes)'!A$6:D$747,2,0)," ") -> NJ | B41: =IFERROR(VLOOKUP(D41,'Master sheet (Clientes)'!A$6:D$747,3,0)," ") -> Greystar | C41: =IFERROR(VLOOKUP(D41,'Master sheet (Clientes)'!A$6:D$747,4,0)," ") -> A-V | D41: Liberty Bay Club Apartments 190 W 54th St, Bayonne, NJ 07002 | E41: 239 | F41: 2BDR | G41: Vacant | H41: Paint unit and cleaning at 8:0am Note: Property will provide the paint. | I41: Atlas Douglas Espinal - Jesus Alvarado | J41: Email | N41: Paint done
A42: =IFERROR(VLOOKUP(D42,'Master sheet (Clientes)'!A$6:D$747,2,0)," ") -> NJ | B42: =IFERROR(VLOOKUP(D42,'Master sheet (Clientes)'!A$6:D$747,3,0)," ") -> Greystar | C42: =IFERROR(VLOOKUP(D42,'Master sheet (Clientes)'!A$6:D$747,4,0)," ") -> A-V | D42: Liberty Bay Club Apartments 190 W 54th St, Bayonne, NJ 07002 | E42: 147 | F42: 1BDR | G42: Vacant | H42: Paint unit and cleaning at 8:0am Note: Property will provide the paint. | I42: Atlas Douglas Espinal - Jesus Alvarado | J42: Email | N42: Paint done
A43: =IFERROR(VLOOKUP(D43,'Master sheet (Clientes)'!A$6:D$747,2,0)," ") -> NJ | B43: =IFERROR(VLOOKUP(D43,'Master sheet (Clientes)'!A$6:D$747,3,0)," ") -> Vivmark Residential | C43: =IFERROR(VLOOKUP(D43,'Master sheet (Clientes)'!A$6:D$747,4,0)," ") -> A-V | D43: Hudson Point Apartments 131 Dudley St Ste Off, Jersey City, NJ 07302. | E43: 415 | F43: 1BDR | G43: Vacant | H43: Paint unit and Cleaning same day at 8:00 am NOTE: The building will provide the Paint For access, Please call Colin 1(973) 255-8682 or Eli 917-442-0088 | I43: Atlas Javier Santiago | J43: Paint WTN 86508201 | N43: Paint done
A44: =IFERROR(VLOOKUP(D44,'Master sheet (Clientes)'!A$6:D$747,2,0)," ") -> NJ | B44: =IFERROR(VLOOKUP(D44,'Master sheet (Clientes)'!A$6:D$747,3,0)," ") -> Vivmark Residential | C44: =IFERROR(VLOOKUP(D44,'Master sheet (Clientes)'!A$6:D$747,4,0)," ") -> A-V | D44: 70 Greene Apartments 70 Greene St, Jersey City, NJ 07302. | E44: 3107 | F44: 1BDR | G44: Vacant | H44: Paint unit at 8:00 am | I44: Atlas Elder Velasquez | J44: WTN 86388866 | N44: Paint done
A46: State | B46: MANAGEMENT | C46: BC CLERK | D46: BUILDING / ADDRESS | E46: UNIT / AREA | F46: SIZE | G46: WORKSITE STATUS | H46: JOB DESCRIPTION | I46: JOB AWARDED TO: / TECHS QUANTITY: | J46: REQUEST / P.O / WTN / W.O | K46: BC WORK ORDER / BC ESTIMATE | L46: EXTRAS | M46: SPECIAL NOTES / SEQUENCE | N46: VENDORS DAILY STATUS REPORT
A47: =IFERROR(VLOOKUP(D47,'Master sheet (Clientes)'!A$6:D$747,2,0)," ") -> NJ | B47: =IFERROR(VLOOKUP(D47,'Master sheet (Clientes)'!A$6:D$747,3,0)," ") -> Bozzuto | C47: =IFERROR(VLOOKUP(D47,'Master sheet (Clientes)'!A$6:D$747,4,0)," ") -> N-O | D47: Vantage Collection 1 Park View Ave, Jersey City, NJ 07302 | E47: PH38 | G47: Occupied | H47: Continue Door and shelving Installation: Remove and demo the existing pocket door, including the frame. \ Perform all necessary repairs required to install a Buildcare-provided 36" x 80" metal frame. \ Install the property-provided door. \ Install Buildcare-provided door hardware. \ Paint the wall, door, and frame using property-provided paint. \ Install the Buildcare-provided closet shelving system that was previously removed by the client. | I47: Alluda Anibal Yojero / Misael Yojero | J47: Email | K47: Estimate 15942 | M47: 4 Handys quoted | N47: Done
A49: State | B49: MANAGEMENT | C49: BC CLERK | D49: BUILDING / ADDRESS | E49: UNIT / AREA | F49: SIZE | G49: WORKSITE STATUS | H49: JOB DESCRIPTION | I49: JOB AWARDED TO: / TECHS QUANTITY: | J49: REQUEST / P.O / WTN / W.O | K49: BC WORK ORDER / BC ESTIMATE | L49: EXTRAS | M49: SPECIAL NOTES / SEQUENCE | N49: VENDORS DAILY STATUS REPORT
A50: =IFERROR(VLOOKUP(D50,'Master sheet (Clientes)'!A$6:D$747,2,0)," ") -> NJ | B50: =IFERROR(VLOOKUP(D50,'Master sheet (Clientes)'!A$6:D$747,3,0)," ") -> Bozzuto | C50: =IFERROR(VLOOKUP(D50,'Master sheet (Clientes)'!A$6:D$747,4,0)," ") -> N-O | D50: Birch House 49 Fisk St, Jersey City, NJ 07305 | E50: 102 | F50: 1BDR | G50: Vacant | H50: Paint unit and Same-day cleaning at 8:00 am | I50: DVM Celestino Luc | J50: Email | M50: Same-day clean | N50: Paint done
A51: =IFERROR(VLOOKUP(D51,'Master sheet (Clientes)'!A$6:D$747,2,0)," ") -> NJ | B51: =IFERROR(VLOOKUP(D51,'Master sheet (Clientes)'!A$6:D$747,3,0)," ") -> Greystar | C51: =IFERROR(VLOOKUP(D51,'Master sheet (Clientes)'!A$6:D$747,4,0)," ") -> A-V | D51: Liberty Bay Club Apartments 190 W 54th St, Bayonne, NJ 07002 | E51: 109 | F51: 1BDR | G51: Vacant | H51: Paint unit and cleaning at 8:0am Note: Property will provide the paint. | I51: DVM Ignacio Luc | J51: Email | N51: Paint done
A52: =IFERROR(VLOOKUP(D52,'Master sheet (Clientes)'!A$6:D$747,2,0)," ") -> NJ | B52: =IFERROR(VLOOKUP(D52,'Master sheet (Clientes)'!A$6:D$747,3,0)," ") -> Greystar | C52: =IFERROR(VLOOKUP(D52,'Master sheet (Clientes)'!A$6:D$747,4,0)," ") -> A-V | D52: The Greyson 25 Cottage St Jersey City, NJ 07306 | E52: 604 | G52: Occupied | H52: Remove base board and Cut drywall 1’x4’ in kitchen area. - Install new drywall and insulation. - Tape, spackle, sand, prime, and paint repaired area.at 9:00 am For access call Raul:+1 (551) 556-8864 | I52: DVM Angel Davila | J52: Email | M52: Note: we only provide the easy sand 20, property provides all materials and paint. | N52: Done
A53: =IFERROR(VLOOKUP(D53,'Master sheet (Clientes)'!A$6:D$747,2,0)," ") -> NJ | B53: =IFERROR(VLOOKUP(D53,'Master sheet (Clientes)'!A$6:D$747,3,0)," ") -> Vivmark Residential | C53: =IFERROR(VLOOKUP(D53,'Master sheet (Clientes)'!A$6:D$747,4,0)," ") -> A-V | D53: 70 Greene Apartments 70 Greene St, Jersey City, NJ 07302. | E53: 4104 | F53: 3BDR | G53: Vacant | H53: Paint unit at 8:00 am NOTE: For access, please call Jonathan 862-387-9993 or Danny 646-508-3402 | I53: DVM Marvin Cumes | J53: WTN Pending | M53: Clean 09/03 | N53: Paint done
A54: =IFERROR(VLOOKUP(D54,'Master sheet (Clientes)'!A$6:D$747,2,0)," ") -> NJ | B54: =IFERROR(VLOOKUP(D54,'Master sheet (Clientes)'!A$6:D$747,3,0)," ") -> Vivmark Residential | C54: =IFERROR(VLOOKUP(D54,'Master sheet (Clientes)'!A$6:D$747,4,0)," ") -> A-V | D54: Madox Apartments 198 Van Vorst St, Jersey City, NJ 07302. | E54: 802 | G54: Occupied | H54: Replace cracked floating sink NOTE: For access, please call Colin 973-255-8682or Eli at 1 (917) 442-0088 | I54: DVM Juan Mendoza | J54: Email | N54: Done
A56: State | B56: MANAGEMENT | C56: BC CLERK | D56: BUILDING / ADDRESS | E56: UNIT / AREA | F56: SIZE | G56: WORKSITE STATUS | H56: JOB DESCRIPTION | I56: JOB AWARDED TO: / TECHS QUANTITY: | J56: REQUEST / P.O / WTN / W.O | K56: BC WORK ORDER / BC ESTIMATE | L56: EXTRAS | M56: SPECIAL NOTES / SEQUENCE | N56: VENDORS DAILY STATUS REPORT
A57: =IFERROR(VLOOKUP(D57,'Master sheet (Clientes)'!A$6:D$747,2,0)," ") -> NJ | B57: =IFERROR(VLOOKUP(D57,'Master sheet (Clientes)'!A$6:D$747,3,0)," ") -> Rose Associates | C57: =IFERROR(VLOOKUP(D57,'Master sheet (Clientes)'!A$6:D$747,4,0)," ") -> A-V | D57: 39 High Street 39 High Street Jersey City, NJ 07306 | E57: 201 | G57: Vacant | H57: Continue Drywall Repairs: Repair the damaged drywall at the bedroom soffit, approximately 2 ft x 9 ft \ Provide and install the necessary framing support \ Install approximately 1 linear ft of 1x2 lumber at the wall as needed for proper drywall support \ Provide and install missing drywall in the hallway in the following approximate areas: 2 ft x 5 ft and 2 ft x 4 ft \ Tape, apply joint compound, and finish all drywall seams and repaired areas \ Sand all repaired surfaces to achieve a smooth and even finish \ Prime all repaired areas and leave them ready for paint. | I57: AJ Canas Solutions Alberto | J57: Email | K57: Estimate 16927 | M57: 3 handys quoted | N57: Done
A59: State | B59: MANAGEMENT | C59: BC CLERK | D59: BUILDING / ADDRESS | E59: UNIT / AREA | F59: SIZE | G59: WORKSITE STATUS | H59: JOB DESCRIPTION | I59: JOB AWARDED TO: / TECHS QUANTITY: | J59: REQUEST / P.O / WTN / W.O | K59: BC WORK ORDER / BC ESTIMATE | L59: EXTRAS | M59: SPECIAL NOTES / SEQUENCE | N59: VENDORS DAILY STATUS REPORT
A60: =IFERROR(VLOOKUP(D60,'Master sheet (Clientes)'!A$6:D$747,2,0)," ") -> NJ | B60: =IFERROR(VLOOKUP(D60,'Master sheet (Clientes)'!A$6:D$747,3,0)," ") -> Bozzuto | C60: =IFERROR(VLOOKUP(D60,'Master sheet (Clientes)'!A$6:D$747,4,0)," ") -> N-O | D60: Vantage Collection 33 Park View Ave, Jersey City, NJ 07302 | E60: PH 20 | G60: Vacant | H60: Floor repairs at 8:00 am | I60: M&J Flooring | J60: Email | N60: Done
A61: =IFERROR(VLOOKUP(D61,'Master sheet (Clientes)'!A$6:D$747,2,0)," ") -> NJ | B61: =IFERROR(VLOOKUP(D61,'Master sheet (Clientes)'!A$6:D$747,3,0)," ") -> Bozzuto | C61: =IFERROR(VLOOKUP(D61,'Master sheet (Clientes)'!A$6:D$747,4,0)," ") -> N-O | D61: Vantage Collection 33 Park View Ave, Jersey City, NJ 07302 | E61: 2307 | G61: Vacant | H61: Floor repairs at 8:00 am | I61: M&J Flooring | J61: Email | N61: Done
A62: =IFERROR(VLOOKUP(D62,'Master sheet (Clientes)'!A$6:D$747,2,0)," ") -> NJ | B62: =IFERROR(VLOOKUP(D62,'Master sheet (Clientes)'!A$6:D$747,3,0)," ") -> Greystar | C62: =IFERROR(VLOOKUP(D62,'Master sheet (Clientes)'!A$6:D$747,4,0)," ") -> A-V | D62: Embankment House 270 10th St, Jersey City, NJ 07302 | E62: 421 | F62: 3BDR | G62: Vacant | H62: Replace damage windowsill in living room last minute request - Assigned by Carlos **Note** unit is already clean please be careful and clean up after repair The building will provide the paint For access, please call Mike: 1 (845) 542-9676 or Gus 347-583-7765 | I62: M&J Flooring | J62: Email | M62: Bathroom repair for next day | N62: Done
A64: State | B64: MANAGEMENT | C64: BC CLERK | D64: BUILDING / ADDRESS | E64: UNIT / AREA | F64: SIZE | G64: WORKSITE STATUS | H64: JOB DESCRIPTION | I64: JOB AWARDED TO: / TECHS QUANTITY: | J64: REQUEST / P.O / WTN / W.O | K64: BC WORK ORDER / BC ESTIMATE | L64: EXTRAS | M64: SPECIAL NOTES / SEQUENCE | N64: VENDORS DAILY STATUS REPORT
A65: =IFERROR(VLOOKUP(D65,'Master sheet (Clientes)'!A$6:D$747,2,0)," ") -> NJ | B65: =IFERROR(VLOOKUP(D65,'Master sheet (Clientes)'!A$6:D$747,3,0)," ") -> Bozzuto | C65: =IFERROR(VLOOKUP(D65,'Master sheet (Clientes)'!A$6:D$747,4,0)," ") -> N-O | D65: The Morgan 160 Morgan St, Jersey City, NJ | E65: 1012 | F65: 2BDR | G65: Vacant | H65: Unit cleaning at 8:00am | I65: Atlas Way Cleaning | J65: Email | N65: Done
A66: =IFERROR(VLOOKUP(D66,'Master sheet (Clientes)'!A$6:D$747,2,0)," ") -> NJ | B66: =IFERROR(VLOOKUP(D66,'Master sheet (Clientes)'!A$6:D$747,3,0)," ") -> Bozzuto | C66: =IFERROR(VLOOKUP(D66,'Master sheet (Clientes)'!A$6:D$747,4,0)," ") -> N-O | D66: The Morgan 160 Morgan St, Jersey City, NJ | E66: 213 | F66: 3BDR | G66: Vacant | H66: post renovation cleanings at 8:00am | I66: Atlas Way Cleaning | J66: Email | N66: Done
A67: =IFERROR(VLOOKUP(D67,'Master sheet (Clientes)'!A$6:D$747,2,0)," ") -> NJ | B67: =IFERROR(VLOOKUP(D67,'Master sheet (Clientes)'!A$6:D$747,3,0)," ") -> Bozzuto | C67: =IFERROR(VLOOKUP(D67,'Master sheet (Clientes)'!A$6:D$747,4,0)," ") -> N-O | D67: The Morgan 160 Morgan St, Jersey City, NJ | E67: p105 | F67: 1BDR | G67: Vacant | H67: post renovation cleanings at 8:00am | I67: Atlas Way Cleaning | J67: Email | N67: Done
A69: State | B69: MANAGEMENT | C69: BC CLERK | D69: BUILDING / ADDRESS | E69: UNIT / AREA | F69: SIZE | G69: WORKSITE STATUS | H69: JOB DESCRIPTION | I69: JOB AWARDED TO: / TECHS QUANTITY: | J69: REQUEST / P.O / WTN / W.O | K69: BC WORK ORDER / BC ESTIMATE | L69: EXTRAS | M69: SPECIAL NOTES / SEQUENCE | N69: VENDORS DAILY STATUS REPORT
A70: =IFERROR(VLOOKUP(D70,'Master sheet (Clientes)'!A$6:D$747,2,0)," ") -> NJ | B70: =IFERROR(VLOOKUP(D70,'Master sheet (Clientes)'!A$6:D$747,3,0)," ") -> Bozzuto | C70: =IFERROR(VLOOKUP(D70,'Master sheet (Clientes)'!A$6:D$747,4,0)," ") -> N-O | D70: Birch House 49 Fisk St, Jersey City, NJ 07305 | E70: 102 | F70: 1BDR | G70: Vacant | H70: Unit cleaning AFTER 2:00 PM NOTE: Same-day paint | I70: YL Cleaning | J70: Email | N70: Done
A71: =IFERROR(VLOOKUP(D71,'Master sheet (Clientes)'!A$6:D$747,2,0)," ") -> NJ | B71: =IFERROR(VLOOKUP(D71,'Master sheet (Clientes)'!A$6:D$747,3,0)," ") -> Bozzuto | C71: =IFERROR(VLOOKUP(D71,'Master sheet (Clientes)'!A$6:D$747,4,0)," ") -> N-O | D71: Birch House 49 Fisk St, Jersey City, NJ 07305 | E71: 219 | F71: 1BDR | G71: Vacant | H71: Unit cleaning in the morning | I71: YL Cleaning | J71: Email | N71: Done
A72: =IFERROR(VLOOKUP(D72,'Master sheet (Clientes)'!A$6:D$747,2,0)," ") -> NJ | B72: =IFERROR(VLOOKUP(D72,'Master sheet (Clientes)'!A$6:D$747,3,0)," ") -> Bozzuto | C72: =IFERROR(VLOOKUP(D72,'Master sheet (Clientes)'!A$6:D$747,4,0)," ") -> N-O | D72: Edge Avenue F 170 Avenue F, Bayonne, NJ 07002 | E72: 442 | F72: 2BDR | G72: Vacant | H72: Unit cleaning at 8:00am | I72: YL Cleaning | J72: Email | N72: Done
A73: =IFERROR(VLOOKUP(D73,'Master sheet (Clientes)'!A$6:D$747,2,0)," ") -> NJ | B73: =IFERROR(VLOOKUP(D73,'Master sheet (Clientes)'!A$6:D$747,3,0)," ") -> Greystar | C73: =IFERROR(VLOOKUP(D73,'Master sheet (Clientes)'!A$6:D$747,4,0)," ") -> A-V | D73: The Bedford 374 Communipaw Ave, Jersey City, NJ 07304 | E73: 410 | F73: 2BDR | G73: Vacant | H73: Unit cleaning at 8:00am | I73: YL Cleaning | J73: Email | N73: Done
A74: =IFERROR(VLOOKUP(D74,'Master sheet (Clientes)'!A$6:D$747,2,0)," ") -> NJ | B74: =IFERROR(VLOOKUP(D74,'Master sheet (Clientes)'!A$6:D$747,3,0)," ") -> Greystar | C74: =IFERROR(VLOOKUP(D74,'Master sheet (Clientes)'!A$6:D$747,4,0)," ") -> A-V | D74: BELA 74 Maple St, Jersey City, NJ 07304 | E74: 316 | F74: 2BDR | G74: Vacant | H74: Unit cleaning at 8:00am | I74: YL Cleaning | J74: Email | N74: Done
A75: =IFERROR(VLOOKUP(D75,'Master sheet (Clientes)'!A$6:D$747,2,0)," ") -> NJ | B75: =IFERROR(VLOOKUP(D75,'Master sheet (Clientes)'!A$6:D$747,3,0)," ") -> Greystar | C75: =IFERROR(VLOOKUP(D75,'Master sheet (Clientes)'!A$6:D$747,4,0)," ") -> A-V | D75: BELA 74 Maple St, Jersey City, NJ 07304 | E75: 801 | F75: 2BDR | G75: Vacant | H75: Unit cleaning at 8:00am | I75: YL Cleaning | J75: Email | M75: Reglaze 09/02 | N75: Done
A76: =IFERROR(VLOOKUP(D76,'Master sheet (Clientes)'!A$6:D$747,2,0)," ") -> NJ | B76: =IFERROR(VLOOKUP(D76,'Master sheet (Clientes)'!A$6:D$747,3,0)," ") -> Vivmark Residential | C76: =IFERROR(VLOOKUP(D76,'Master sheet (Clientes)'!A$6:D$747,4,0)," ") -> A-V | D76: Portside Towers Apartments 155 Washington St, Jersey City, NJ 07302. | E76: 1408W | F76: 1BDR | G76: Vacant | H76: Unit cleaning at 8:00 am | I76: YL Cleaning | J76: WTN 86393684 | N76: Done
A77: =IFERROR(VLOOKUP(D77,'Master sheet (Clientes)'!A$6:D$747,2,0)," ") -> NJ | B77: =IFERROR(VLOOKUP(D77,'Master sheet (Clientes)'!A$6:D$747,3,0)," ") -> Vivmark Residential | C77: =IFERROR(VLOOKUP(D77,'Master sheet (Clientes)'!A$6:D$747,4,0)," ") -> A-V | D77: Hudson Point Apartments 131 Dudley St Ste Off, Jersey City, NJ 07302. | E77: 415 | F77: 1BDR | G77: Vacant | H77: Unit Cleaning AFTER 2:00 PM NOTE: same-day paint / For access, Please call Colin 1(973) 255-8682 or Eli 917-442-0088 | I77: YL Cleaning | J77: WTN Pending | N77: Done
A79: State | B79: MANAGEMENT | C79: BC CLERK | D79: BUILDING / ADDRESS | E79: UNIT / AREA | F79: SIZE | G79: WORKSITE STATUS | H79: JOB DESCRIPTION | I79: JOB AWARDED TO: / TECHS QUANTITY: | J79: REQUEST / P.O / WTN / W.O | K79: BC WORK ORDER / BC ESTIMATE | L79: EXTRAS | M79: SPECIAL NOTES / SEQUENCE | N79: VENDORS DAILY STATUS REPORT
A80: =IFERROR(VLOOKUP(D80,'Master sheet (Clientes)'!A$6:D$747,2,0)," ") -> NJ | B80: =IFERROR(VLOOKUP(D80,'Master sheet (Clientes)'!A$6:D$747,3,0)," ") -> Bozzuto | C80: =IFERROR(VLOOKUP(D80,'Master sheet (Clientes)'!A$6:D$747,4,0)," ") -> N-O | D80: Edge Avenue G 100 Avenue G, Bayonne, NJ 07002 | E80: 374 | F80: 1BDR | G80: Vacant | H80: Unit cleaning at 8:00am | I80: JYL Cleaning | J80: Email | N80: Done
A81: =IFERROR(VLOOKUP(D81,'Master sheet (Clientes)'!A$6:D$747,2,0)," ") -> NJ | B81: =IFERROR(VLOOKUP(D81,'Master sheet (Clientes)'!A$6:D$747,3,0)," ") -> Bozzuto | C81: =IFERROR(VLOOKUP(D81,'Master sheet (Clientes)'!A$6:D$747,4,0)," ") -> N-O | D81: Edge Avenue G 100 Avenue G, Bayonne, NJ 07002 | E81: 466 | F81: 1BDR | G81: Vacant | H81: Unit cleaning at 8:00am | I81: JYL Cleaning | J81: Email | N81: Done
A83: State | B83: MANAGEMENT | C83: BC CLERK | D83: BUILDING / ADDRESS | E83: UNIT / AREA | F83: SIZE | G83: WORKSITE STATUS | H83: JOB DESCRIPTION | I83: JOB AWARDED TO: / TECHS QUANTITY: | J83: REQUEST / P.O / WTN / W.O | K83: BC WORK ORDER / BC ESTIMATE | L83: EXTRAS | M83: SPECIAL NOTES / SEQUENCE | N83: VENDORS DAILY STATUS REPORT
A84: =IFERROR(VLOOKUP(D84,'Master sheet (Clientes)'!A$6:D$747,2,0)," ") -> NJ | B84: =IFERROR(VLOOKUP(D84,'Master sheet (Clientes)'!A$6:D$747,3,0)," ") -> Vivmark Residential | C84: =IFERROR(VLOOKUP(D84,'Master sheet (Clientes)'!A$6:D$747,4,0)," ") -> N-O | D84: Avalon at Edgewater I Old Building (River Mews). | E84: 136 | G84: Occupied | H84: Guest bathtub reglaze NOTE: Please be on tie since this unit is occupied / For access, please call Christian 201-705-0879 or Alex 201-713-8719 | I84: Felix R santos | J84: Email | N84: Done
A86: State | B86: MANAGEMENT | C86: BC CLERK | D86: BUILDING / ADDRESS | E86: UNIT / AREA | F86: SIZE | G86: WORKSITE STATUS | H86: JOB DESCRIPTION | I86: JOB AWARDED TO: / TECHS QUANTITY: | J86: REQUEST / P.O / WTN / W.O | K86: BC WORK ORDER / BC ESTIMATE | L86: EXTRAS | M86: SPECIAL NOTES / SEQUENCE | N86: VENDORS DAILY STATUS REPORT
A87: =IFERROR(VLOOKUP(D87,'Master sheet (Clientes)'!A$6:D$747,2,0)," ") -> NJ | B87: =IFERROR(VLOOKUP(D87,'Master sheet (Clientes)'!A$6:D$747,3,0)," ") -> Skylight | C87: =IFERROR(VLOOKUP(D87,'Master sheet (Clientes)'!A$6:D$747,4,0)," ") -> N-O | D87: Grand Adams Apartments 300 Grand St, Hoboken, NJ 07030 | E87: Leasing Office | H87: Carpet Replacement: Remove and dispose of the existing commercial carpet at the side entrance of the leasing office. -Furnish and install new commercial_x0002_grade carpet in a similar blue color. -Installation areas are approximately: * 17’ x 5’ 85 SF * 12’ x 6’ 72 SF -Install new tack strips and transition strips as required for a complete installation. Secure and finish all edges to ensure a clean, professional appearance. at 9:00am | I87: Excellent Carpet | J87: Email | K87: Estimate 16644 | N87: Cancelled Materials were not available / Rescheduled for Thursday 09/03
D89: NEWPORT
D90: BC SUPERVISOR: Jhonatan Perez (201) 800-5601 jperez@build-care.com / BC RUNNER: Eduard Bonifacio (551) 242-5958 purchases@build-care.com
A92: State | B92: MANAGEMENT | C92: BC CLERK | D92: BUILDING / ADDRESS | E92: UNIT / AREA | F92: SIZE | G92: WORKSITE STATUS | H92: JOB DESCRIPTION | I92: JOB AWARDED TO: / TECHS QUANTITY: | J92: REQUEST / P.O / WTN / W.O | K92: BC WORK ORDER / BC ESTIMATE | L92: EXTRAS | M92: SPECIAL NOTES / SEQUENCE | N92: VENDORS DAILY STATUS REPORT
A93: =IFERROR(VLOOKUP(D93,'Master sheet (Clientes)'!A$6:D$747,2,0)," ") -> NJ | B93: =IFERROR(VLOOKUP(D93,'Master sheet (Clientes)'!A$6:D$747,3,0)," ") -> C/O Realty | C93: =IFERROR(VLOOKUP(D93,'Master sheet (Clientes)'!A$6:D$747,4,0)," ") -> N-O | D93: Waterside Square South at Newport 35 River Dr S, Jersey City, NJ 07310 | H93: 1 handyman for 5 days Assist the property with handyman tasks work orders / make ready Tuesday 09/01/26 through Saturday 09/05/26from 12pm through 8:30pm Note: Send Marvin Perez | I93: Alluda Marvin Perez | J93: PO Pending | N93: Continue
A95: State | B95: MANAGEMENT | C95: BC CLERK | D95: BUILDING / ADDRESS | E95: UNIT / AREA | F95: SIZE | G95: WORKSITE STATUS | H95: JOB DESCRIPTION | I95: JOB AWARDED TO: / TECHS QUANTITY: | J95: REQUEST / P.O / WTN / W.O | K95: BC WORK ORDER / BC ESTIMATE | L95: EXTRAS | M95: SPECIAL NOTES / SEQUENCE | N95: VENDORS DAILY STATUS REPORT
A96: =IFERROR(VLOOKUP(D96,'Master sheet (Clientes)'!A$6:D$747,2,0)," ") -> NJ | B96: =IFERROR(VLOOKUP(D96,'Master sheet (Clientes)'!A$6:D$747,3,0)," ") -> C/O Realty | C96: =IFERROR(VLOOKUP(D96,'Master sheet (Clientes)'!A$6:D$747,4,0)," ") -> N-O | D96: Pacific at Newport 25 River Dr S, Jersey City, NJ 07310 | H96: 1 handyman for 5 days Assist the property with handyman tasks work orders / make ready from Monday 08/31/26 through Friday 09/04/26 at 8am Note: send Othoniel Gonzalez | I96: Cuxil Group Ottoniel Gonzales | J96: PO Pending | K96: Estimate 17341 | M96: Until Friday 09/04 | N96: Continue
A97: =IFERROR(VLOOKUP(D97,'Master sheet (Clientes)'!A$6:D$747,2,0)," ") -> NJ | B97: =IFERROR(VLOOKUP(D97,'Master sheet (Clientes)'!A$6:D$747,3,0)," ") -> C/O Realty | C97: =IFERROR(VLOOKUP(D97,'Master sheet (Clientes)'!A$6:D$747,4,0)," ") -> N-O | D97: Pacific at Newport 25 River Dr S, Jersey City, NJ 07310 | H97: 2 daily painters for 6 days Assist the property with painter tasks from Saturday 08/28/26 and Monday 08/31/26 through Friday 09/04/26 at 8am Note: property will provide all the materials and supervision | I97: Cuxil Group David Pineda / Sanai Pliability Luis Garcia | J97: PO Pending | K97: Estimate 17343 | M97: Until Friday 09/04 | N97: Continue
A98: =IFERROR(VLOOKUP(D98,'Master sheet (Clientes)'!A$6:D$747,2,0)," ") -> NJ | B98: =IFERROR(VLOOKUP(D98,'Master sheet (Clientes)'!A$6:D$747,3,0)," ") -> C/O Realty | C98: =IFERROR(VLOOKUP(D98,'Master sheet (Clientes)'!A$6:D$747,4,0)," ") -> N-O | D98: Pacific at Newport 25 River Dr S, Jersey City, NJ 07310 | E98: 610 | F98: 2BDR | G98: Vacant | H98: Continue Renovation: Popcorn ceiling removal / renovation Bathroom / install kitchen backsplash / Paint entire unit incluiding ceiling | I98: Cuxil Group / Sanai Piability | J98: PO Pending | N98: Flooring not done yet / continue after floor
A99: =IFERROR(VLOOKUP(D99,'Master sheet (Clientes)'!A$6:D$747,2,0)," ") -> NJ | B99: =IFERROR(VLOOKUP(D99,'Master sheet (Clientes)'!A$6:D$747,3,0)," ") -> C/O Realty | C99: =IFERROR(VLOOKUP(D99,'Master sheet (Clientes)'!A$6:D$747,4,0)," ") -> N-O | D99: Pacific at Newport 25 River Dr S, Jersey City, NJ 07310 | E99: 610 | F99: 2BDR | G99: Vacant | H99: Continue Full Laundry build-up: Framing | I99: Cuxil Group / Sanai Piability | J99: PO Pending | K99: Estimate 17172 | N99: Flooring not done yet / continue after floor
A100: =IFERROR(VLOOKUP(D100,'Master sheet (Clientes)'!A$6:D$747,2,0)," ") -> NJ | B100: =IFERROR(VLOOKUP(D100,'Master sheet (Clientes)'!A$6:D$747,3,0)," ") -> C/O Realty | C100: =IFERROR(VLOOKUP(D100,'Master sheet (Clientes)'!A$6:D$747,4,0)," ") -> N-O | D100: Parkside West at Newport 40 Newport Parkway, Jersey City, NJ | H100: 1 handyman for 20 days Job: assist the property with handyman work work orders / make ready Schedule from Tuesday 08/25/26 through Saturday 08/29/26 Monday 08/31/26 through Friday 09/04/26 Tuesday 09/08/26 through Saturday 09/12/26 Monday 09/14/26 through Friday 09/18/26 at 8am Note: send Geovanny Saldivar Note: handyman will not work Monday 09/07/26 due to Labor Day holiday | I100: Cuxil Group Giovanny Saldivar | J100: PO Pending | M100: Until Fri 09/18 | N100: Continue
A101: =IFERROR(VLOOKUP(D101,'Master sheet (Clientes)'!A$6:D$747,2,0)," ") -> NJ | B101: =IFERROR(VLOOKUP(D101,'Master sheet (Clientes)'!A$6:D$747,3,0)," ") -> C/O Realty | C101: =IFERROR(VLOOKUP(D101,'Master sheet (Clientes)'!A$6:D$747,4,0)," ") -> N-O | D101: Parkside East at Newport 30 Newport Parkway, Jersey City, NJ | H101: 1 handyman for 20 days Job: assist the property with handyman work work orders / make ready Schedule from Tuesday 08/25/26 through Saturday 08/29/26 Monday 08/31/26 through Friday 09/04/26 Tuesday 09/08/26 through Saturday 09/12/26 Monday 09/14/26 through Friday 09/18/26 at 8am Note: send Oscar Monasterio Note: handyman will not work Monday 09/07/26 due to Labor Day holiday | I101: Cuxil Group Oscar Monasterio | J101: PO Pending | M101: Until Fri 09/18 | N101: Continue
A102: =IFERROR(VLOOKUP(D102,'Master sheet (Clientes)'!A$6:D$747,2,0)," ") -> NJ | B102: =IFERROR(VLOOKUP(D102,'Master sheet (Clientes)'!A$6:D$747,3,0)," ") -> C/O Realty | C102: =IFERROR(VLOOKUP(D102,'Master sheet (Clientes)'!A$6:D$747,4,0)," ") -> N-O | D102: East Hampton at Newport 30 River Ct, Jersey City, NJ 07310 | E102: 1212 | F102: 1BDR | G102: Vacant | H102: Continue Laundry room build-up ONLY | I102: Cuxil Group Edgar cuxil | J102: PO Pending | K102: Estimate 17170 | N102: Done
A103: =IFERROR(VLOOKUP(D103,'Master sheet (Clientes)'!A$6:D$747,2,0)," ") -> NJ | B103: =IFERROR(VLOOKUP(D103,'Master sheet (Clientes)'!A$6:D$747,3,0)," ") -> C/O Realty | C103: =IFERROR(VLOOKUP(D103,'Master sheet (Clientes)'!A$6:D$747,4,0)," ") -> N-O | D103: East Hampton at Newport 30 River Ct, Jersey City, NJ 07310 | E103: 1705 | F103: 2BDR | G103: Vacant | H103: 1 handyman for 2 days make ready - Monday and Tuesday 08/31-09/01 | I103: Cuxil Group Juan Garcia | J103: PO Pending | N103: Done
A104: =IFERROR(VLOOKUP(D104,'Master sheet (Clientes)'!A$6:D$747,2,0)," ") -> NJ | B104: =IFERROR(VLOOKUP(D104,'Master sheet (Clientes)'!A$6:D$747,3,0)," ") -> C/O Realty | C104: =IFERROR(VLOOKUP(D104,'Master sheet (Clientes)'!A$6:D$747,4,0)," ") -> N-O | D104: East Hampton at Newport 30 River Ct, Jersey City, NJ 07310 | E104: 415 | F104: 1BDR | G104: Vacant | H104: Continue Full Renovation: Popcorn ceiling removal / renovation Bathroom / install kitchen backsplash / Paint entire unit incluiding ceiling | I104: Sanai Piability Lorenzo Vaquiax | J104: PO Pending | N104: Continue
A105: =IFERROR(VLOOKUP(D105,'Master sheet (Clientes)'!A$6:D$747,2,0)," ") -> NJ | B105: =IFERROR(VLOOKUP(D105,'Master sheet (Clientes)'!A$6:D$747,3,0)," ") -> C/O Realty | C105: =IFERROR(VLOOKUP(D105,'Master sheet (Clientes)'!A$6:D$747,4,0)," ") -> N-O | D105: Riverside at Newport 1 River Ct, Jersey City, NJ 07310 | E105: Garage 2nd floor | H105: 1 handyman for 10 days Assist the property with bathroom vanities repair from Monday 08/24/26 through Friday 08/28/26 - Monday 08/31/26 through Friday 09/04/26 at 8:30am Note: property to provide all materials and supervision Note: send David Pineda Must contact Karan upon arrival UPDATE: Tuesday 09/01 to Saturday 09/05 | I105: Cuxil Group David Pineda | J105: PO Pending | M105: Until Fri 09/04 | N105: Continue
A106: =IFERROR(VLOOKUP(D106,'Master sheet (Clientes)'!A$6:D$747,2,0)," ") -> NJ | B106: =IFERROR(VLOOKUP(D106,'Master sheet (Clientes)'!A$6:D$747,3,0)," ") -> C/O Realty | C106: =IFERROR(VLOOKUP(D106,'Master sheet (Clientes)'!A$6:D$747,4,0)," ") -> N-O | D106: Riverside at Newport 1 River Ct, Jersey City, NJ 07310 | E106: Hallways | H106: Provide (2) full-time painters for (2) day to assist the property with painter's tasks Monday and Tuesday. 08/31/26-09/01/26 | I106: Cuxil Group Yovanny Olgadez / Sanai Piability Josue Olgadez / Sanai Pliability Josue Olgadez | J106: PO Pending | K106: Estimate 17304 | M106: Until Tues 09/01 | N106: Done
A107: =IFERROR(VLOOKUP(D107,'Master sheet (Clientes)'!A$6:D$747,2,0)," ") -> NJ | B107: =IFERROR(VLOOKUP(D107,'Master sheet (Clientes)'!A$6:D$747,3,0)," ") -> C/O Realty | C107: =IFERROR(VLOOKUP(D107,'Master sheet (Clientes)'!A$6:D$747,4,0)," ") -> N-O | D107: Riverside at Newport 1 River Ct, Jersey City, NJ 07310 | E107: Storage Room | H107: Continue Repair: Install new property provided ptac unit -Build drain line for back of the ptac unit, to allow water to travel away from the wall -Replace approximately 10 gfci outlets and 4 light switches (Property to provide materials) -Install new property provided outlet and switch covers -Install property provided appliances, toilet, and bathtub on wooden dollies -Paint exterior wall of the training room using white semigloss paint Wall: 35ft long x 8ft high -Purchase and install a tv mounting bracket for a 40” tv -Install a 40” property provided tv. -Build two dollies for washer/dryer machines 26”x24” with plywood and 4 wheels each. -Build drainage with pvc pipes for training purposes for - showerpan - toilet - vanity sink - install copper including pipes for hot and cold water for training purposes only Note: all the pipe installations will not be connected to any water or drainage lines Notes: *Property to provide appliances, electrical outlets, switches, and covers *Debris to be disposed of in property provided dumpster. | I107: Cuxil Group / Sanai Pliability | J107: PO Pending | K107: Estimate 16991 | N107: Rescheduled Friday
A108: =IFERROR(VLOOKUP(D108,'Master sheet (Clientes)'!A$6:D$747,2,0)," ") -> NJ | B108: =IFERROR(VLOOKUP(D108,'Master sheet (Clientes)'!A$6:D$747,3,0)," ") -> C/O Realty | C108: =IFERROR(VLOOKUP(D108,'Master sheet (Clientes)'!A$6:D$747,4,0)," ") -> N-O | D108: Roosevelt House at Hamilton Park 180 10th St, Jersey City, NJ 07302 | H108: 1 handyman work for 15 days Assist the property with handyman tasks - work order / turns Sunday 08/16/26 through Thursday 08/20/26 - Sunday 08/23/26 through Thursday 08/27/26 Sunday 08/30/26 through Thursday 09/03/26 from 9am to 5:30pm Note: send Michael Garcia | I108: Sanai pliability Mayco Garcia | J108: PO Pending | K108: Estimate 17232 | M108: Until Thu 09/03 | N108: Continue
A109: =IFERROR(VLOOKUP(D109,'Master sheet (Clientes)'!A$6:D$747,2,0)," ") -> NJ | B109: =IFERROR(VLOOKUP(D109,'Master sheet (Clientes)'!A$6:D$747,3,0)," ") -> C/O Realty | C109: =IFERROR(VLOOKUP(D109,'Master sheet (Clientes)'!A$6:D$747,4,0)," ") -> N-O | D109: Southampton at Newport 20 River Ct, Jersey City, NJ 07310 | H109: 1 handyman for 15 days Assist the property with handyman task work orders / make ready from Tuesday 08/18/26 through Saturday 08/22/26, Tuesday 08/25/26 through Saturday 08/29/26 , Tuesday 09/01/26 through Saturday 09/05/26 from 10am to 6:30pm | I109: Sanai Pliability Wilber Ramirez | J109: PO Pending | K109: Estimate 17233 | N109: Continue
A110: =IFERROR(VLOOKUP(D110,'Master sheet (Clientes)'!A$6:D$747,2,0)," ") -> NJ | B110: =IFERROR(VLOOKUP(D110,'Master sheet (Clientes)'!A$6:D$747,3,0)," ") -> C/O Realty | C110: =IFERROR(VLOOKUP(D110,'Master sheet (Clientes)'!A$6:D$747,4,0)," ") -> N-O | D110: Pacific at Newport 25 River Dr S, Jersey City, NJ 07310 | E110: 1409 | F110: 2BDR | G110: Vacant | H110: Continue Full laundry room build-up: Framing | I110: Cuxil group Extra de: Demetrio Semeya | J110: PO Pending | K110: Estimate 17169 | N110: Continue
A111: =IFERROR(VLOOKUP(D111,'Master sheet (Clientes)'!A$6:D$747,2,0)," ") -> NJ | B111: =IFERROR(VLOOKUP(D111,'Master sheet (Clientes)'!A$6:D$747,3,0)," ") -> C/O Realty | C111: =IFERROR(VLOOKUP(D111,'Master sheet (Clientes)'!A$6:D$747,4,0)," ") -> N-O | D111: Pacific at Newport 25 River Dr S, Jersey City, NJ 07310 | E111: 2504 | H111: Continue Laundry Room Construction framing and demo work | I111: Cuxil group Extra de Edgar Cuxil | J111: PO Pending | K111: Estimate 17249 | N111: Continue
A112: =IFERROR(VLOOKUP(D112,'Master sheet (Clientes)'!A$6:D$747,2,0)," ") -> NJ | B112: =IFERROR(VLOOKUP(D112,'Master sheet (Clientes)'!A$6:D$747,3,0)," ") -> C/O Realty | C112: =IFERROR(VLOOKUP(D112,'Master sheet (Clientes)'!A$6:D$747,4,0)," ") -> N-O | D112: Aquablu at Newport 110 River Dr S, Jersey City, NJ 07310 | E112: 2305 | G112: Vacant | H112: Kitchen Countertop Reduction: -Demo and discard existing kitchen countertops and stone backsplash. -Demo and discard existing drywall to make surfaces level. Area to be Demoed: *17" wide x 79" long x 4" high -Provide and install metal corner bead. -Perform drywall repairs as needed. -Tape, spackle, sand and prime all repaired areas. -Apply (1) coat of paint to repair area, matching property specs. at 8:00am | I112: Sanai Pliability Jairo Cuxil / Santiago Chanchavac | J112: PO Pending | K112: Estimate 17380 | N112: Done
A113: =IFERROR(VLOOKUP(D113,'Master sheet (Clientes)'!A$6:D$747,2,0)," ") -> NJ | B113: =IFERROR(VLOOKUP(D113,'Master sheet (Clientes)'!A$6:D$747,3,0)," ") -> C/O Realty | C113: =IFERROR(VLOOKUP(D113,'Master sheet (Clientes)'!A$6:D$747,4,0)," ") -> N-O | D113: Aquablu at Newport 110 River Dr S, Jersey City, NJ 07310 | E113: 231 | G113: Vacant | H113: Kitchen Countertop Reduction: -Demo and discard existing kitchen countertops and stone backsplash. -Demo and discard existing drywall to make surfaces level. Area to be Demoed: *17" wide x 79" long x 4" high -Provide and install metal corner bead. -Perform drywall repairs as needed. -Tape, spackle, sand and prime all repaired areas. -Apply (1) coat of paint to repair area, matching property specs. at 8:00am | I113: Sanai Pliability Extra de: Jairo Cuxil / Santiago Chanchavac | J113: PO Pending | K113: Estimate 17381 | N113: Done
A114: =IFERROR(VLOOKUP(D114,'Master sheet (Clientes)'!A$6:D$747,2,0)," ") -> NJ | B114: =IFERROR(VLOOKUP(D114,'Master sheet (Clientes)'!A$6:D$747,3,0)," ") -> C/O Realty | C114: =IFERROR(VLOOKUP(D114,'Master sheet (Clientes)'!A$6:D$747,4,0)," ") -> N-O | D114: Aquablu at Newport 110 River Dr S, Jersey City, NJ 07310 | E114: 5th floor hallway near unit 527 | H114: Drywall Demo+Repairs: Demo drywall on ceiling to allow plumbing work.\ Size of the opening: 8 ft x 4 ft and 2 ft x 8 ft.\ Remove and save an existing door access panel.\ Once plumbing repairs are completed by others, install new drywall to seal the demo area.\ Tape, spackle, sand, and prime newly installed drywall.\ Paint repaired ceiling areas using flat white paint.\ Use property-provided paint to perform touch-up painting on walls as needed. | I114: Cuxil group Demetrio Semeya | J114: PO Pending | K114: Estimate 17317 | M114: We will return 09/02 in the afternoon to begin sealing demo areas once their plumber has completed their work. | N114: Continue
A116: State | B116: MANAGEMENT | C116: BC CLERK | D116: BUILDING / ADDRESS | E116: UNIT / AREA | F116: SIZE | G116: WORKSITE STATUS | H116: JOB DESCRIPTION | I116: JOB AWARDED TO: / TECHS QUANTITY: | J116: REQUEST / P.O / WTN / W.O | K116: BC WORK ORDER / BC ESTIMATE | L116: EXTRAS | M116: SPECIAL NOTES / SEQUENCE | N116: VENDORS DAILY STATUS REPORT
A117: =IFERROR(VLOOKUP(D117,'Master sheet (Clientes)'!A$6:D$747,2,0)," ") -> NJ | B117: =IFERROR(VLOOKUP(D117,'Master sheet (Clientes)'!A$6:D$747,3,0)," ") -> C/O Realty | C117: =IFERROR(VLOOKUP(D117,'Master sheet (Clientes)'!A$6:D$747,4,0)," ") -> N-O | D117: Pacific at Newport 25 River Dr S, Jersey City, NJ 07310 | E117: 1907 | F117: 1BDR | G117: Vacant | H117: Full laundry room build-up: Plumbing work | I117: E&P Mechanical Corp Cassio | J117: PO Pending | K117: Estimate 17168 | N117: Done
A118: =IFERROR(VLOOKUP(D118,'Master sheet (Clientes)'!A$6:D$747,2,0)," ") -> NJ | B118: =IFERROR(VLOOKUP(D118,'Master sheet (Clientes)'!A$6:D$747,3,0)," ") -> C/O Realty | C118: =IFERROR(VLOOKUP(D118,'Master sheet (Clientes)'!A$6:D$747,4,0)," ") -> N-O | D118: Atlantic at Newport 31 River Ct, Jersey City, NJ 07310 | E118: 2707 | F118: 1BDR | G118: Vacant | H118: P-trap Replacement: Provide certified plumber, necessary equipment, and materials to: -Remove and discard existing p-trap and connections -Purchase and install all PVC P-trap, fittings, washers, and associated connections up to the sink drain / Last minute request job assigned by Casey | I118: E&P Mechanical Corp Cassio | J118: PO Pending | K118: Estimate 17398 | N118: Done
A120: State | B120: MANAGEMENT | C120: BC CLERK | D120: BUILDING / ADDRESS | E120: UNIT / AREA | F120: SIZE | G120: WORKSITE STATUS | H120: JOB DESCRIPTION | I120: JOB AWARDED TO: / TECHS QUANTITY: | J120: REQUEST / P.O / WTN / W.O | K120: BC WORK ORDER / BC ESTIMATE | L120: EXTRAS | M120: SPECIAL NOTES / SEQUENCE | N120: VENDORS DAILY STATUS REPORT
A121: =IFERROR(VLOOKUP(D121,'Master sheet (Clientes)'!A$6:D$747,2,0)," ") -> NJ | B121: =IFERROR(VLOOKUP(D121,'Master sheet (Clientes)'!A$6:D$747,3,0)," ") -> C/O Realty | C121: =IFERROR(VLOOKUP(D121,'Master sheet (Clientes)'!A$6:D$747,4,0)," ") -> N-O | D121: Bisby at Newport 30 Park Lane North Jersey City, NJ 07310 | E121: 211 | G121: Occupied | H121: Continue Wood Floor Repair AT 11:00 AM: Remove and discard damaged flooring located in walk-in closet (4 ft x 9 ft) \ Prep and perform minor subfloor repairs \ Install 36 sq ft of new, property-provided flooring \ BC to provide adhesive. | I121: M&J Flooring | J121: PO Pending | K121: Estimate 17308 | N121: Done
A122: =IFERROR(VLOOKUP(D122,'Master sheet (Clientes)'!A$6:D$747,2,0)," ") -> NJ | B122: =IFERROR(VLOOKUP(D122,'Master sheet (Clientes)'!A$6:D$747,3,0)," ") -> C/O Realty | C122: =IFERROR(VLOOKUP(D122,'Master sheet (Clientes)'!A$6:D$747,4,0)," ") -> N-O | D122: Southampton at Newport 20 River Ct, Jersey City, NJ 07310 | E122: 2409 | F122: 2BDR | G122: Vacant | H122: Kahrs Floor Repair: -Demo and discard karhs floor in 2 areas of the apartment guest bedroom master bedroom near closet total size of repairs 48sqft -Prep and perform minor subfloor repairs prior to new floor installation. -Provide and install 48 sqft new KahrsFloor in mentioned area Kahrs Floor Refinish: -Sand 954 sqft existing Kahrs flooring located in throughout unit. -Smooth out any scratches left after sanding process to ensure a more even final appearance. -Clean up the dust by vacuuming entire area. -Apply one (1) coat of clear coat to area.at 8:00am | I122: M&J Flooring | J122: PO Pending | K122: Estimate 17382 | M122: Pending 1 coat of floor paint | N122: Done
A123: =IFERROR(VLOOKUP(D123,'Master sheet (Clientes)'!A$6:D$747,2,0)," ") -> NJ | B123: =IFERROR(VLOOKUP(D123,'Master sheet (Clientes)'!A$6:D$747,3,0)," ") -> C/O Realty | C123: =IFERROR(VLOOKUP(D123,'Master sheet (Clientes)'!A$6:D$747,4,0)," ") -> N-O | D123: Bisby at Newport 30 Park Lane North Jersey City, NJ 07310 | E123: 3202 | F123: =IFERROR(VLOOKUP(H123,'Master sheet (Clientes)'!E$6:H$747,3,0)," ") | G123: =IFERROR(VLOOKUP(H123,'Master sheet (Clientes)'!E$6:H$747,4,0)," ") | H123: Floor Repair and Refinish: -Replace water damaged floor located in: kitchen- 8ft x 18ft -Sand approximately 730 square feet of existing flooring in: - entrance hallway - entire living room and kitchen - entire left side bedroom including closet - right side bedroom in front of closet -Smooth out any scratches left after sanding process to ensure a more even final appearance. -Apply one (1) coat of stain to area, match | I123: M&J Flooring | J123: PO Pending | K123: Estimate 17397 | N123: Continue
A125: State | B125: MANAGEMENT | C125: BC CLERK | D125: BUILDING / ADDRESS | E125: UNIT / AREA | F125: SIZE | G125: WORKSITE STATUS | H125: JOB DESCRIPTION | I125: JOB AWARDED TO: / TECHS QUANTITY: | J125: REQUEST / P.O / WTN / W.O | K125: BC WORK ORDER / BC ESTIMATE | L125: EXTRAS | M125: SPECIAL NOTES / SEQUENCE | N125: VENDORS DAILY STATUS REPORT
A126: =IFERROR(VLOOKUP(D126,'Master sheet (Clientes)'!A$6:D$747,2,0)," ") -> NJ | B126: =IFERROR(VLOOKUP(D126,'Master sheet (Clientes)'!A$6:D$747,3,0)," ") -> C/O Realty | C126: =IFERROR(VLOOKUP(D126,'Master sheet (Clientes)'!A$6:D$747,4,0)," ") -> N-O | D126: Waterside Square North at Newport 55 River Dr S, Jersey City, NJ 07310 | E126: 1801 | F126: 2BDR | G126: Vacant | H126: Regular cleaning at 8:00am | I126: YL Cleaning | J126: Email | N126: Done
...

Sheet Wed, Sep 02
A1: BuildCare SCHEDULE WEDNESDAY, SEPTEMBER 02 / 2026
A3: SUPERVISOR ON CALL NJ: Sebastian Lopez (551) 202-4443 jlopez@build-care.com
A4: CREWS ASSIGNED BY DEFAULT ON CALL: DVM - Atlas Techs / Atlas Cleaning - HG Services
A5: CREWS CONFIRMED BY THE ON CALL: ????
A6: BC MEMBERS OFF/VACATIONS:
D9: STATE OF NEW JERSEY
D11: WATERFRONT AREA (Fort Lee - Edgewater - Cliffside Park - Fairview - North Bergen - West New York - Weehawken - North Hoboken "8th Street Up" )
D12: BC SUPERVISOR: Carlos Perez (862) 383-3884 cperez@build-care.com BC SUPERVISOR/RUNNER: Juan Zapata (551) 202-4443 jzapata@build-care.com
A14: State | B14: MANAGEMENT (Inmobiliaria) | C14: BC CLERK (Persona de Buildcare que hace la factura) | D14: BUILDING / ADDRESS (Nombre y dirección del edificio) | E14: UNIT / AREA (número apartamento - área edificio) | F14: SIZE (tamaño del apartamento) | G14: WORKSITE STATUS (Estado del inmueble) | H14: JOB DESCRIPTION | I14: JOB AWARDED TO: / TECHS QUANTITY: (Nombre de la compañía y trabajador de la compañía) | J14: REQUEST / P.O / WTN / W.O (Por dónde se pidió) | K14: BC WORK ORDER / BC ESTIMATE (Cotizaciones) | L14: EXTRAS | M14: SPECIAL NOTES / SEQUENCE | N14: VENDORS DAILY STATUS REPORT (Continúa o no el trabajo)
A15: =IFERROR(VLOOKUP(D15,'Master sheet (Clientes)'!A$6:D$747,2,0)," ") -> NJ | B15: =IFERROR(VLOOKUP(D15,'Master sheet (Clientes)'!A$6:D$747,3,0)," ") -> Vivmark Residential | C15: =IFERROR(VLOOKUP(D15,'Master sheet (Clientes)'!A$6:D$747,4,0)," ") -> N-O | D15: Avalon at Edgewater II New Building (Russell). | E15: 104 | F15: 1BDR | G15: Occupeid | H15: Continue Repair openings that were made by other after suffering leak damage -Repairs will be in the coat closet, laundry closet, living room, hallway, bedroom, and bathroom walls. In the bathroom we will have to redo the bathroom tiles area is approximately 8x10 tiles will have to be removed, and sub floor repaired before installing new tiles at 9:00am The building will provide paint Bc to provide all other materials and labor needed to complete the job. For access, please call Christian 201-705-0879 or Alex 201-713-8719 | I15: AJ Canas Solutions Ricardo Willian Alvares. | J15: Email | N15: Continue
A16: =IFERROR(VLOOKUP(D16,'Master sheet (Clientes)'!A$6:D$747,2,0)," ") -> NJ | B16: =IFERROR(VLOOKUP(D16,'Master sheet (Clientes)'!A$6:D$747,3,0)," ") -> Vivmark Residential | C16: =IFERROR(VLOOKUP(D16,'Master sheet (Clientes)'!A$6:D$747,4,0)," ") -> N-O | D16: Avalon at Edgewater II New Building (Russell). | E16: 155 | G16: Occupied | H16: Continue Left side bedroom bathroom tile floor to be demoed, sub floor fixed, install new tiles, and grout area is 9ft x 6ft. at 9am Bc to provide all materials and labor needed to complete the job. For access, please call Christian 201-705-0879 or Alex 201-713-8719 | I16: AJ Canas Solutions Vinicio / Carlos | J16: Email | N16: Continue
A17: =IFERROR(VLOOKUP(D17,'Master sheet (Clientes)'!A$6:D$747,2,0)," ") -> NJ | B17: =IFERROR(VLOOKUP(D17,'Master sheet (Clientes)'!A$6:D$747,3,0)," ") -> Skylight | C17: =IFERROR(VLOOKUP(D17,'Master sheet (Clientes)'!A$6:D$747,4,0)," ") -> N-O | D17: The Sterling 2055 Center Ave, Fort Lee, NJ 07024 | E17: 5D | G17: Occupied | H17: Continue Repair opening made by others and install missing parquet NOTE: BC to provide plastic drop, spackle, rosin paper, wall paint, blue tape, metal for framing, drywall, primer grip, sanding sponge, floor trim and other materials and labor needed to complete the job. / For access, please call Steve (646) 299-5888 or Jeffery 929-218-9732 | I17: AJ Canas Solutions Alberto | J17: Email | N17: Done
A18: =IFERROR(VLOOKUP(D18,'Master sheet (Clientes)'!A$6:D$747,2,0)," ") -> NJ | B18: =IFERROR(VLOOKUP(D18,'Master sheet (Clientes)'!A$6:D$747,3,0)," ") -> Vivmark Residential | C18: =IFERROR(VLOOKUP(D18,'Master sheet (Clientes)'!A$6:D$747,4,0)," ") -> N-O | D18: Avalon at Edgewater I Old Building (River Mews). | E18: 426 | G18: Occupied | H18: Continue Make opening in guest bedroom 3x3 to reinstall loose Hvac vent, close opening, spackle, sand and paint NOTE: Bc to provide carpet film, plastic drop, spackle, mesh tape, trash bags, sanding sponge, blue tape and all other materials and labor needed to complete the job. / For access, please call Christian 201-705-0879 or Alex 201-713-8719 update the scope of work. Two more openings of 2x4 were required to see where ducts weren't connected. After the ducts were taped with duct tape, there still wasn't air flow. The building asked to please just temporarily close openings so they can do their own investigation tomorrow to see where the problem is. Once they determine and fix it, they will let us know so we can close all openings properly. | I18: AJ Canas Solutions javier | J18: Email | N18: Done
A19: =IFERROR(VLOOKUP(D19,'Master sheet (Clientes)'!A$6:D$747,2,0)," ") -> NJ | B19: =IFERROR(VLOOKUP(D19,'Master sheet (Clientes)'!A$6:D$747,3,0)," ") -> Skylight | C19: =IFERROR(VLOOKUP(D19,'Master sheet (Clientes)'!A$6:D$747,4,0)," ") -> N-O | D19: Riello 99 Gorge Rd, Edgewater, NJ 07020 | E19: 801 | F19: 1BDR | G19: Vacant | H19: Paint unit and cleaning at 8:00am | I19: AJ Canas Solutions William Diaz | J19: Email | N19: Done
A21: State | B21: MANAGEMENT | C21: BC CLERK | D21: BUILDING / ADDRESS | E21: UNIT / AREA | F21: SIZE | G21: WORKSITE STATUS | H21: JOB DESCRIPTION | I21: JOB AWARDED TO: / TECHS QUANTITY: | J21: REQUEST / P.O / WTN / W.O | K21: BC WORK ORDER / BC ESTIMATE | L21: EXTRAS | M21: SPECIAL NOTES / SEQUENCE | N21: VENDORS DAILY STATUS REPORT
A22: =IFERROR(VLOOKUP(D22,'Master sheet (Clientes)'!A$6:D$747,2,0)," ") -> NJ | B22: =IFERROR(VLOOKUP(D22,'Master sheet (Clientes)'!A$6:D$747,3,0)," ") -> Skylight | C22: =IFERROR(VLOOKUP(D22,'Master sheet (Clientes)'!A$6:D$747,4,0)," ") -> N-O | D22: Infinity at Edgewater 340 Old River Rd, Edgewater, NJ 07020 | E22: 523 | F22: 1BDR | G22: Vacant | H22: Paint Unit (Remove and re-install cover plates / Protect all floors/carpets) at 9:00am Note: BC provides the paint, Call Enrique for access: +1 (646) 984-3300 | I22: Atlas Armando Gaona | J22: Email | M22: Carpet / Clean | N22: Paint done
A23: =IFERROR(VLOOKUP(D23,'Master sheet (Clientes)'!A$6:D$747,2,0)," ") -> NJ | B23: =IFERROR(VLOOKUP(D23,'Master sheet (Clientes)'!A$6:D$747,3,0)," ") -> Vivmark Residential | C23: =IFERROR(VLOOKUP(D23,'Master sheet (Clientes)'!A$6:D$747,4,0)," ") -> N-O | D23: Avalon Hoboken 800 Madison St, Hoboken, NJ 07030. | E23: 630 | F23: 2BDR | G23: Occupied | H23: Paint unit at 8:00 am | I23: Atlas Douglas Espinal | J23: PO-1543976 | N23: Done
A25: State | B25: MANAGEMENT | C25: BC CLERK | D25: BUILDING / ADDRESS | E25: UNIT / AREA | F25: SIZE | G25: WORKSITE STATUS | H25: JOB DESCRIPTION | I25: JOB AWARDED TO: / TECHS QUANTITY: | J25: REQUEST / P.O / WTN / W.O | K25: BC WORK ORDER / BC ESTIMATE | L25: EXTRAS | M25: SPECIAL NOTES / SEQUENCE | N25: VENDORS DAILY STATUS REPORT
A26: =IFERROR(VLOOKUP(D26,'Master sheet (Clientes)'!A$6:D$747,2,0)," ") -> NJ | B26: =IFERROR(VLOOKUP(D26,'Master sheet (Clientes)'!A$6:D$747,3,0)," ") -> No Charge / Courtesy Job | C26: =IFERROR(VLOOKUP(D26,'Master sheet (Clientes)'!A$6:D$747,4,0)," ") -> N/A | D26: 1114 92nd St North Bergen, NJ 07047 | H26: Continue 2 techs to install drywall. Spackle and sand | I26: Sanai Pliability Elmer Morales / Santiago Chanchavac | J26: Email | M26: No Charge / Courtesy job for Christian Glaser | N26: Continue Friday
A28: State | B28: MANAGEMENT | C28: BC CLERK | D28: BUILDING / ADDRESS | E28: UNIT / AREA | F28: SIZE | G28: WORKSITE STATUS | H28: JOB DESCRIPTION | I28: JOB AWARDED TO: / TECHS QUANTITY: | J28: REQUEST / P.O / WTN / W.O | K28: BC WORK ORDER / BC ESTIMATE | L28: EXTRAS | M28: SPECIAL NOTES / SEQUENCE | N28: VENDORS DAILY STATUS REPORT
A29: =IFERROR(VLOOKUP(D29,'Master sheet (Clientes)'!A$6:D$747,2,0)," ") -> NJ | B29: =IFERROR(VLOOKUP(D29,'Master sheet (Clientes)'!A$6:D$747,3,0)," ") -> Vivmark Residential | C29: =IFERROR(VLOOKUP(D29,'Master sheet (Clientes)'!A$6:D$747,4,0)," ") -> A-V | D29: The Rivington Apartments 1130 Grand St, Hoboken, NJ 07030. | E29: SG 505 | G29: Occupied | H29: Replace the kitchen kick plate - 5"x16' - 1/8" thickness - Build care provides the new kick plate Hallway vinyl floor replacement 1 board replacement Build care provides the new vinyl floor.at 9:00 am For access call Emilio:+1 (917) 971-4114 | I29: M&J Flooring | J29: Email | N29: Done
A30: =IFERROR(VLOOKUP(D30,'Master sheet (Clientes)'!A$6:D$747,2,0)," ") -> NJ | B30: =IFERROR(VLOOKUP(D30,'Master sheet (Clientes)'!A$6:D$747,3,0)," ") -> Vivmark Residential | C30: =IFERROR(VLOOKUP(D30,'Master sheet (Clientes)'!A$6:D$747,4,0)," ") -> A-V | D30: The Rivington Apartments 1130 Grand St, Hoboken, NJ 07030. | E30: SG 205 | G30: Occupied | H30: Replace kitchen transition molding. at 9:00am Build care provides the molding. | I30: M&J Flooring | J30: Email | N30: Done
A31: =IFERROR(VLOOKUP(D31,'Master sheet (Clientes)'!A$6:D$747,2,0)," ") -> NJ | B31: =IFERROR(VLOOKUP(D31,'Master sheet (Clientes)'!A$6:D$747,3,0)," ") -> Vivmark Residential | C31: =IFERROR(VLOOKUP(D31,'Master sheet (Clientes)'!A$6:D$747,4,0)," ") -> A-V | D31: The Rivington Apartments 1130 Grand St, Hoboken, NJ 07030. | E31: NG 608 | G31: Occupied | H31: Floor repair Last minute request - assigned by property | I31: M&J Flooring | J31: Email pending Roberto | N31: Done
A32: =IFERROR(VLOOKUP(D32,'Master sheet (Clientes)'!A$6:D$747,2,0)," ") -> NJ | B32: =IFERROR(VLOOKUP(D32,'Master sheet (Clientes)'!A$6:D$747,3,0)," ") -> Vivmark Residential | C32: =IFERROR(VLOOKUP(D32,'Master sheet (Clientes)'!A$6:D$747,4,0)," ") -> A-V | D32: The Rivington Apartments 1130 Grand St, Hoboken, NJ 07030. | E32: NG 207 | G32: Occupied | H32: Floor repair Last minute request - assigned by property | I32: M&J Flooring | J32: Email pending Roberto | N32: Done
A34: State | B34: MANAGEMENT | C34: BC CLERK | D34: BUILDING / ADDRESS | E34: UNIT / AREA | F34: SIZE | G34: WORKSITE STATUS | H34: JOB DESCRIPTION | I34: JOB AWARDED TO: / TECHS QUANTITY: | J34: REQUEST / P.O / WTN / W.O | K34: BC WORK ORDER / BC ESTIMATE | L34: EXTRAS | M34: SPECIAL NOTES / SEQUENCE | N34: VENDORS DAILY STATUS REPORT
A35: =IFERROR(VLOOKUP(D35,'Master sheet (Clientes)'!A$6:D$747,2,0)," ") -> NJ | B35: =IFERROR(VLOOKUP(D35,'Master sheet (Clientes)'!A$6:D$747,3,0)," ") -> Vivmark Residential | C35: =IFERROR(VLOOKUP(D35,'Master sheet (Clientes)'!A$6:D$747,4,0)," ") -> A-V | D35: The Rivington Apartments 1130 Grand St, Hoboken, NJ 07030. | E35: SG 310 | F35: 2BDR | G35: Vacant | H35: Unit Cleaning at 8:00 am | I35: YL Cleaning | J35: Email | N35: Done
A36: =IFERROR(VLOOKUP(D36,'Master sheet (Clientes)'!A$6:D$747,2,0)," ") -> NJ | B36: =IFERROR(VLOOKUP(D36,'Master sheet (Clientes)'!A$6:D$747,3,0)," ") -> Post Brothers | C36: =IFERROR(VLOOKUP(D36,'Master sheet (Clientes)'!A$6:D$747,4,0)," ") -> A-V | D36: The Duchess 7601 River Rd, North Bergen, NJ 07047 | E36: 1222 | F36: 2BDR | G36: Vacant | H36: Unit Cleaning at 8:00 am | I36: YL Cleaning | J36: Email | N36: Done
A37: =IFERROR(VLOOKUP(D37,'Master sheet (Clientes)'!A$6:D$747,2,0)," ") -> NJ | B37: =IFERROR(VLOOKUP(D37,'Master sheet (Clientes)'!A$6:D$747,3,0)," ") -> Skylight | C37: =IFERROR(VLOOKUP(D37,'Master sheet (Clientes)'!A$6:D$747,4,0)," ") -> N-O | D37: Infinity at Edgewater 340 Old River Rd, Edgewater, NJ 07020 | E37: 609 | F37: 1BDR | G37: Vacant | H37: Unit Cleaning at 8:00am | I37: YL Cleaning | J37: Email | N37: Done
A38: =IFERROR(VLOOKUP(D38,'Master sheet (Clientes)'!A$6:D$747,2,0)," ") -> NJ | B38: =IFERROR(VLOOKUP(D38,'Master sheet (Clientes)'!A$6:D$747,3,0)," ") -> Vivmark Residential | C38: =IFERROR(VLOOKUP(D38,'Master sheet (Clientes)'!A$6:D$747,4,0)," ") -> N-O | D38: Avalon at Edgewater II New Building (Russell). | E38: 104 | F38: 1BDR | G38: Occupeid | H38: Unit Cleaning after repair after 2pm | I38: YL Cleaning | J38: Email | N38: Done
A39: =IFERROR(VLOOKUP(D39,'Master sheet (Clientes)'!A$6:D$747,2,0)," ") -> NJ | B39: =IFERROR(VLOOKUP(D39,'Master sheet (Clientes)'!A$6:D$747,3,0)," ") -> Vivmark Residential | C39: =IFERROR(VLOOKUP(D39,'Master sheet (Clientes)'!A$6:D$747,4,0)," ") -> N-O | D39: Avalon at Edgewater II New Building (Russell). | E39: 155 | G39: Occupied | H39: Unit Cleaning after repair after 2pm / Last minute request assigned by Carlos Perez | I39: YL Cleaning | J39: Email | M39: Clean 09/02 and 09/03 | N39: Cancelled by Tenant
D41: SOUTH HOBOKEN "7th Street down" - JERSEY CITY - BAYONNE
D42: JERSEY CITY - BC SUPERVISOR: Carlos Perez (862) 383-3884 cperez@build-care.com - BC RUNNER: Juan Sebastian Salazar (862) 394-6010 jssalazar@build-care.com
A44: State | B44: MANAGEMENT | C44: BC CLERK | D44: BUILDING / ADDRESS | E44: UNIT / AREA | F44: SIZE | G44: WORKSITE STATUS | H44: JOB DESCRIPTION | I44: JOB AWARDED TO: / TECHS QUANTITY: | J44: REQUEST / P.O / WTN / W.O | K44: BC WORK ORDER / BC ESTIMATE | L44: EXTRAS | M44: SPECIAL NOTES / SEQUENCE | N44: VENDORS DAILY STATUS REPORT
A45: =IFERROR(VLOOKUP(D45,'Master sheet (Clientes)'!A$6:D$747,2,0)," ") -> NJ | B45: =IFERROR(VLOOKUP(D45,'Master sheet (Clientes)'!A$6:D$747,3,0)," ") -> Skylight | C45: =IFERROR(VLOOKUP(D45,'Master sheet (Clientes)'!A$6:D$747,4,0)," ") -> N-O | D45: Grand Adams Apartments 300 Grand St, Hoboken, NJ 07030 | H45: 1 Daily Handyman to work with the maintenance staff 8hrs shift to cover multiple properties under the instructions of the service general manager Upon Arrival Call Orville (646) 984-3306 from 9:00am to 5:00pm Monday to Friday until further notice Starting Tuesday 02/26/2025 | I45: Cuxil Group Eduardo Garcia | J45: Email | M45: until further notice | N45: Continue
A46: =IFERROR(VLOOKUP(D46,'Master sheet (Clientes)'!A$6:D$747,2,0)," ") -> NJ | B46: =IFERROR(VLOOKUP(D46,'Master sheet (Clientes)'!A$6:D$747,3,0)," ") -> Skylight | C46: =IFERROR(VLOOKUP(D46,'Master sheet (Clientes)'!A$6:D$747,4,0)," ") -> N-O | D46: Grand Adams Apartments 300 Grand St, Hoboken, NJ 07030 | H46: 1 Daily handyman for 8hrs shift to assist the property with internal tasks from Monday to Friday until further notice NOTE: Please Report to Christina 973-776-4602 | I46: Cuxil Group Marcos Garcia | J46: Email | M46: until further notice | N46: Continue
A47: =IFERROR(VLOOKUP(D47,'Master sheet (Clientes)'!A$6:D$747,2,0)," ") -> NJ | B47: =IFERROR(VLOOKUP(D47,'Master sheet (Clientes)'!A$6:D$747,3,0)," ") -> RHO | C47: =IFERROR(VLOOKUP(D47,'Master sheet (Clientes)'!A$6:D$747,4,0)," ") -> A-V | D47: Sable 200 Greene Street, Jersey City, NJ 07311. | H47: 1 Daily Handyman service from Wednesday 09/02/2026 trough Sunday 09/06/2026 Please Report to Nate (201) 466-8357 | I47: Sanai Pliability Delfino Cuxil | J47: Email | M47: Extended until Sunday 09/06 | N47: Continue
A49: State | B49: MANAGEMENT | C49: BC CLERK | D49: BUILDING / ADDRESS | E49: UNIT / AREA | F49: SIZE | G49: WORKSITE STATUS | H49: JOB DESCRIPTION | I49: JOB AWARDED TO: / TECHS QUANTITY: | J49: REQUEST / P.O / WTN / W.O | K49: BC WORK ORDER / BC ESTIMATE | L49: EXTRAS | M49: SPECIAL NOTES / SEQUENCE | N49: VENDORS DAILY STATUS REPORT
A50: =IFERROR(VLOOKUP(D50,'Master sheet (Clientes)'!A$6:D$747,2,0)," ") -> NJ | B50: =IFERROR(VLOOKUP(D50,'Master sheet (Clientes)'!A$6:D$747,3,0)," ") -> Rose Associates | C50: =IFERROR(VLOOKUP(D50,'Master sheet (Clientes)'!A$6:D$747,4,0)," ") -> A-V | D50: VYV Apartments North and South 474 Warren St, Jersey City, NJ 07302. | H50: 1 Daily Handyman Service: Provide a full-time daily handyman to assist the property with make-ready orders from 8:00 am to 4:30 pm. 5 Days per week Monday to Friday Starting Monday 08/03/26 to Friday 10/16/2026 | I50: Atlas Alexis Gomez | J50: Email | M50: 5 days per week Until 10/16 | N50: Continue
A51: =IFERROR(VLOOKUP(D51,'Master sheet (Clientes)'!A$6:D$747,2,0)," ") -> NJ | B51: =IFERROR(VLOOKUP(D51,'Master sheet (Clientes)'!A$6:D$747,3,0)," ") -> Vivmark Residential | C51: =IFERROR(VLOOKUP(D51,'Master sheet (Clientes)'!A$6:D$747,4,0)," ") -> A-V | D51: 70 Greene Apartments 70 Greene St, Jersey City, NJ 07302. | H51: Daily Painter at 8am please report to Jonathan 862-387-9993 | I51: Atlas Javier Santiago | J51: WTN Pending | N51: Done
A52: =IFERROR(VLOOKUP(D52,'Master sheet (Clientes)'!A$6:D$747,2,0)," ") -> NJ | B52: =IFERROR(VLOOKUP(D52,'Master sheet (Clientes)'!A$6:D$747,3,0)," ") -> Dalan Management | C52: =IFERROR(VLOOKUP(D52,'Master sheet (Clientes)'!A$6:D$747,4,0)," ") -> N-O | D52: The Lively Apartments 321 Warren St, Jersey City, NJ 07302 | E52: 1611 | F52: Studio | G52: Vacant | H52: Paint unit and cleaning at 8:00am The building will provide the paint Please call Kyle for access (551) 208-2742 | I52: Atlas Elder Velasquez | J52: Email | N52: Paint done
A54: State | B54: MANAGEMENT | C54: BC CLERK | D54: BUILDING / ADDRESS | E54: UNIT / AREA | F54: SIZE | G54: WORKSITE STATUS | H54: JOB DESCRIPTION | I54: JOB AWARDED TO: / TECHS QUANTITY: | J54: REQUEST / P.O / WTN / W.O | K54: BC WORK ORDER / BC ESTIMATE | L54: EXTRAS | M54: SPECIAL NOTES / SEQUENCE | N54: VENDORS DAILY STATUS REPORT
A55: =IFERROR(VLOOKUP(D55,'Master sheet (Clientes)'!A$6:D$747,2,0)," ") -> NJ | B55: =IFERROR(VLOOKUP(D55,'Master sheet (Clientes)'!A$6:D$747,3,0)," ") -> Vivmark Residential | C55: =IFERROR(VLOOKUP(D55,'Master sheet (Clientes)'!A$6:D$747,4,0)," ") -> A-V | D55: 70 Greene Apartments 70 Greene St, Jersey City, NJ 07302. | E55: 2807 | F55: 1BDR | G55: Vacant | H55: Paint unit and Same-day cleaning at 8:00 am | I55: DVM Marvin Cumes / Celestino Luc | J55: WTN 86388866 | M55: Same-day clean - rescheduled by Carlos | N55: Paint done
A56: =IFERROR(VLOOKUP(D56,'Master sheet (Clientes)'!A$6:D$747,2,0)," ") -> NJ | B56: =IFERROR(VLOOKUP(D56,'Master sheet (Clientes)'!A$6:D$747,3,0)," ") -> Vivmark Residential | C56: =IFERROR(VLOOKUP(D56,'Master sheet (Clientes)'!A$6:D$747,4,0)," ") -> A-V | D56: 70 Greene Apartments 70 Greene St, Jersey City, NJ 07302. | E56: 3102 | F56: Studio | G56: Vacant | H56: Paint unit at 8:00 am | I56: DVM Marvin Cumes / Celestino Luc | J56: WTN 86388866 | M56: Clean 09/03 | N56: Paint done
A57: =IFERROR(VLOOKUP(D57,'Master sheet (Clientes)'!A$6:D$747,2,0)," ") -> NJ | B57: =IFERROR(VLOOKUP(D57,'Master sheet (Clientes)'!A$6:D$747,3,0)," ") -> Vivmark Residential | C57: =IFERROR(VLOOKUP(D57,'Master sheet (Clientes)'!A$6:D$747,4,0)," ") -> A-V | D57: 70 Greene Apartments 70 Greene St, Jersey City, NJ 07302. | E57: 2408 | F57: 1BDR | G57: Vacant | H57: Paint unit at 8:00am | I57: DVM Marvin Cumes / Celestino Luc | J57: WTN 86388866 | M57: Clean 09/03 | N57: Paint done
A58: =IFERROR(VLOOKUP(D58,'Master sheet (Clientes)'!A$6:D$747,2,0)," ") -> NJ | B58: =IFERROR(VLOOKUP(D58,'Master sheet (Clientes)'!A$6:D$747,3,0)," ") -> Vivmark Residential | C58: =IFERROR(VLOOKUP(D58,'Master sheet (Clientes)'!A$6:D$747,4,0)," ") -> A-V | D58: 70 Greene Apartments 70 Greene St, Jersey City, NJ 07302. | H58: 1 Daily handyman at 8am please report to Jonathan 862-387-9993 | I58: DVM Juan Mendoza | J58: WTN Pending | N58: Done
A60: State | B60: MANAGEMENT | C60: BC CLERK | D60: BUILDING / ADDRESS | E60: UNIT / AREA | F60: SIZE | G60: WORKSITE STATUS | H60: JOB DESCRIPTION | I60: JOB AWARDED TO: / TECHS QUANTITY: | J60: REQUEST / P.O / WTN / W.O | K60: BC WORK ORDER / BC ESTIMATE | L60: EXTRAS | M60: SPECIAL NOTES / SEQUENCE | N60: VENDORS DAILY STATUS REPORT
A61: =IFERROR(VLOOKUP(D61,'Master sheet (Clientes)'!A$6:D$747,2,0)," ") -> NJ | B61: =IFERROR(VLOOKUP(D61,'Master sheet (Clientes)'!A$6:D$747,3,0)," ") -> Skylight | C61: =IFERROR(VLOOKUP(D61,'Master sheet (Clientes)'!A$6:D$747,4,0)," ") -> N-O | D61: Grand Adams Apartments 300 Grand St, Hoboken, NJ 07030 | E61: 410 | F61: Studio | G61: Vacant | H61: Paint unit and cleaning at 8:00 am | I61: Alluda Misal Yojero | J61: Email | N61: Paint done
A62: =IFERROR(VLOOKUP(D62,'Master sheet (Clientes)'!A$6:D$747,2,0)," ") -> NJ | B62: =IFERROR(VLOOKUP(D62,'Master sheet (Clientes)'!A$6:D$747,3,0)," ") -> Vivmark Residential | C62: =IFERROR(VLOOKUP(D62,'Master sheet (Clientes)'!A$6:D$747,4,0)," ") -> A-V | D62: The Pier Apartments 1 Harborside Pl, Jersey City, NJ 07311. | E62: 542 | F62: 1BDR | G62: Vacant | H62: Paint unit (color change) at 8:00 am | I62: Alluda Anibal Yojero | J62: WTN 85884977 | M62: Clean 09/03 | N62: Paint done
A63: =IFERROR(VLOOKUP(D63,'Master sheet (Clientes)'!A$6:D$747,2,0)," ") -> NJ | B63: =IFERROR(VLOOKUP(D63,'Master sheet (Clientes)'!A$6:D$747,3,0)," ") -> Skylight | C63: =IFERROR(VLOOKUP(D63,'Master sheet (Clientes)'!A$6:D$747,4,0)," ") -> N-O | D63: 221 Washington St, Hoboken, NJ 07030 | E63: 303 | F63: 1BDR | G63: Vacant | H63: Paint Unit and cleaning at 8:00am For Access, please call Orville 646-984-3306 | I63: Alluda Arturo Lopez | J63: Email | N63: Paint done
A65: State | B65: MANAGEMENT | C65: BC CLERK | D65: BUILDING / ADDRESS | E65: UNIT / AREA | F65: SIZE | G65: WORKSITE STATUS | H65: JOB DESCRIPTION | I65: JOB AWARDED TO: / TECHS QUANTITY: | J65: REQUEST / P.O / WTN / W.O | K65: BC WORK ORDER / BC ESTIMATE | L65: EXTRAS | M65: SPECIAL NOTES / SEQUENCE | N65: VENDORS DAILY STATUS REPORT
A66: =IFERROR(VLOOKUP(D66,'Master sheet (Clientes)'!A$6:D$747,2,0)," ") -> NJ | B66: =IFERROR(VLOOKUP(D66,'Master sheet (Clientes)'!A$6:D$747,3,0)," ") -> Vivmark Residential | C66: =IFERROR(VLOOKUP(D66,'Master sheet (Clientes)'!A$6:D$747,4,0)," ") -> A-V | D66: 70 Greene Apartments 70 Greene St, Jersey City, NJ 07302. | E66: 2807 | F66: 1BDR | G66: Vacant | H66: Unit cleaning AFTER 2:00 PM NOTE: Same-day paint | I66: YL Cleaning | J66: WTN 86388686 | M66: rescheduled by Carlos | N66: Done
A67: =IFERROR(VLOOKUP(D67,'Master sheet (Clientes)'!A$6:D$747,2,0)," ") -> NJ | B67: =IFERROR(VLOOKUP(D67,'Master sheet (Clientes)'!A$6:D$747,3,0)," ") -> Vivmark Residential | C67: =IFERROR(VLOOKUP(D67,'Master sheet (Clientes)'!A$6:D$747,4,0)," ") -> A-V | D67: 70 Greene Apartments 70 Greene St, Jersey City, NJ 07302. | E67: 3107 | F67: 1BDR | G67: Vacant | H67: Unit cleaning at 8:00 am | I67: YL Cleaning | J67: WTN 86388686 | N67: Done
A68: =IFERROR(VLOOKUP(D68,'Master sheet (Clientes)'!A$6:D$747,2,0)," ") -> NJ | B68: =IFERROR(VLOOKUP(D68,'Master sheet (Clientes)'!A$6:D$747,3,0)," ") -> Vivmark Residential | C68: =IFERROR(VLOOKUP(D68,'Master sheet (Clientes)'!A$6:D$747,4,0)," ") -> A-V | D68: Portside Towers Apartments 155 Washington St, Jersey City, NJ 07302. | E68: 1408W | F68: 1BDR | G68: Vacant | H68: Unit cleaning at 8:00 am | I68: YL Cleaning | J68: WTN 86393684 | M68: This job it was done on 09/01 | N68: cancelled
A69: =IFERROR(VLOOKUP(D69,'Master sheet (Clientes)'!A$6:D$747,2,0)," ") -> NJ | B69: =IFERROR(VLOOKUP(D69,'Master sheet (Clientes)'!A$6:D$747,3,0)," ") -> Greystar | C69: =IFERROR(VLOOKUP(D69,'Master sheet (Clientes)'!A$6:D$747,4,0)," ") -> A-V | D69: Liberty Bay Club Apartments 190 W 54th St, Bayonne, NJ 07002 | E69: 239 | F69: 2BDR | G69: Vacant | H69: Unit cleaning at 8:00 am | I69: YL Cleaning | J69: Email | N69: Done
A70: =IFERROR(VLOOKUP(D70,'Master sheet (Clientes)'!A$6:D$747,2,0)," ") -> NJ | B70: =IFERROR(VLOOKUP(D70,'Master sheet (Clientes)'!A$6:D$747,3,0)," ") -> Greystar | C70: =IFERROR(VLOOKUP(D70,'Master sheet (Clientes)'!A$6:D$747,4,0)," ") -> A-V | D70: Liberty Bay Club Apartments 190 W 54th St, Bayonne, NJ 07002 | E70: 147 | F70: 1BDR | G70: Vacant | H70: Unit cleaning at 8:00 am | I70: YL Cleaning | J70: Email | N70: Done
A71: =IFERROR(VLOOKUP(D71,'Master sheet (Clientes)'!A$6:D$747,2,0)," ") -> NJ | B71: =IFERROR(VLOOKUP(D71,'Master sheet (Clientes)'!A$6:D$747,3,0)," ") -> Greystar | C71: =IFERROR(VLOOKUP(D71,'Master sheet (Clientes)'!A$6:D$747,4,0)," ") -> A-V | D71: Liberty Bay Club Apartments 190 W 54th St, Bayonne, NJ 07002 | E71: 109 | F71: 1BDR | G71: Vacant | H71: Unit cleaning at 8:00 am | I71: YL Cleaning | J71: Email | N71: Done
A73: State | B73: MANAGEMENT | C73: BC CLERK | D73: BUILDING / ADDRESS | E73: UNIT / AREA | F73: SIZE | G73: WORKSITE STATUS | H73: JOB DESCRIPTION | I73: JOB AWARDED TO: / TECHS QUANTITY: | J73: REQUEST / P.O / WTN / W.O | K73: BC WORK ORDER / BC ESTIMATE | L73: EXTRAS | M73: SPECIAL NOTES / SEQUENCE | N73: VENDORS DAILY STATUS REPORT
A74: =IFERROR(VLOOKUP(D74,'Master sheet (Clientes)'!A$6:D$747,2,0)," ") -> NJ | B74: =IFERROR(VLOOKUP(D74,'Master sheet (Clientes)'!A$6:D$747,3,0)," ") -> Bozzuto | C74: =IFERROR(VLOOKUP(D74,'Master sheet (Clientes)'!A$6:D$747,4,0)," ") -> N-O | D74: Birch House 49 Fisk St, Jersey City, NJ 07305 | E74: 201 | F74: 1BDR | G74: Vacant | H74: Unit Cleaning at 8:00am | I74: Atlas Way Cleaning | J74: Email | N74: Done
A75: =IFERROR(VLOOKUP(D75,'Master sheet (Clientes)'!A$6:D$747,2,0)," ") -> NJ | B75: =IFERROR(VLOOKUP(D75,'Master sheet (Clientes)'!A$6:D$747,3,0)," ") -> Bozzuto | C75: =IFERROR(VLOOKUP(D75,'Master sheet (Clientes)'!A$6:D$747,4,0)," ") -> N-O | D75: The Morgan 160 Morgan St, Jersey City, NJ | E75: 609 | F75: Studio | G75: Vacant | H75: Unit cleaning at 8:00am | I75: Atlas Way Cleaning | J75: Email | N75: Done
A77: State | B77: MANAGEMENT | C77: BC CLERK | D77: BUILDING / ADDRESS | E77: UNIT / AREA | F77: SIZE | G77: WORKSITE STATUS | H77: JOB DESCRIPTION | I77: JOB AWARDED TO: / TECHS QUANTITY: | J77: REQUEST / P.O / WTN / W.O | K77: BC WORK ORDER / BC ESTIMATE | L77: EXTRAS | M77: SPECIAL NOTES / SEQUENCE | N77: VENDORS DAILY STATUS REPORT
A78: =IFERROR(VLOOKUP(D78,'Master sheet (Clientes)'!A$6:D$747,2,0)," ") -> NJ | B78: =IFERROR(VLOOKUP(D78,'Master sheet (Clientes)'!A$6:D$747,3,0)," ") -> Greystar | C78: =IFERROR(VLOOKUP(D78,'Master sheet (Clientes)'!A$6:D$747,4,0)," ") -> A-V | D78: BELA 74 Maple St, Jersey City, NJ 07304 | E78: 801 | F78: 2BDR | G78: Vacant | H78: 1 tub reglaze | I78: Felix R Santos | J78: Email | N78: Done
A79: =IFERROR(VLOOKUP(D79,'Master sheet (Clientes)'!A$6:D$747,2,0)," ") -> NJ | B79: =IFERROR(VLOOKUP(D79,'Master sheet (Clientes)'!A$6:D$747,3,0)," ") -> KRE Group Management | C79: =IFERROR(VLOOKUP(D79,'Master sheet (Clientes)'!A$6:D$747,4,0)," ") -> A-V | D79: Grove Pointe 100 Christopher Columbus Drive, Jersey City, NJ 07302 | E79: 1617 | G79: Vacant | H79: 1 Tub reglaze | I79: Felix R Santos | J79: Email | N79: Done
A80: =IFERROR(VLOOKUP(D80,'Master sheet (Clientes)'!A$6:D$747,2,0)," ") -> NJ | B80: =IFERROR(VLOOKUP(D80,'Master sheet (Clientes)'!A$6:D$747,3,0)," ") -> KRE Group Management | C80: =IFERROR(VLOOKUP(D80,'Master sheet (Clientes)'!A$6:D$747,4,0)," ") -> A-V | D80: Grove Pointe 100 Christopher Columbus Drive, Jersey City, NJ 07302 | E80: 1619 | G80: Vacant | H80: 1 Tub reglaze | I80: Felix R Santos | J80: Email | N80: Done
D82: NEWPORT
D83: BC SUPERVISOR: Jhonatan Perez (201) 800-5601 jperez@build-care.com / BC RUNNER: Eduard Bonifacio (551) 242-5958 purchases@build-care.com
A85: State | B85: MANAGEMENT | C85: BC CLERK | D85: BUILDING / ADDRESS | E85: UNIT / AREA | F85: SIZE | G85: WORKSITE STATUS | H85: JOB DESCRIPTION | I85: JOB AWARDED TO: / TECHS QUANTITY: | J85: REQUEST / P.O / WTN / W.O | K85: BC WORK ORDER / BC ESTIMATE | L85: EXTRAS | M85: SPECIAL NOTES / SEQUENCE | N85: VENDORS DAILY STATUS REPORT
A86: =IFERROR(VLOOKUP(D86,'Master sheet (Clientes)'!A$6:D$747,2,0)," ") -> NJ | B86: =IFERROR(VLOOKUP(D86,'Master sheet (Clientes)'!A$6:D$747,3,0)," ") -> C/O Realty | C86: =IFERROR(VLOOKUP(D86,'Master sheet (Clientes)'!A$6:D$747,4,0)," ") -> N-O | D86: Pacific at Newport 25 River Dr S, Jersey City, NJ 07310 | H86: 1 handyman for 5 days Assist the property with handyman tasks work orders / make ready from Monday 08/31/26 through Friday 09/04/26 at 8am Note: send Othoniel Gonzalez | I86: Cuxil Group Ottoniel Gonzales | J86: PO Pending | K86: Estimate 17341 | M86: Until Friday 09/04 | N86: Continue
A87: =IFERROR(VLOOKUP(D87,'Master sheet (Clientes)'!A$6:D$747,2,0)," ") -> NJ | B87: =IFERROR(VLOOKUP(D87,'Master sheet (Clientes)'!A$6:D$747,3,0)," ") -> C/O Realty | C87: =IFERROR(VLOOKUP(D87,'Master sheet (Clientes)'!A$6:D$747,4,0)," ") -> N-O | D87: Pacific at Newport 25 River Dr S, Jersey City, NJ 07310 | H87: 2 daily painters for 6 days Assist the property with painter tasks from Saturday 08/28/26 and Monday 08/31/26 through Friday 09/04/26 at 8am Note: property will provide all the materials and supervision | I87: Cuxil Group Edgar Lool / Sanai Pliability Luis Garcia | J87: PO Pending | K87: Estimate 17343 | M87: Until Friday 09/04 | N87: Continue
A88: =IFERROR(VLOOKUP(D88,'Master sheet (Clientes)'!A$6:D$747,2,0)," ") -> NJ | B88: =IFERROR(VLOOKUP(D88,'Master sheet (Clientes)'!A$6:D$747,3,0)," ") -> C/O Realty | C88: =IFERROR(VLOOKUP(D88,'Master sheet (Clientes)'!A$6:D$747,4,0)," ") -> N-O | D88: Parkside West at Newport 40 Newport Parkway, Jersey City, NJ | H88: 1 handyman for 20 days Job: assist the property with handyman work work orders / make ready Schedule from Tuesday 08/25/26 through Saturday 08/29/26 Monday 08/31/26 through Friday 09/04/26 Tuesday 09/08/26 through Saturday 09/12/26 Monday 09/14/26 through Friday 09/18/26 at 8am Note: send Geovanny Saldivar Note: handyman will not work Monday 09/07/26 due to Labor Day holiday | I88: Cuxil Group Giovanny Saldivar | J88: PO Pending | M88: Until Fri 09/18 | N88: Continue
A89: =IFERROR(VLOOKUP(D89,'Master sheet (Clientes)'!A$6:D$747,2,0)," ") -> NJ | B89: =IFERROR(VLOOKUP(D89,'Master sheet (Clientes)'!A$6:D$747,3,0)," ") -> C/O Realty | C89: =IFERROR(VLOOKUP(D89,'Master sheet (Clientes)'!A$6:D$747,4,0)," ") -> N-O | D89: Parkside East at Newport 30 Newport Parkway, Jersey City, NJ | H89: 1 handyman for 20 days Job: assist the property with handyman work work orders / make ready Schedule from Tuesday 08/25/26 through Saturday 08/29/26 Monday 08/31/26 through Friday 09/04/26 Tuesday 09/08/26 through Saturday 09/12/26 Monday 09/14/26 through Friday 09/18/26 at 8am Note: send Oscar Monasterio Note: handyman will not work Monday 09/07/26 due to Labor Day holiday | I89: Cuxil Group Oscar Monasterio | J89: PO Pending | M89: Until Fri 09/18 | N89: Continue
A90: =IFERROR(VLOOKUP(D90,'Master sheet (Clientes)'!A$6:D$747,2,0)," ") -> NJ | B90: =IFERROR(VLOOKUP(D90,'Master sheet (Clientes)'!A$6:D$747,3,0)," ") -> C/O Realty | C90: =IFERROR(VLOOKUP(D90,'Master sheet (Clientes)'!A$6:D$747,4,0)," ") -> N-O | D90: East Hampton at Newport 30 River Ct, Jersey City, NJ 07310 | E90: 415 | F90: 1BDR | G90: Vacant | H90: Continue Full Renovation: Popcorn ceiling removal / renovation Bathroom / install kitchen backsplash / Paint entire unit incluiding ceiling | I90: Sanai Piability Extras de Jairo Cuxil | J90: PO Pending | N90: Continue
A91: =IFERROR(VLOOKUP(D91,'Master sheet (Clientes)'!A$6:D$747,2,0)," ") -> NJ | B91: =IFERROR(VLOOKUP(D91,'Master sheet (Clientes)'!A$6:D$747,3,0)," ") -> C/O Realty | C91: =IFERROR(VLOOKUP(D91,'Master sheet (Clientes)'!A$6:D$747,4,0)," ") -> N-O | D91: Riverside at Newport 1 River Ct, Jersey City, NJ 07310 | E91: Garage 2nd floor | H91: 1 handyman for 10 days Assist the property with bathroom vanities repair from Monday 08/24/26 through Friday 08/28/26 - Monday 08/31/26 through Friday 09/04/26 at 8:30am Note: property to provide all materials and supervision Note: send David Pineda Must contact Karan upon arrival UPDATE: Tuesday 09/01 to Saturday 09/05 | I91: Cuxil Group David Pineda | J91: PO Pending | M91: Until Fri 09/04 | N91: Continue
A92: =IFERROR(VLOOKUP(D92,'Master sheet (Clientes)'!A$6:D$747,2,0)," ") -> NJ | B92: =IFERROR(VLOOKUP(D92,'Master sheet (Clientes)'!A$6:D$747,3,0)," ") -> C/O Realty | C92: =IFERROR(VLOOKUP(D92,'Master sheet (Clientes)'!A$6:D$747,4,0)," ") -> N-O | D92: Roosevelt House at Hamilton Park 180 10th St, Jersey City, NJ 07302 | H92: 1 handyman work for 15 days Assist the property with handyman tasks - work order / turns Sunday 08/16/26 through Thursday 08/20/26 - Sunday 08/23/26 through Thursday 08/27/26 Sunday 08/30/26 through Thursday 09/03/26 from 9am to 5:30pm Note: send Michael Garcia | I92: Sanai pliability Mayco Garcia | J92: PO Pending | K92: Estimate 17232 | M92: Until Thu 09/03 | N92: Continue
A93: =IFERROR(VLOOKUP(D93,'Master sheet (Clientes)'!A$6:D$747,2,0)," ") -> NJ | B93: =IFERROR(VLOOKUP(D93,'Master sheet (Clientes)'!A$6:D$747,3,0)," ") -> C/O Realty | C93: =IFERROR(VLOOKUP(D93,'Master sheet (Clientes)'!A$6:D$747,4,0)," ") -> N-O | D93: Southampton at Newport 20 River Ct, Jersey City, NJ 07310 | H93: 1 handyman for 15 days Assist the property with handyman task work orders / make ready from Tuesday 08/18/26 through Saturday 08/22/26, Tuesday 08/25/26 through Saturday 08/29/26 , Tuesday 09/01/26 through Saturday 09/05/26 from 10am to 6:30pm | I93: Sanai Pliability Wilber Ramirez | J93: PO Pending | K93: Estimate 17233 | N93: Continue
A94: =IFERROR(VLOOKUP(D94,'Master sheet (Clientes)'!A$6:D$747,2,0)," ") -> NJ | B94: =IFERROR(VLOOKUP(D94,'Master sheet (Clientes)'!A$6:D$747,3,0)," ") -> C/O Realty | C94: =IFERROR(VLOOKUP(D94,'Master sheet (Clientes)'!A$6:D$747,4,0)," ") -> N-O | D94: Pacific at Newport 25 River Dr S, Jersey City, NJ 07310 | E94: 1409 | F94: 2BDR | G94: Vacant | H94: Continue Full laundry room build-up: Framing | I94: Cuxil group Extra de Demetrio Semeya | J94: PO Pending | K94: Estimate 17169 | N94: Continue
A95: =IFERROR(VLOOKUP(D95,'Master sheet (Clientes)'!A$6:D$747,2,0)," ") -> NJ | B95: =IFERROR(VLOOKUP(D95,'Master sheet (Clientes)'!A$6:D$747,3,0)," ") -> C/O Realty | C95: =IFERROR(VLOOKUP(D95,'Master sheet (Clientes)'!A$6:D$747,4,0)," ") -> N-O | D95: Pacific at Newport 25 River Dr S, Jersey City, NJ 07310 | E95: 2504 | H95: Continue Laundry Room Construction framing and demo work | I95: Cuxil group Juan Garcia | J95: PO Pending | K95: Estimate 17249 | N95: Done
A96: =IFERROR(VLOOKUP(D96,'Master sheet (Clientes)'!A$6:D$747,2,0)," ") -> NJ | B96: =IFERROR(VLOOKUP(D96,'Master sheet (Clientes)'!A$6:D$747,3,0)," ") -> C/O Realty | C96: =IFERROR(VLOOKUP(D96,'Master sheet (Clientes)'!A$6:D$747,4,0)," ") -> N-O | D96: Aquablu at Newport 110 River Dr S, Jersey City, NJ 07310 | E96: 5th floor hallway near unit 527 | H96: Continue Drywall Demo+Repairs: Demo drywall on ceiling to allow plumbing work.\ Size of the opening: 8 ft x 4 ft and 2 ft x 8 ft.\ Remove and save an existing door access panel.\ Once plumbing repairs are completed by others, install new drywall to seal the demo area.\ Tape, spackle, sand, and prime newly installed drywall.\ Paint repaired ceiling areas using flat white paint.\ Use property-provided paint to perform touch-up painting on walls as needed. | I96: Cuxil Group / Sanai Plaibility | J96: PO Pending | K96: Estimate 17317 | M96: We will return 09/02 in the afternoon to begin sealing demo areas once their plumber has completed their work. | N96: Rescheduled for next day
A97: =IFERROR(VLOOKUP(D97,'Master sheet (Clientes)'!A$6:D$747,2,0)," ") -> NJ | B97: =IFERROR(VLOOKUP(D97,'Master sheet (Clientes)'!A$6:D$747,3,0)," ") -> C/O Realty | C97: =IFERROR(VLOOKUP(D97,'Master sheet (Clientes)'!A$6:D$747,4,0)," ") -> N-O | D97: Atlantic at Newport 31 River Ct, Jersey City, NJ 07310 | H97: 1 handyman for 1 day Assist the property with handyman tasks work orders / make ready at 8:00am Property will provide all materials and supervision Note: Send Enrique Cumez | I97: Sanai Plaibility Eddy Cumes | J97: PO Pending | N97: Done
A98: =IFERROR(VLOOKUP(D98,'Master sheet (Clientes)'!A$6:D$747,2,0)," ") -> NJ | B98: =IFERROR(VLOOKUP(D98,'Master sheet (Clientes)'!A$6:D$747,3,0)," ") -> C/O Realty | C98: =IFERROR(VLOOKUP(D98,'Master sheet (Clientes)'!A$6:D$747,4,0)," ") -> N-O | D98: Pacific at Newport 25 River Dr S, Jersey City, NJ 07310 | E98: 1907 | F98: 1BDR | G98: Vacant | H98: Continue Full laundry room build-up: Framing | I98: Sanai Plaibility Extra de Jairo Cuxil | J98: PO Pending | K98: Estimate 17168 | N98: Done
A99: =IFERROR(VLOOKUP(D99,'Master sheet (Clientes)'!A$6:D$747,2,0)," ") -> NJ | B99: =IFERROR(VLOOKUP(D99,'Master sheet (Clientes)'!A$6:D$747,3,0)," ") -> C/O Realty | C99: =IFERROR(VLOOKUP(D99,'Master sheet (Clientes)'!A$6:D$747,4,0)," ") -> N-O | D99: Pacific at Newport 25 River Dr S, Jersey City, NJ 07310 | E99: 2007 | F99: 1BDR | G99: Vacant | H99: Continue Renovation: Popcorn ceiling removal / renovation Bathroom / install kitchen backsplash / Paint unit | I99: Cuxil Group / Sanai Plaibility Extras | J99: PO Pending | N99: Continue
A100: =IFERROR(VLOOKUP(D100,'Master sheet (Clientes)'!A$6:D$747,2,0)," ") -> NJ | B100: =IFERROR(VLOOKUP(D100,'Master sheet (Clientes)'!A$6:D$747,3,0)," ") -> C/O Realty | C100: =IFERROR(VLOOKUP(D100,'Master sheet (Clientes)'!A$6:D$747,4,0)," ") -> N-O | D100: Pacific at Newport 25 River Dr S, Jersey City, NJ 07310 | E100: 1701 | F100: ??? | G100: ??? | H100: AC Sleeve Replacement at 9:00am | I100: Cuxil Group Demetrio Semeya | J100: PO Pending | K100: Estimate 17336 | N100: Done
A101: =IFERROR(VLOOKUP(D101,'Master sheet (Clientes)'!A$6:D$747,2,0)," ") -> NJ | B101: =IFERROR(VLOOKUP(D101,'Master sheet (Clientes)'!A$6:D$747,3,0)," ") -> C/O Realty | C101: =IFERROR(VLOOKUP(D101,'Master sheet (Clientes)'!A$6:D$747,4,0)," ") -> N-O | D101: Aquablu at Newport 110 River Dr S, Jersey City, NJ 07310 | E101: 3208 | G101: Vacant | H101: 1 handymen work for 1 day - make ready Note: send Lorenzo Vaquiax | I101: Sanai Plaibility Lorenzo Vaquiax | J101: PO Pending | M101: Please note only one handyman was sent today to this unit today due to our schedule being at capacity . | N101: Continue
A102: =IFERROR(VLOOKUP(D102,'Master sheet (Clientes)'!A$6:D$747,2,0)," ") -> NJ | B102: =IFERROR(VLOOKUP(D102,'Master sheet (Clientes)'!A$6:D$747,3,0)," ") -> C/O Realty | C102: =IFERROR(VLOOKUP(D102,'Master sheet (Clientes)'!A$6:D$747,4,0)," ") -> N-O | D102: Pacific at Newport 25 River Dr S, Jersey City, NJ 07310 | E102: 2504 | G102: Vacant | H102: 1 handyman for 1 day make ready at 8:00am | I102: Cuxil Group / Sanai Plaibility | J102: PO Pending | N102: Unit not ready for Make ready yet
A103: =IFERROR(VLOOKUP(D103,'Master sheet (Clientes)'!A$6:D$747,2,0)," ") -> NJ | B103: =IFERROR(VLOOKUP(D103,'Master sheet (Clientes)'!A$6:D$747,3,0)," ") -> C/O Realty | C103: =IFERROR(VLOOKUP(D103,'Master sheet (Clientes)'!A$6:D$747,4,0)," ") -> N-O | D103: Atlantic at Newport 31 River Ct, Jersey City, NJ 07310 | E103: 2707 & 2609 | G103: Vacant | H103: One (1) handyman to install washer/dryer Please send Enrique | I103: Sanai Plaibility Extra de Eddy Cumes | J103: PO749336 | N103: Done
A104: =IFERROR(VLOOKUP(D104,'Master sheet (Clientes)'!A$6:D$747,2,0)," ") -> NJ | B104: =IFERROR(VLOOKUP(D104,'Master sheet (Clientes)'!A$6:D$747,3,0)," ") -> C/O Realty | C104: =IFERROR(VLOOKUP(D104,'Master sheet (Clientes)'!A$6:D$747,4,0)," ") -> N-O | D104: Riverside at Newport 1 River Ct, Jersey City, NJ 07310 | E104: 2905 | F104: 2BDR | G104: Vacant | H104: 1 handyman for continue make ready | I104: Sanai Plaibility Sergio Chex | J104: PO Pending | M104: Please note only one handyman was sent today to this unit today due to our schedule being at capacity . | N104: Continue
A105: =IFERROR(VLOOKUP(D105,'Master sheet (Clientes)'!A$6:D$747,2,0)," ") -> NJ | B105: =IFERROR(VLOOKUP(D105,'Master sheet (Clientes)'!A$6:D$747,3,0)," ") -> C/O Realty | C105: =IFERROR(VLOOKUP(D105,'Master sheet (Clientes)'!A$6:D$747,4,0)," ") -> N-O | D105: Riverside at Newport 1 River Ct, Jersey City, NJ 07310 | E105: Garage | H105: 1 Laborer to assist the property organize storage room | I105: Sanai Plaibility Alexander Polanco | J105: PO Pending | N105: Done
A106: =IFERROR(VLOOKUP(D106,'Master sheet (Clientes)'!A$6:D$747,2,0)," ") -> NJ | B106: =IFERROR(VLOOKUP(D106,'Master sheet (Clientes)'!A$6:D$747,3,0)," ") -> C/O Realty | C106: =IFERROR(VLOOKUP(D106,'Master sheet (Clientes)'!A$6:D$747,4,0)," ") -> N-O | D106: Ellipse at Newport 25 Park Ln S, Jersey City, NJ 07310 | E106: 3310 | G106: Occupied | H106: Bathroom Ceramic Tile Repair: Install new moisture resistant drywall to seal existing demo area. \ Install property provided tiles to repair area. \ Apply grout to newly installed tiles, matching property specs. | I106: Cuxil Group Extra de Edgar Cuxil | J106: PO Pending | K106: Estimate 17393 | N106: Done
A107: =IFERROR(VLOOKUP(D107,'Master sheet (Clientes)'!A$6:D$747,2,0)," ") -> NJ | B107: =IFERROR(VLOOKUP(D107,'Master sheet (Clientes)'!A$6:D$747,3,0)," ") -> C/O Realty | C107: =IFERROR(VLOOKUP(D107,'Master sheet (Clientes)'!A$6:D$747,4,0)," ") -> N-O | D107: Atlantic at Newport 31 River Ct, Jersey City, NJ 07310 | E107: 3508 | G107: Occupied | H107: AC Sleeve Replacement: Remove existing AC unit and sleeve. -Reinforce existing frame for new sleeve and PTAC installation. -Install new PTAC and sleeve following original set up and specs. -Perform drywall and insulation repairs as needed upon PTAC and sleeve installation. -Tape, spackle, sand and prime all repaired areas. -Apply one (1) coat of paint to repaired areas once PTAC sleeve and dry wall repairs are completed. at 9:00am | I107: Sanai Plaibility Jairo Cuxil | J107: PO Pending | K107: Estimate 17401 | N107: Done
A108: =IFERROR(VLOOKUP(D108,'Master sheet (Clientes)'!A$6:D$747,2,0)," ") -> NJ | B108: =IFERROR(VLOOKUP(D108,'Master sheet (Clientes)'!A$6:D$747,3,0)," ") -> C/O Realty | C108: =IFERROR(VLOOKUP(D108,'Master sheet (Clientes)'!A$6:D$747,4,0)," ") -> N-O | D108: Riverside at Newport 1 River Ct, Jersey City, NJ 07310 | H108: Provide (2) full-time painters for (3) days to assist the property with painter's tasks.Wednesday 09/02/26 through Friday 09/04/26 | I108: Cuxil Group Yovanny Olgadez / Sanai Pliability Josue Olgadez | J108: PO Pending | K108: Estimate 17304 | N108: Continue
A109: =IFERROR(VLOOKUP(D109,'Master sheet (Clientes)'!A$6:D$747,2,0)," ") -> NJ | B109: =IFERROR(VLOOKUP(D109,'Master sheet (Clientes)'!A$6:D$747,3,0)," ") -> C/O Realty | C109: =IFERROR(VLOOKUP(D109,'Master sheet (Clientes)'!A$6:D$747,4,0)," ") -> N-O | D109: Atlantic at Newport 31 River Ct, Jersey City, NJ 07310 | E109: 1202 | G109: Vacant | H109: Full laundry room build up - Metal framing | I109: Cuxil Group Edgar Cuxil | J109: PO Pending | K109: Estimate 17407 | N109: Continue after electricity and plumbing made by others
A111: State | B111: MANAGEMENT | C111: BC CLERK | D111: BUILDING / ADDRESS | E111: UNIT / AREA | F111: SIZE | G111: WORKSITE STATUS | H111: JOB DESCRIPTION | I111: JOB AWARDED TO: / TECHS QUANTITY: | J111: REQUEST / P.O / WTN / W.O | K111: BC WORK ORDER / BC ESTIMATE | L111: EXTRAS | M111: SPECIAL NOTES / SEQUENCE | N111: VENDORS DAILY STATUS REPORT
A112: =IFERROR(VLOOKUP(D112,'Master sheet (Clientes)'!A$6:D$747,2,0)," ") -> NJ | B112: =IFERROR(VLOOKUP(D112,'Master sheet (Clientes)'!A$6:D$747,3,0)," ") -> C/O Realty | C112: =IFERROR(VLOOKUP(D112,'Master sheet (Clientes)'!A$6:D$747,4,0)," ") -> N-O | D112: Atlantic at Newport 31 River Ct, Jersey City, NJ 07310 | E112: 1202 | G112: Vacant | H112: Full laundry room build up - electrical work | I112: Cuxil Group Electrical | J112: PO Pending | K112: Estimate 17407 | N112: Cancelled
A114: State | B114: MANAGEMENT | C114: BC CLERK | D114: BUILDING / ADDRESS | E114: UNIT / AREA | F114: SIZE | G114: WORKSITE STATUS | H114: JOB DESCRIPTION | I114: JOB AWARDED TO: / TECHS QUANTITY: | J114: REQUEST / P.O / WTN / W.O | K114: BC WORK ORDER / BC ESTIMATE | L114: EXTRAS | M114: SPECIAL NOTES / SEQUENCE | N114: VENDORS DAILY STATUS REPORT
A115: =IFERROR(VLOOKUP(D115,'Master sheet (Clientes)'!A$6:D$747,2,0)," ") -> NJ | B115: =IFERROR(VLOOKUP(D115,'Master sheet (Clientes)'!A$6:D$747,3,0)," ") -> C/O Realty | C115: =IFERROR(VLOOKUP(D115,'Master sheet (Clientes)'!A$6:D$747,4,0)," ") -> N-O | D115: Southampton at Newport 20 River Ct, Jersey City, NJ 07310 | E115: 3405 | F115: 2BDR | G115: Occupied | H115: Karhs floor repair near ac unit in living room - Size of repair 48sqft at 9am Scope will be UPDATED: Due to an active water leak, approximately 200 sqft. of Kahrs flooring was removed, and the subfloor was left exposed to dry. | I115: M&J Flooring | J115: PO Pending | K115: Estimate pending | M115: Scope will be UPDATED | N115: Continue
A116: =IFERROR(VLOOKUP(D116,'Master sheet (Clientes)'!A$6:D$747,2,0)," ") -> NJ | B116: =IFERROR(VLOOKUP(D116,'Master sheet (Clientes)'!A$6:D$747,3,0)," ") -> C/O Realty | C116: =IFERROR(VLOOKUP(D116,'Master sheet (Clientes)'!A$6:D$747,4,0)," ") -> N-O | D116: Bisby at Newport 30 Park Lane North Jersey City, NJ 07310 | E116: 3202 | H116: Continue Floor Repair and Refinish: -Replace water damaged floor located in: kitchen- 8ft x 18ft -Sand approximately 730 square feet of existing flooring in: - entrance hallway - entire living room and kitchen - entire left side bedroom including closet - right side bedroom in front of closet -Smooth out any scratches left after sanding process to ensure a more even final appearance. -Apply one (1) coat of stain to area, match Scope will be UPDATED | I116: M&J Flooring | J116: PO Pending | K116: Estimate 17397 | M116: Scope will be UPDATED | N116: Continue
A117: =IFERROR(VLOOKUP(D117,'Master sheet (Clientes)'!A$6:D$747,2,0)," ") -> NJ | B117: =IFERROR(VLOOKUP(D117,'Master sheet (Clientes)'!A$6:D$747,3,0)," ") -> C/O Realty | C117: =IFERROR(VLOOKUP(D117,'Master sheet (Clientes)'!A$6:D$747,4,0)," ") -> N-O | D117: Atlantic at Newport 31 River Ct, Jersey City, NJ 07310 | E117: 1811 | G117: Vacant | H117: Living room Kahrs Floor Repair: Demo and discard damaged/scratched kahrs flooring located living room. -Prep and perform minor subfloor repairs. -Provide and install 72 sqft aprox of new Karhs Floor in mentioned area. | I117: M&J Flooring | J117: PO Pending | K117: Estimate 17396 | N117: Done
A118: =IFERROR(VLOOKUP(D118,'Master sheet (Clientes)'!A$6:D$747,2,0)," ") -> NJ | B118: =IFERROR(VLOOKUP(D118,'Master sheet (Clientes)'!A$6:D$747,3,0)," ") -> C/O Realty | C118: =IFERROR(VLOOKUP(D118,'Master sheet (Clientes)'!A$6:D$747,4,0)," ") -> N-O | D118: Atlantic at Newport 31 River Ct, Jersey City, NJ 07310 | E118: 1711 | G118: Occupied | H118: Parquet Floor Repair: Remove and discard 25 sqft of damaged parquet flooring located in front of the bathroom.\ Prep and perform minor subfloor repairs prior to the new floor installation.\ Provide and install 25 sqft of new parquet flooring in the mentioned area. | I118: M&J Flooring | J118: PO Pending | K118: Estimate 17404 | N118: Done
A119: =IFERROR(VLOOKUP(D119,'Master sheet (Clientes)'!A$6:D$747,2,0)," ") -> NJ | B119: =IFERROR(VLOOKUP(D119,'Master sheet (Clientes)'!A$6:D$747,3,0)," ") -> C/O Realty | C119: =IFERROR(VLOOKUP(D119,'Master sheet (Clientes)'!A$6:D$747,4,0)," ") -> N-O | D119: Riverside at Newport 1 River Ct, Jersey City, NJ 07310 | E119: 2907 | G119: Vacant | H119: Kahrs Floor Repair: Demo and discard damaged Kahrs floor located in the living room, approximately 25 sq. ft. \ Prepare and perform minor subfloor repairs prior to new floor installation. \ Provide and install 25 sq. ft. of new Kahrs flooring in the mentioned area. | I119: M&J Flooring | J119: PO Pending | K119: Estimate 17394 | N119: Done
A121: State | B121: MANAGEMENT | C121: BC CLERK | D121: BUILDING / ADDRESS | E121: UNIT / AREA | F121: SIZE | G121: WORKSITE STATUS | H121: JOB DESCRIPTION | I121: JOB AWARDED TO: / TECHS QUANTITY: | J121: REQUEST / P.O / WTN / W.O | K121: BC WORK ORDER / BC ESTIMATE | L121: EXTRAS | M121: SPECIAL NOTES / SEQUENCE | N121: VENDORS DAILY STATUS REPORT
A122: =IFERROR(VLOOKUP(D122,'Master sheet (Clientes)'!A$6:D$747,2,0)," ") -> NJ | B122: =IFERROR(VLOOKUP(D122,'Master sheet (Clientes)'!A$6:D$747,3,0)," ") -> C/O Realty | C122: =IFERROR(VLOOKUP(D122,'Master sheet (Clientes)'!A$6:D$747,4,0)," ") -> N-O | D122: Southampton at Newport 20 River Ct, Jersey City, NJ 07310 | E122: MGMT Office | H122: Offices Cleaning follow scope of work sent via email every Wednesday after 5PM and every Saturday during the day until further notice. | I122: YL Cleaning | J122: PO Pending | N122: Done
...

Sheet Thu, Sep 03
A1: BuildCare SCHEDULE THURSDAY, SEPTEMBER 03 / 2026
A3: SUPERVISOR ON CALL NJ: Sebastian Lopez (551) 202-4443 jlopez@build-care.com
A4: CREWS ASSIGNED BY DEFAULT ON CALL: DVM - Atlas Techs / Atlas Cleaning - HG Services
A5: CREWS CONFIRMED BY THE ON CALL: ????
A6: BC MEMBERS OFF/VACATIONS:
D9: STATE OF NEW JERSEY
D11: WATERFRONT AREA (Fort Lee - Edgewater - Cliffside Park - Fairview - North Bergen - West New York - Weehawken - North Hoboken "8th Street Up" )
D12: BC SUPERVISOR: Carlos Perez (862) 383-3884 cperez@build-care.com BC SUPERVISOR/RUNNER: Juan Zapata (551) 202-4443 jzapata@build-care.com
A14: State | B14: MANAGEMENT | C14: BC CLERK | D14: BUILDING / ADDRESS | E14: UNIT / AREA | F14: SIZE | G14: WORKSITE STATUS | H14: JOB DESCRIPTION | I14: JOB AWARDED TO: / TECHS QUANTITY: | J14: REQUEST / P.O / WTN / W.O | K14: BC WORK ORDER / BC ESTIMATE | L14: EXTRAS | M14: SPECIAL NOTES / SEQUENCE | N14: VENDORS DAILY STATUS REPORT
A15: =IFERROR(VLOOKUP(D15,'Master sheet (Clientes)'!A$6:D$747,2,0)," ") -> NJ | B15: =IFERROR(VLOOKUP(D15,'Master sheet (Clientes)'!A$6:D$747,3,0)," ") -> Vivmark Residential | C15: =IFERROR(VLOOKUP(D15,'Master sheet (Clientes)'!A$6:D$747,4,0)," ") -> N-O | D15: Avalon at Edgewater II New Building (Russell). | E15: 155 | G15: Occupied | H15: Continue Left side bedroom bathroom tile floor to be demoed, sub floor fixed, install new tiles, and grout area is 9ft x 6ft. at 9am Bc to provide all materials and labor needed to complete the job. For access, please call Christian 201-705-0879 or Alex 201-713-8719 | I15: AJ Canas Solutions Carlos / Willian Alvarez | J15: Email | N15: Done
A16: =IFERROR(VLOOKUP(D16,'Master sheet (Clientes)'!A$6:D$747,2,0)," ") -> NJ | B16: =IFERROR(VLOOKUP(D16,'Master sheet (Clientes)'!A$6:D$747,3,0)," ") -> Vivmark Residential | C16: =IFERROR(VLOOKUP(D16,'Master sheet (Clientes)'!A$6:D$747,4,0)," ") -> N-O | D16: Avalon at Edgewater I Old Building (River Mews). | E16: 426 | G16: Occupied | H16: Continue Make opening in guest bedroom 3x3 to reinstall loose Hvac vent, close opening, spackle, sand and paint NOTE: Bc to provide carpet film, plastic drop, spackle, mesh tape, trash bags, sanding sponge, blue tape and all other materials and labor needed to complete the job. / For access, please call Christian 201-705-0879 or Alex 201-713-8719 update the scope of work. Two more openings of 2x4 were required to see where ducts weren't connected. After the ducts were taped with duct tape, there still wasn't air flow. The building asked to please just temporarily close openings so they can do their own investigation tomorrow to see where the problem is. Once they determine and fix it, they will let us know so we can close all openings properly. | I16: AJ Canas Solutions Javier | J16: Email | N16: Continue
A17: =IFERROR(VLOOKUP(D17,'Master sheet (Clientes)'!A$6:D$747,2,0)," ") -> NJ | B17: =IFERROR(VLOOKUP(D17,'Master sheet (Clientes)'!A$6:D$747,3,0)," ") -> Vivmark Residential | C17: =IFERROR(VLOOKUP(D17,'Master sheet (Clientes)'!A$6:D$747,4,0)," ") -> N-O | D17: Avalon at Edgewater II New Building (Russell). | E17: 151 | G17: Occupied | H17: Make opening in bedroom ceiling to try to determine where leak is coming from once repaired, close opening, plaster, sand and paint ceiling at 9am The building will provide the paint Bc to provide all other materials and labor needed to complete the job. For access, please call Christian 201-705-0879 or Alex 201-713-8719 | I17: AJ Canas Solutions Ricardo | J17: Email | N17: Continue
A18: =IFERROR(VLOOKUP(D18,'Master sheet (Clientes)'!A$6:D$747,2,0)," ") -> NJ | B18: =IFERROR(VLOOKUP(D18,'Master sheet (Clientes)'!A$6:D$747,3,0)," ") -> Vivmark Residential | C18: =IFERROR(VLOOKUP(D18,'Master sheet (Clientes)'!A$6:D$747,4,0)," ") -> N-O | D18: Avalon at Edgewater II New Building (Russell). | E18: 116 | G18: Vacant | H18: Purchase and Install 24-inch grab bar by toilet wall in master bathroom NOTE: Bc to provide 24-inch grab bar, plastic drop, rosin paper, blue tape, and trash bags. / For access, please call Christian 201-705-0879 or Alex 201-713-8719 | I18: AJ Canas Solutions Marlon | J18: Email | N18: Done
A19: =IFERROR(VLOOKUP(D19,'Master sheet (Clientes)'!A$6:D$747,2,0)," ") -> NJ | B19: =IFERROR(VLOOKUP(D19,'Master sheet (Clientes)'!A$6:D$747,3,0)," ") -> Vivmark Residential | C19: =IFERROR(VLOOKUP(D19,'Master sheet (Clientes)'!A$6:D$747,4,0)," ") -> N-O | D19: Avalon at Edgewater I Old Building (River Mews). | E19: 313 | F19: 2BDR | G19: Vacant | H19: Paint unit ( Paint kitchen and livinroom ceiling) at 8:00am | I19: AJ Canas Solutions William Diaz | J19: Email | N19: Done
A20: =IFERROR(VLOOKUP(D20,'Master sheet (Clientes)'!A$6:D$747,2,0)," ") -> NJ | B20: =IFERROR(VLOOKUP(D20,'Master sheet (Clientes)'!A$6:D$747,3,0)," ") -> Vivmark Residential | C20: =IFERROR(VLOOKUP(D20,'Master sheet (Clientes)'!A$6:D$747,4,0)," ") -> N-O | D20: Avalon Hoboken 800 Madison St, Hoboken, NJ 07030. | E20: 420 | G20: Occupied | H20: Sheetrock replacement / Last Minute request assigned by Roberto | I20: AJ Canas Solutions Vinicio | J20: Email | N20: Continue
A22: State | B22: MANAGEMENT | C22: BC CLERK | D22: BUILDING / ADDRESS | E22: UNIT / AREA | F22: SIZE | G22: WORKSITE STATUS | H22: JOB DESCRIPTION | I22: JOB AWARDED TO: / TECHS QUANTITY: | J22: REQUEST / P.O / WTN / W.O | K22: BC WORK ORDER / BC ESTIMATE | L22: EXTRAS | M22: SPECIAL NOTES / SEQUENCE | N22: VENDORS DAILY STATUS REPORT
A23: =IFERROR(VLOOKUP(D23,'Master sheet (Clientes)'!A$6:D$747,2,0)," ") -> NJ | B23: =IFERROR(VLOOKUP(D23,'Master sheet (Clientes)'!A$6:D$747,3,0)," ") -> Vivmark Residential | C23: =IFERROR(VLOOKUP(D23,'Master sheet (Clientes)'!A$6:D$747,4,0)," ") -> N-O | D23: Avalon Hoboken 800 Madison St, Hoboken, NJ 07030. | E23: 520 | G23: Occupied | H23: Provide a certified plumber to replace a supply valve They have the valve Wednesday 09/92 /2026 Requested by Ian / Last Minute request assigned by Roberto | I23: Hydro Jersey | J23: Email | M23: Job done 09/02 / This leak at unit 520 damaged the unit 420 drywall | N23: Done
A25: State | B25: MANAGEMENT | C25: BC CLERK | D25: BUILDING / ADDRESS | E25: UNIT / AREA | F25: SIZE | G25: WORKSITE STATUS | H25: JOB DESCRIPTION | I25: JOB AWARDED TO: / TECHS QUANTITY: | J25: REQUEST / P.O / WTN / W.O | K25: BC WORK ORDER / BC ESTIMATE | L25: EXTRAS | M25: SPECIAL NOTES / SEQUENCE | N25: VENDORS DAILY STATUS REPORT
A26: =IFERROR(VLOOKUP(D26,'Master sheet (Clientes)'!A$6:D$747,2,0)," ") -> NJ | B26: =IFERROR(VLOOKUP(D26,'Master sheet (Clientes)'!A$6:D$747,3,0)," ") -> Vivmark Residential | C26: =IFERROR(VLOOKUP(D26,'Master sheet (Clientes)'!A$6:D$747,4,0)," ") -> N-O | D26: Avalon North Bergen 5665 John F. Kennedy Blvd, North Bergen, NJ 07047. | E26: 505 | G26: Occupied | H26: Purchase and install fire dumper (requires scaffolding) Note: Send two (2) people to assemble the scaffolding and disassemble the bed; the bed must be reassembled after the work is finished at 9:00am | I26: Perfect Weather Solutions / Atlas 2 Laborers with tools: Carlos Marin / Oscar Salazar | J26: Email | N26: Done
A27: =IFERROR(VLOOKUP(D27,'Master sheet (Clientes)'!A$6:D$747,2,0)," ") -> NJ | B27: =IFERROR(VLOOKUP(D27,'Master sheet (Clientes)'!A$6:D$747,3,0)," ") -> Greystar | C27: =IFERROR(VLOOKUP(D27,'Master sheet (Clientes)'!A$6:D$747,4,0)," ") -> A-V | D27: The Grand 508 51st St, West New York, NJ 07093 | E27: 411 | F27: 2BDR | G27: Vacant | H27: Paint unit and cleaning at 8:00am Note: The property will provide the paint. | I27: Atlas Armando Gaona | J27: Email | N27: Paint done
A28: =IFERROR(VLOOKUP(D28,'Master sheet (Clientes)'!A$6:D$747,2,0)," ") -> NJ | B28: =IFERROR(VLOOKUP(D28,'Master sheet (Clientes)'!A$6:D$747,3,0)," ") -> Greystar | C28: =IFERROR(VLOOKUP(D28,'Master sheet (Clientes)'!A$6:D$747,4,0)," ") -> A-V | D28: Twenty50 2050 Central Rd, Fort Lee, NJ 07024 | E28: 520 | F28: 1BDR + Den | G28: Vacant | H28: Paint unit at 8:00 am NOTE: For access call Willie:+1 (386) 518-9413 | I28: Atlas Douglas Espinal | J28: Email | M28: Make ready 09/04 | N28: Paint done
A30: State | B30: MANAGEMENT | C30: BC CLERK | D30: BUILDING / ADDRESS | E30: UNIT / AREA | F30: SIZE | G30: WORKSITE STATUS | H30: JOB DESCRIPTION | I30: JOB AWARDED TO: / TECHS QUANTITY: | J30: REQUEST / P.O / WTN / W.O | K30: BC WORK ORDER / BC ESTIMATE | L30: EXTRAS | M30: SPECIAL NOTES / SEQUENCE | N30: VENDORS DAILY STATUS REPORT
A31: =IFERROR(VLOOKUP(D31,'Master sheet (Clientes)'!A$6:D$747,2,0)," ") -> NJ | B31: =IFERROR(VLOOKUP(D31,'Master sheet (Clientes)'!A$6:D$747,3,0)," ") -> Vivmark Residential | C31: =IFERROR(VLOOKUP(D31,'Master sheet (Clientes)'!A$6:D$747,4,0)," ") -> N-O | D31: Avalon at Edgewater I Old Building (River Mews). | E31: 432 | F31: 3BDR | G31: Vacant | H31: Paint unit at 8:00am | I31: DVM Ignacio Luc / Celestino Luc | J31: Email | N31: Done
A33: State | B33: MANAGEMENT | C33: BC CLERK | D33: BUILDING / ADDRESS | E33: UNIT / AREA | F33: SIZE | G33: WORKSITE STATUS | H33: JOB DESCRIPTION | I33: JOB AWARDED TO: / TECHS QUANTITY: | J33: REQUEST / P.O / WTN / W.O | K33: BC WORK ORDER / BC ESTIMATE | L33: EXTRAS | M33: SPECIAL NOTES / SEQUENCE | N33: VENDORS DAILY STATUS REPORT
A34: =IFERROR(VLOOKUP(D34,'Master sheet (Clientes)'!A$6:D$747,2,0)," ") -> NJ | B34: =IFERROR(VLOOKUP(D34,'Master sheet (Clientes)'!A$6:D$747,3,0)," ") -> Vivmark Residential | C34: =IFERROR(VLOOKUP(D34,'Master sheet (Clientes)'!A$6:D$747,4,0)," ") -> N-O | D34: Avalon Hoboken 800 Madison St, Hoboken, NJ 07030. | E34: 606 | H34: Balcony door threshold and kitchen transition strip repair replacement. 1 transition of 36" and 1 transition of 72". at 9:00 am For access call Felix:+1 (848) 242-6308 Note: Build care provides the new transitions. | I34: M&J Flooring | J34: Email | N34: Done
A35: =IFERROR(VLOOKUP(D35,'Master sheet (Clientes)'!A$6:D$747,2,0)," ") -> NJ | B35: =IFERROR(VLOOKUP(D35,'Master sheet (Clientes)'!A$6:D$747,3,0)," ") -> Vivmark Residential | C35: =IFERROR(VLOOKUP(D35,'Master sheet (Clientes)'!A$6:D$747,4,0)," ") -> N-O | D35: Avalon Hoboken 800 Madison St, Hoboken, NJ 07030. | E35: 537 | H35: Balcony door threshold at 9:00 am For access call Felix:+1 (848) 242-6308 Last minute request / assigned by Property | I35: M&J Flooring | J35: Email pending roberto | N35: Done
A37: State | B37: MANAGEMENT | C37: BC CLERK | D37: BUILDING / ADDRESS | E37: UNIT / AREA | F37: SIZE | G37: WORKSITE STATUS | H37: JOB DESCRIPTION | I37: JOB AWARDED TO: / TECHS QUANTITY: | J37: REQUEST / P.O / WTN / W.O | K37: BC WORK ORDER / BC ESTIMATE | L37: EXTRAS | M37: SPECIAL NOTES / SEQUENCE | N37: VENDORS DAILY STATUS REPORT
A38: =IFERROR(VLOOKUP(D38,'Master sheet (Clientes)'!A$6:D$747,2,0)," ") -> NJ | B38: =IFERROR(VLOOKUP(D38,'Master sheet (Clientes)'!A$6:D$747,3,0)," ") -> Vivmark Residential | C38: =IFERROR(VLOOKUP(D38,'Master sheet (Clientes)'!A$6:D$747,4,0)," ") -> N-O | D38: Avalon at Edgewater II New Building (Russell). | E38: 155 | G38: Occupied | H38: Unit Cleaning after repair after 2pm | I38: YL Cleaning | J38: Email | M38: Clean 09/02 and 09/03
A39: =IFERROR(VLOOKUP(D39,'Master sheet (Clientes)'!A$6:D$747,2,0)," ") -> NJ | B39: =IFERROR(VLOOKUP(D39,'Master sheet (Clientes)'!A$6:D$747,3,0)," ") -> Vivmark Residential | C39: =IFERROR(VLOOKUP(D39,'Master sheet (Clientes)'!A$6:D$747,4,0)," ") -> N-O | D39: Avalon at Edgewater II New Building (Russell). | E39: 151 | G39: Occupied | H39: Unit Cleaning after repair after 2pm last minute request assigned by Carlos | I39: YL Cleaning | J39: Email | M39: Clean 09/02 and 09/03
A40: =IFERROR(VLOOKUP(D40,'Master sheet (Clientes)'!A$6:D$747,2,0)," ") -> NJ | B40: =IFERROR(VLOOKUP(D40,'Master sheet (Clientes)'!A$6:D$747,3,0)," ") -> Skylight | C40: =IFERROR(VLOOKUP(D40,'Master sheet (Clientes)'!A$6:D$747,4,0)," ") -> N-O | D40: Riello 99 Gorge Rd, Edgewater, NJ 07020 | E40: 801 | F40: 1BDR | G40: Vacant | H40: Unit cleaning at 8:00am | I40: YL Cleaning | J40: Email
A42: State | B42: MANAGEMENT | C42: BC CLERK | D42: BUILDING / ADDRESS | E42: UNIT / AREA | F42: SIZE | G42: WORKSITE STATUS | H42: JOB DESCRIPTION | I42: JOB AWARDED TO: / TECHS QUANTITY: | J42: REQUEST / P.O / WTN / W.O | K42: BC WORK ORDER / BC ESTIMATE | L42: EXTRAS | M42: SPECIAL NOTES / SEQUENCE | N42: VENDORS DAILY STATUS REPORT
A43: =IFERROR(VLOOKUP(D43,'Master sheet (Clientes)'!A$6:D$747,2,0)," ") -> NJ | B43: =IFERROR(VLOOKUP(D43,'Master sheet (Clientes)'!A$6:D$747,3,0)," ") -> Tower Management Service, LP | C43: =IFERROR(VLOOKUP(D43,'Master sheet (Clientes)'!A$6:D$747,4,0)," ") -> A-V | D43: Hudson Ridge Apartments Building 7300 JFK Blvd E North Bergen, NJ 07047 | E43: 4G | G43: Occupied | H43: Reglaze interior walls at 10:00 am (ON TIME PLEASE) | I43: Felix R Santos | J43: P.O SEP 170
A45: State | B45: MANAGEMENT | C45: BC CLERK | D45: BUILDING / ADDRESS | E45: UNIT / AREA | F45: SIZE | G45: WORKSITE STATUS | H45: JOB DESCRIPTION | I45: JOB AWARDED TO: / TECHS QUANTITY: | J45: REQUEST / P.O / WTN / W.O | K45: BC WORK ORDER / BC ESTIMATE | L45: EXTRAS | M45: SPECIAL NOTES / SEQUENCE | N45: VENDORS DAILY STATUS REPORT
A46: =IFERROR(VLOOKUP(D46,'Master sheet (Clientes)'!A$6:D$747,2,0)," ") -> NJ | B46: =IFERROR(VLOOKUP(D46,'Master sheet (Clientes)'!A$6:D$747,3,0)," ") -> Skylight | C46: =IFERROR(VLOOKUP(D46,'Master sheet (Clientes)'!A$6:D$747,4,0)," ") -> N-O | D46: Infinity at Edgewater 340 Old River Rd, Edgewater, NJ 07020 | E46: 523 | F46: 1BDR | G46: Vacant | H46: Carpet Replacement at 9:00am Note: Unit is painted already. Call Enrique for access: +1 (646) 984-3300 | I46: Excellent carpet | J46: Email | M46: Clean | N46: rescheduled next day the tech did not arrive
D48: SOUTH HOBOKEN "7th Street down" - JERSEY CITY - BAYONNE
D49: JERSEY CITY - BC SUPERVISOR: Carlos Perez (862) 383-3884 cperez@build-care.com - BC RUNNER: Juan Sebastian Salazar (862) 394-6010 jssalazar@build-care.com
A51: State | B51: MANAGEMENT | C51: BC CLERK | D51: BUILDING / ADDRESS | E51: UNIT / AREA | F51: SIZE | G51: WORKSITE STATUS | H51: JOB DESCRIPTION | I51: JOB AWARDED TO: / TECHS QUANTITY: | J51: REQUEST / P.O / WTN / W.O | K51: BC WORK ORDER / BC ESTIMATE | L51: EXTRAS | M51: SPECIAL NOTES / SEQUENCE | N51: VENDORS DAILY STATUS REPORT
A52: =IFERROR(VLOOKUP(D52,'Master sheet (Clientes)'!A$6:D$747,2,0)," ") -> NJ | B52: =IFERROR(VLOOKUP(D52,'Master sheet (Clientes)'!A$6:D$747,3,0)," ") -> Skylight | C52: =IFERROR(VLOOKUP(D52,'Master sheet (Clientes)'!A$6:D$747,4,0)," ") -> N-O | D52: Grand Adams Apartments 300 Grand St, Hoboken, NJ 07030 | H52: 1 Daily Handyman to work with the maintenance staff 8hrs shift to cover multiple properties under the instructions of the service general manager Upon Arrival Call Orville (646) 984-3306 from 9:00am to 5:00pm Monday to Friday until further notice Starting Tuesday 02/26/2025 | I52: Cuxil Group Eduardo Garcia | J52: Email | M52: until further notice | N52: Continue
A53: =IFERROR(VLOOKUP(D53,'Master sheet (Clientes)'!A$6:D$747,2,0)," ") -> NJ | B53: =IFERROR(VLOOKUP(D53,'Master sheet (Clientes)'!A$6:D$747,3,0)," ") -> Skylight | C53: =IFERROR(VLOOKUP(D53,'Master sheet (Clientes)'!A$6:D$747,4,0)," ") -> N-O | D53: Grand Adams Apartments 300 Grand St, Hoboken, NJ 07030 | H53: 1 Daily handyman for 8hrs shift to assist the property with internal tasks from Monday to Friday until further notice NOTE: Please Report to Christina 973-776-4602 | I53: Cuxil Group Marcos Garcia | J53: Email | M53: until further notice | N53: Continue
A54: =IFERROR(VLOOKUP(D54,'Master sheet (Clientes)'!A$6:D$747,2,0)," ") -> NJ | B54: =IFERROR(VLOOKUP(D54,'Master sheet (Clientes)'!A$6:D$747,3,0)," ") -> RHO | C54: =IFERROR(VLOOKUP(D54,'Master sheet (Clientes)'!A$6:D$747,4,0)," ") -> A-V | D54: Sable 200 Greene Street, Jersey City, NJ 07311. | H54: 1 Daily Handyman service from Wednesday 09/02/2026 trough Sunday 09/06/2026 Please Report to Nate (201) 466-8357 | I54: Sanai Pliability Delfino Cuxil | J54: Email | M54: Extended until Sunday 09/06 | N54: Continue
A56: State | B56: MANAGEMENT | C56: BC CLERK | D56: BUILDING / ADDRESS | E56: UNIT / AREA | F56: SIZE | G56: WORKSITE STATUS | H56: JOB DESCRIPTION | I56: JOB AWARDED TO: / TECHS QUANTITY: | J56: REQUEST / P.O / WTN / W.O | K56: BC WORK ORDER / BC ESTIMATE | L56: EXTRAS | M56: SPECIAL NOTES / SEQUENCE | N56: VENDORS DAILY STATUS REPORT
A57: =IFERROR(VLOOKUP(D57,'Master sheet (Clientes)'!A$6:D$747,2,0)," ") -> NJ | B57: =IFERROR(VLOOKUP(D57,'Master sheet (Clientes)'!A$6:D$747,3,0)," ") -> Rose Associates | C57: =IFERROR(VLOOKUP(D57,'Master sheet (Clientes)'!A$6:D$747,4,0)," ") -> A-V | D57: VYV Apartments North and South 474 Warren St, Jersey City, NJ 07302. | H57: 1 Daily Handyman Service: Provide a full-time daily handyman to assist the property with make-ready orders from 8:00 am to 4:30 pm. 5 Days per week Monday to Friday Starting Monday 08/03/26 to Friday 10/16/2026 | I57: Atlas Alexis Gomez | J57: Email | M57: 5 days per week Until 10/16 | N57: Continue
A58: =IFERROR(VLOOKUP(D58,'Master sheet (Clientes)'!A$6:D$747,2,0)," ") -> NJ | B58: =IFERROR(VLOOKUP(D58,'Master sheet (Clientes)'!A$6:D$747,3,0)," ") -> Bozzuto | C58: =IFERROR(VLOOKUP(D58,'Master sheet (Clientes)'!A$6:D$747,4,0)," ") -> N-O | D58: Vantage Collection 1 Park View Ave, Jersey City, NJ 07302 | E58: PH38 | F58: 2BDR | G58: Vacant | H58: Paint unit at 8:00 am | I58: Atlas Elder Velasquez / Jesus Alvardo | J58: Email | N58: Done
A59: =IFERROR(VLOOKUP(D59,'Master sheet (Clientes)'!A$6:D$747,2,0)," ") -> NJ | B59: =IFERROR(VLOOKUP(D59,'Master sheet (Clientes)'!A$6:D$747,3,0)," ") -> Vivmark Residential | C59: =IFERROR(VLOOKUP(D59,'Master sheet (Clientes)'!A$6:D$747,4,0)," ") -> A-V | D59: 70 Greene Apartments 70 Greene St, Jersey City, NJ 07302. | E59: 3111 | F59: Studio | G59: Vacant | H59: Paint unit at 8:00 am | I59: Atlas Javier Santiago | J59: WTN 86388866 | N59: Done
A61: State | B61: MANAGEMENT | C61: BC CLERK | D61: BUILDING / ADDRESS | E61: UNIT / AREA | F61: SIZE | G61: WORKSITE STATUS | H61: JOB DESCRIPTION | I61: JOB AWARDED TO: / TECHS QUANTITY: | J61: REQUEST / P.O / WTN / W.O | K61: BC WORK ORDER / BC ESTIMATE | L61: EXTRAS | M61: SPECIAL NOTES / SEQUENCE | N61: VENDORS DAILY STATUS REPORT
A62: =IFERROR(VLOOKUP(D62,'Master sheet (Clientes)'!A$6:D$747,2,0)," ") -> NJ | B62: =IFERROR(VLOOKUP(D62,'Master sheet (Clientes)'!A$6:D$747,3,0)," ") -> Greystar | C62: =IFERROR(VLOOKUP(D62,'Master sheet (Clientes)'!A$6:D$747,4,0)," ") -> A-V | D62: Observer Park Apartments 51 Garden St, Hoboken, NJ 07030 | E62: 1st floor hallway on the Bloomfield side | H62: Repair and install new drywall in ceiling of opening made by others at 9amThe building will provide the paint Bc to provide all other materials and labor needed to complete the job. For access, please call Victor 732-850-2331 | I62: Alluda Anibal Yojero / Misael Yojero | J62: Email | N62: Done
A64: State | B64: MANAGEMENT | C64: BC CLERK | D64: BUILDING / ADDRESS | E64: UNIT / AREA | F64: SIZE | G64: WORKSITE STATUS | H64: JOB DESCRIPTION | I64: JOB AWARDED TO: / TECHS QUANTITY: | J64: REQUEST / P.O / WTN / W.O | K64: BC WORK ORDER / BC ESTIMATE | L64: EXTRAS | M64: SPECIAL NOTES / SEQUENCE | N64: VENDORS DAILY STATUS REPORT
A65: =IFERROR(VLOOKUP(D65,'Master sheet (Clientes)'!A$6:D$747,2,0)," ") -> NJ | B65: =IFERROR(VLOOKUP(D65,'Master sheet (Clientes)'!A$6:D$747,3,0)," ") -> Skylight | C65: =IFERROR(VLOOKUP(D65,'Master sheet (Clientes)'!A$6:D$747,4,0)," ") -> N-O | D65: 335 Garden St Hoboken, NJ 07030 | E65: 8 | F65: 2BDR | G65: Vacant | H65: Paint unit and cleaning at 8:00am For Access, please call Orville 646-984-3306 | I65: DVM Marvin Cumes | J65: Email | N65: Paint done
A67: State | B67: MANAGEMENT | C67: BC CLERK | D67: BUILDING / ADDRESS | E67: UNIT / AREA | F67: SIZE | G67: WORKSITE STATUS | H67: JOB DESCRIPTION | I67: JOB AWARDED TO: / TECHS QUANTITY: | J67: REQUEST / P.O / WTN / W.O | K67: BC WORK ORDER / BC ESTIMATE | L67: EXTRAS | M67: SPECIAL NOTES / SEQUENCE | N67: VENDORS DAILY STATUS REPORT
A68: =IFERROR(VLOOKUP(D68,'Master sheet (Clientes)'!A$6:D$747,2,0)," ") -> NJ | B68: =IFERROR(VLOOKUP(D68,'Master sheet (Clientes)'!A$6:D$747,3,0)," ") -> Dalan Management | C68: =IFERROR(VLOOKUP(D68,'Master sheet (Clientes)'!A$6:D$747,4,0)," ") -> N-O | D68: The Lively Apartments 321 Warren St, Jersey City, NJ 07302 | E68: Lobby Entrance | H68: Make an opening on the panel so the heating system can let heat out between the doors. Create framing so panel can be secure from falling. at 8:00am BC to provide all materials and labor needed to complete the job Please call Kyle for access (551) 208-2742 | I68: HG Services | J68: Email | N68: Done
A70: State | B70: MANAGEMENT | C70: BC CLERK | D70: BUILDING / ADDRESS | E70: UNIT / AREA | F70: SIZE | G70: WORKSITE STATUS | H70: JOB DESCRIPTION | I70: JOB AWARDED TO: / TECHS QUANTITY: | J70: REQUEST / P.O / WTN / W.O | K70: BC WORK ORDER / BC ESTIMATE | L70: EXTRAS | M70: SPECIAL NOTES / SEQUENCE | N70: VENDORS DAILY STATUS REPORT
A71: =IFERROR(VLOOKUP(D71,'Master sheet (Clientes)'!A$6:D$747,2,0)," ") -> NJ | B71: =IFERROR(VLOOKUP(D71,'Master sheet (Clientes)'!A$6:D$747,3,0)," ") -> Greystar | C71: =IFERROR(VLOOKUP(D71,'Master sheet (Clientes)'!A$6:D$747,4,0)," ") -> A-V | D71: Embankment House 270 10th St, Jersey City, NJ 07302 | E71: 421 | F71: 3BDR | G71: Vacant | H71: Repair bathroom ceiling where the opening was made by others at 8:00am Note** unit is already clean please be careful and clean up after repair The building will provide the paint For access, please call Mike: 1 (845) 542-9676 or Gus 347-583-7765 | I71: AJ Canas Solutions Alberto | J71: Email | N71: Done
A73: State | B73: MANAGEMENT | C73: BC CLERK | D73: BUILDING / ADDRESS | E73: UNIT / AREA | F73: SIZE | G73: WORKSITE STATUS | H73: JOB DESCRIPTION | I73: JOB AWARDED TO: / TECHS QUANTITY: | J73: REQUEST / P.O / WTN / W.O | K73: BC WORK ORDER / BC ESTIMATE | L73: EXTRAS | M73: SPECIAL NOTES / SEQUENCE | N73: VENDORS DAILY STATUS REPORT
A74: =IFERROR(VLOOKUP(D74,'Master sheet (Clientes)'!A$6:D$747,2,0)," ") -> NJ | B74: =IFERROR(VLOOKUP(D74,'Master sheet (Clientes)'!A$6:D$747,3,0)," ") -> Vivmark Residential | C74: =IFERROR(VLOOKUP(D74,'Master sheet (Clientes)'!A$6:D$747,4,0)," ") -> A-V | D74: 70 Greene Apartments 70 Greene St, Jersey City, NJ 07302. | E74: 4104 | F74: 3BDR | G74: Vacant | H74: Unit cleaning 8:00 am NOTE: For access, please call Jonathan 862-387-9993 or Danny 646-508-3402 | I74: YL Cleaning | J74: WTN Pending | N74: Rescheduled next day
A75: =IFERROR(VLOOKUP(D75,'Master sheet (Clientes)'!A$6:D$747,2,0)," ") -> NJ | B75: =IFERROR(VLOOKUP(D75,'Master sheet (Clientes)'!A$6:D$747,3,0)," ") -> Vivmark Residential | C75: =IFERROR(VLOOKUP(D75,'Master sheet (Clientes)'!A$6:D$747,4,0)," ") -> A-V | D75: 70 Greene Apartments 70 Greene St, Jersey City, NJ 07302. | E75: 3102 | F75: Studio | G75: Vacant | H75: Unit cleaning at 8:00 am | I75: YL Cleaning | J75: WTN 86388686
A76: =IFERROR(VLOOKUP(D76,'Master sheet (Clientes)'!A$6:D$747,2,0)," ") -> NJ | B76: =IFERROR(VLOOKUP(D76,'Master sheet (Clientes)'!A$6:D$747,3,0)," ") -> Vivmark Residential | C76: =IFERROR(VLOOKUP(D76,'Master sheet (Clientes)'!A$6:D$747,4,0)," ") -> A-V | D76: 70 Greene Apartments 70 Greene St, Jersey City, NJ 07302. | E76: 2408 | F76: Studio | G76: Vacant | H76: Unit cleaning at 8:00 am | I76: YL Cleaning | J76: WTN 86388686
A77: =IFERROR(VLOOKUP(D77,'Master sheet (Clientes)'!A$6:D$747,2,0)," ") -> NJ | B77: =IFERROR(VLOOKUP(D77,'Master sheet (Clientes)'!A$6:D$747,3,0)," ") -> Vivmark Residential | C77: =IFERROR(VLOOKUP(D77,'Master sheet (Clientes)'!A$6:D$747,4,0)," ") -> A-V | D77: The Pier Apartments 1 Harborside Pl, Jersey City, NJ 07311. | E77: 542 | F77: 1BDR | G77: Vacant | H77: Unit cleaning at 8:00am | I77: YL Cleaning | J77: WTN 85887899
A78: =IFERROR(VLOOKUP(D78,'Master sheet (Clientes)'!A$6:D$747,2,0)," ") -> NJ | B78: =IFERROR(VLOOKUP(D78,'Master sheet (Clientes)'!A$6:D$747,3,0)," ") -> Skylight | C78: =IFERROR(VLOOKUP(D78,'Master sheet (Clientes)'!A$6:D$747,4,0)," ") -> N-O | D78: 221 Washington St, Hoboken, NJ 07030 | E78: 303 | F78: 1BDR | G78: Vacant | H78: Unit cleaning at 8:00am For Access, please call Orville 646-984-3306 | I78: YL Cleaning | J78: Email
A80: State | B80: MANAGEMENT | C80: BC CLERK | D80: BUILDING / ADDRESS | E80: UNIT / AREA | F80: SIZE | G80: WORKSITE STATUS | H80: JOB DESCRIPTION | I80: JOB AWARDED TO: / TECHS QUANTITY: | J80: REQUEST / P.O / WTN / W.O | K80: BC WORK ORDER / BC ESTIMATE | L80: EXTRAS | M80: SPECIAL NOTES / SEQUENCE | N80: VENDORS DAILY STATUS REPORT
A81: =IFERROR(VLOOKUP(D81,'Master sheet (Clientes)'!A$6:D$747,2,0)," ") -> NJ | B81: =IFERROR(VLOOKUP(D81,'Master sheet (Clientes)'!A$6:D$747,3,0)," ") -> Bozzuto | C81: =IFERROR(VLOOKUP(D81,'Master sheet (Clientes)'!A$6:D$747,4,0)," ") -> N-O | D81: The Morgan 160 Morgan St, Jersey City, NJ | E81: 1204 | F81: 1BDR | G81: Vacant | H81: Unit cleaning at 8:00am | I81: Atlas Way Cleaning | J81: Email
A82: =IFERROR(VLOOKUP(D82,'Master sheet (Clientes)'!A$6:D$747,2,0)," ") -> NJ | B82: =IFERROR(VLOOKUP(D82,'Master sheet (Clientes)'!A$6:D$747,3,0)," ") -> Skylight | C82: =IFERROR(VLOOKUP(D82,'Master sheet (Clientes)'!A$6:D$747,4,0)," ") -> N-O | D82: Grand Adams Apartments 300 Grand St, Hoboken, NJ 07030 | E82: 410 | F82: Studio | G82: Vacant | H82: Unit cleaning at 8:00am | I82: Atlas Way Cleaning | J82: Email
A84: State | B84: MANAGEMENT | C84: BC CLERK | D84: BUILDING / ADDRESS | E84: UNIT / AREA | F84: SIZE | G84: WORKSITE STATUS | H84: JOB DESCRIPTION | I84: JOB AWARDED TO: / TECHS QUANTITY: | J84: REQUEST / P.O / WTN / W.O | K84: BC WORK ORDER / BC ESTIMATE | L84: EXTRAS | M84: SPECIAL NOTES / SEQUENCE | N84: VENDORS DAILY STATUS REPORT
A85: =IFERROR(VLOOKUP(D85,'Master sheet (Clientes)'!A$6:D$747,2,0)," ") -> NJ | B85: =IFERROR(VLOOKUP(D85,'Master sheet (Clientes)'!A$6:D$747,3,0)," ") -> Dalan Management | C85: =IFERROR(VLOOKUP(D85,'Master sheet (Clientes)'!A$6:D$747,4,0)," ") -> N-O | D85: The Lively Apartments 321 Warren St, Jersey City, NJ 07302 | E85: 1611 | F85: Studio | G85: Vacant | H85: Unit cleaning at 8:00 am The building will provide the paint Please call Kyle for access (551) 208-2742 | I85: Unique Cleaning | J85: Email
A87: State | B87: MANAGEMENT | C87: BC CLERK | D87: BUILDING / ADDRESS | E87: UNIT / AREA | F87: SIZE | G87: WORKSITE STATUS | H87: JOB DESCRIPTION | I87: JOB AWARDED TO: / TECHS QUANTITY: | J87: REQUEST / P.O / WTN / W.O | K87: BC WORK ORDER / BC ESTIMATE | L87: EXTRAS | M87: SPECIAL NOTES / SEQUENCE | N87: VENDORS DAILY STATUS REPORT
A88: =IFERROR(VLOOKUP(D88,'Master sheet (Clientes)'!A$6:D$747,2,0)," ") -> NJ | B88: =IFERROR(VLOOKUP(D88,'Master sheet (Clientes)'!A$6:D$747,3,0)," ") -> Vivmark Residential | C88: =IFERROR(VLOOKUP(D88,'Master sheet (Clientes)'!A$6:D$747,4,0)," ") -> N-O | D88: Avalon Cove 444 Washington Blvd, Jersey City, NJ 07310. | E88: 2325 | G88: Occupied | H88: Reglaze bathtub at 9am Please be on time Note** please have tech remove all paper and tape after glaze is completed For access, please call Carlos 201-725-6086 or Manny 732-318-9169 | I88: Felix R Santos | J88: Email
A89: =IFERROR(VLOOKUP(D89,'Master sheet (Clientes)'!A$6:D$747,2,0)," ") -> NJ | B89: =IFERROR(VLOOKUP(D89,'Master sheet (Clientes)'!A$6:D$747,3,0)," ") -> Vivmark Residential | C89: =IFERROR(VLOOKUP(D89,'Master sheet (Clientes)'!A$6:D$747,4,0)," ") -> N-O | D89: Avalon Cove 444 Washington Blvd, Jersey City, NJ 07310. | E89: 5424 | G89: Vacant | H89: 2 bathtubs reglaze at 9am PLEASE BE ON TIME **Note** please have tech remove tape and paper reglaze is over For access, please call Carlos 201-725-6086 or Manny 732-318-9169 | I89: Felix R Santos | J89: Email
A90: =IFERROR(VLOOKUP(D90,'Master sheet (Clientes)'!A$6:D$747,2,0)," ") -> NJ | B90: =IFERROR(VLOOKUP(D90,'Master sheet (Clientes)'!A$6:D$747,3,0)," ") -> Vivmark Residential | C90: =IFERROR(VLOOKUP(D90,'Master sheet (Clientes)'!A$6:D$747,4,0)," ") -> N-O | D90: Avalon Cove 444 Washington Blvd, Jersey City, NJ 07310. | E90: 3253 | G90: Vacant | H90: kitchen countertops reglaze at 9am PLEASE BE ON TIME **Note** please have tech remove tape and paper reglaze is over For access, please call Carlos 201-725-6086 or Manny 732-318-9169 | I90: Felix R Santos | J90: Email
A91: =IFERROR(VLOOKUP(D91,'Master sheet (Clientes)'!A$6:D$747,2,0)," ") -> NJ | B91: =IFERROR(VLOOKUP(D91,'Master sheet (Clientes)'!A$6:D$747,3,0)," ") -> Vivmark Residential | C91: =IFERROR(VLOOKUP(D91,'Master sheet (Clientes)'!A$6:D$747,4,0)," ") -> A-V | D91: The Pier Apartments 1 Harborside Pl, Jersey City, NJ 07311. | E91: 754 | G91: Occupied | H91: Right side bathroom Bathtub reglaze and fix overflow Please have tech be there 9am sharp. ***note** please have tech remove tape and paper once reglaze is completed. For access, please call Jonathan 862-387-9993 | I91: Felix R Santos | J91: WTN# 86629971 | N91: Rescheduled for 09/05.
A92: =IFERROR(VLOOKUP(D92,'Master sheet (Clientes)'!A$6:D$747,2,0)," ") -> NJ | B92: =IFERROR(VLOOKUP(D92,'Master sheet (Clientes)'!A$6:D$747,3,0)," ") -> Skylight | C92: =IFERROR(VLOOKUP(D92,'Master sheet (Clientes)'!A$6:D$747,4,0)," ") -> N-O | D92: The Ashton 2 Ash Street, Jersey City | E92: 504 | F92: 1BDR | G92: Vacant | H92: Reglaze bathtub Note: please have tech remove tape and paper once reglaze is completed. For access, please call Brian 347-235-9152 or Camilio 917-615-6183 | I92: Felix R Santos | J92: Email
A93: =IFERROR(VLOOKUP(D93,'Master sheet (Clientes)'!A$6:D$747,2,0)," ") -> NJ | B93: =IFERROR(VLOOKUP(D93,'Master sheet (Clientes)'!A$6:D$747,3,0)," ") -> Windsor Communities | C93: =IFERROR(VLOOKUP(D93,'Master sheet (Clientes)'!A$6:D$747,4,0)," ") -> A-V | D93: Windsor at Liberty House Apartments 115 Morris St, Jersey City, NJ 07302 | E93: 2140 | G93: Vacant | H93: Reglaze bathtub 2nd Floor Right bathrom last minute request | I93: Felix R Santos | J93: Email
A95: State | B95: MANAGEMENT | C95: BC CLERK | D95: BUILDING / ADDRESS | E95: UNIT / AREA | F95: SIZE | G95: WORKSITE STATUS | H95: JOB DESCRIPTION | I95: JOB AWARDED TO: / TECHS QUANTITY: | J95: REQUEST / P.O / WTN / W.O | K95: BC WORK ORDER / BC ESTIMATE | L95: EXTRAS | M95: SPECIAL NOTES / SEQUENCE | N95: VENDORS DAILY STATUS REPORT
A96: =IFERROR(VLOOKUP(D96,'Master sheet (Clientes)'!A$6:D$747,2,0)," ") -> NJ | B96: =IFERROR(VLOOKUP(D96,'Master sheet (Clientes)'!A$6:D$747,3,0)," ") -> Bozzuto | C96: =IFERROR(VLOOKUP(D96,'Master sheet (Clientes)'!A$6:D$747,4,0)," ") -> N-O | D96: Birch House 49 Fisk St, Jersey City, NJ 07305 | E96: PH35 | G96: Occupied | H96: Kitchen Drain Repair: Replace 3-inch tee with a 2-inch tee laundry P-trap connection for the kitchen drain as required. -Repair and patch approximately a 2'x2' section of drywall and plaster following completion of the plumbing repairs before 12:00pm | I96: E&P Mechanical Corp Cassio | J96: Email | K96: Price base on Estimate 16922
A98: State | B98: MANAGEMENT | C98: BC CLERK | D98: BUILDING / ADDRESS | E98: UNIT / AREA | F98: SIZE | G98: WORKSITE STATUS | H98: JOB DESCRIPTION | I98: JOB AWARDED TO: / TECHS QUANTITY: | J98: REQUEST / P.O / WTN / W.O | K98: BC WORK ORDER / BC ESTIMATE | L98: EXTRAS | M98: SPECIAL NOTES / SEQUENCE | N98: VENDORS DAILY STATUS REPORT
A99: =IFERROR(VLOOKUP(D99,'Master sheet (Clientes)'!A$6:D$747,2,0)," ") -> NJ | B99: =IFERROR(VLOOKUP(D99,'Master sheet (Clientes)'!A$6:D$747,3,0)," ") -> Skylight | C99: =IFERROR(VLOOKUP(D99,'Master sheet (Clientes)'!A$6:D$747,4,0)," ") -> N-O | D99: Grand Adams Apartments 300 Grand St, Hoboken, NJ 07030 | E99: Leasing Office | H99: Carpet Replacement: Remove and dispose of the existing commercial carpet at the side entrance of the leasing office. -Furnish and install new commercial_x0002_grade carpet in a similar blue color. -Installation areas are approximately: * 17’ x 5’ 85 SF * 12’ x 6’ 72 SF -Install new tack strips and transition strips as required for a complete installation. Secure and finish all edges to ensure a clean, professional appearance. at 9:00am | I99: Excellent Carpet | J99: Email | K99: Estimate 16644 | N99: rescheduled next day the tech did not arrive
D101: NEWPORT
D102: BC SUPERVISOR: Jhonatan Perez (201) 800-5601 jperez@build-care.com / BC RUNNER: Eduard Bonifacio (551) 242-5958 purchases@build-care.com
A104: State | B104: MANAGEMENT | C104: BC CLERK | D104: BUILDING / ADDRESS | E104: UNIT / AREA | F104: SIZE | G104: WORKSITE STATUS | H104: JOB DESCRIPTION | I104: JOB AWARDED TO: / TECHS QUANTITY: | J104: REQUEST / P.O / WTN / W.O | K104: BC WORK ORDER / BC ESTIMATE | L104: EXTRAS | M104: SPECIAL NOTES / SEQUENCE | N104: VENDORS DAILY STATUS REPORT
A105: =IFERROR(VLOOKUP(D105,'Master sheet (Clientes)'!A$6:D$747,2,0)," ") -> NJ | B105: =IFERROR(VLOOKUP(D105,'Master sheet (Clientes)'!A$6:D$747,3,0)," ") -> C/O Realty | C105: =IFERROR(VLOOKUP(D105,'Master sheet (Clientes)'!A$6:D$747,4,0)," ") -> N-O | D105: Pacific at Newport 25 River Dr S, Jersey City, NJ 07310 | H105: 1 handyman for 5 days Assist the property with handyman tasks work orders / make ready from Monday 08/31/26 through Friday 09/04/26 at 8am Note: send Othoniel Gonzalez | I105: Cuxil Group Ottoniel Gonzales | J105: PO Pending | K105: Estimate 17341 | M105: Until Friday 09/04
A106: =IFERROR(VLOOKUP(D106,'Master sheet (Clientes)'!A$6:D$747,2,0)," ") -> NJ | B106: =IFERROR(VLOOKUP(D106,'Master sheet (Clientes)'!A$6:D$747,3,0)," ") -> C/O Realty | C106: =IFERROR(VLOOKUP(D106,'Master sheet (Clientes)'!A$6:D$747,4,0)," ") -> N-O | D106: Pacific at Newport 25 River Dr S, Jersey City, NJ 07310 | H106: 2 daily painters for 6 days Assist the property with painter tasks from Saturday 08/28/26 and Monday 08/31/26 through Friday 09/04/26 at 8am Note: property will provide all the materials and supervision | I106: Cuxil Group Edgar Lool / Sanai Pliability Alexander Polanco | J106: PO Pending | K106: Estimate 17343 | M106: Until Friday 09/04
A107: =IFERROR(VLOOKUP(D107,'Master sheet (Clientes)'!A$6:D$747,2,0)," ") -> NJ | B107: =IFERROR(VLOOKUP(D107,'Master sheet (Clientes)'!A$6:D$747,3,0)," ") -> C/O Realty | C107: =IFERROR(VLOOKUP(D107,'Master sheet (Clientes)'!A$6:D$747,4,0)," ") -> N-O | D107: Parkside West at Newport 40 Newport Parkway, Jersey City, NJ | H107: 1 handyman for 20 days Job: assist the property with handyman work work orders / make ready Schedule from Tuesday 08/25/26 through Saturday 08/29/26 Monday 08/31/26 through Friday 09/04/26 Tuesday 09/08/26 through Saturday 09/12/26 Monday 09/14/26 through Friday 09/18/26 at 8am Note: send Geovanny Saldivar Note: handyman will not work Monday 09/07/26 due to Labor Day holiday | I107: Cuxil Group Giovanny Saldivar | J107: PO Pending | M107: Until Fri 09/18
A108: =IFERROR(VLOOKUP(D108,'Master sheet (Clientes)'!A$6:D$747,2,0)," ") -> NJ | B108: =IFERROR(VLOOKUP(D108,'Master sheet (Clientes)'!A$6:D$747,3,0)," ") -> C/O Realty | C108: =IFERROR(VLOOKUP(D108,'Master sheet (Clientes)'!A$6:D$747,4,0)," ") -> N-O | D108: Parkside East at Newport 30 Newport Parkway, Jersey City, NJ | H108: 1 handyman for 20 days Job: assist the property with handyman work work orders / make ready Schedule from Tuesday 08/25/26 through Saturday 08/29/26 Monday 08/31/26 through Friday 09/04/26 Tuesday 09/08/26 through Saturday 09/12/26 Monday 09/14/26 through Friday 09/18/26 at 8am Note: send Oscar Monasterio Note: handyman will not work Monday 09/07/26 due to Labor Day holiday | I108: Cuxil Group Oscar Monasterio | J108: PO Pending | M108: Until Fri 09/18
A109: =IFERROR(VLOOKUP(D109,'Master sheet (Clientes)'!A$6:D$747,2,0)," ") -> NJ | B109: =IFERROR(VLOOKUP(D109,'Master sheet (Clientes)'!A$6:D$747,3,0)," ") -> C/O Realty | C109: =IFERROR(VLOOKUP(D109,'Master sheet (Clientes)'!A$6:D$747,4,0)," ") -> N-O | D109: East Hampton at Newport 30 River Ct, Jersey City, NJ 07310 | E109: 415 | F109: 1BDR | G109: Vacant | H109: Continue Full Renovation: Popcorn ceiling removal / renovation Bathroom / install kitchen backsplash / Paint entire unit incluiding ceiling | I109: Sanai Piability | J109: PO Pending | N109: Completed last day
A110: =IFERROR(VLOOKUP(D110,'Master sheet (Clientes)'!A$6:D$747,2,0)," ") -> NJ | B110: =IFERROR(VLOOKUP(D110,'Master sheet (Clientes)'!A$6:D$747,3,0)," ") -> C/O Realty | C110: =IFERROR(VLOOKUP(D110,'Master sheet (Clientes)'!A$6:D$747,4,0)," ") -> N-O | D110: Riverside at Newport 1 River Ct, Jersey City, NJ 07310 | E110: Garage 2nd floor | H110: 1 handyman for 10 days Assist the property with bathroom vanities repair from Monday 08/24/26 through Friday 08/28/26 - Monday 08/31/26 through Friday 09/04/26 at 8:30am Note: property to provide all materials and supervision Note: send David Pineda Must contact Karan upon arrival UPDATE: Tuesday 09/01 to Saturday 09/05 | I110: Cuxil Group | J110: PO Pending | M110: Until Fri 09/04 | N110: Cancelled by karan
A111: =IFERROR(VLOOKUP(D111,'Master sheet (Clientes)'!A$6:D$747,2,0)," ") -> NJ | B111: =IFERROR(VLOOKUP(D111,'Master sheet (Clientes)'!A$6:D$747,3,0)," ") -> C/O Realty | C111: =IFERROR(VLOOKUP(D111,'Master sheet (Clientes)'!A$6:D$747,4,0)," ") -> N-O | D111: Roosevelt House at Hamilton Park 180 10th St, Jersey City, NJ 07302 | H111: 1 handyman work for 15 days Assist the property with handyman tasks - work order / turns Sunday 08/16/26 through Thursday 08/20/26 - Sunday 08/23/26 through Thursday 08/27/26 Sunday 08/30/26 through Thursday 09/03/26 from 9am to 5:30pm Note: send Michael Garcia | I111: Sanai pliability Mayco Garcia | J111: PO Pending | K111: Estimate 17232 | M111: Until Thu 09/03
A112: =IFERROR(VLOOKUP(D112,'Master sheet (Clientes)'!A$6:D$747,2,0)," ") -> NJ | B112: =IFERROR(VLOOKUP(D112,'Master sheet (Clientes)'!A$6:D$747,3,0)," ") -> C/O Realty | C112: =IFERROR(VLOOKUP(D112,'Master sheet (Clientes)'!A$6:D$747,4,0)," ") -> N-O | D112: Southampton at Newport 20 River Ct, Jersey City, NJ 07310 | H112: 1 handyman for 15 days Assist the property with handyman task work orders / make ready from Tuesday 08/18/26 through Saturday 08/22/26, Tuesday 08/25/26 through Saturday 08/29/26 , Tuesday 09/01/26 through Saturday 09/05/26 from 10am to 6:30pm | I112: Sanai Pliability Wilber Ramirez | J112: PO Pending | K112: Estimate 17233 | M112: Until Sat 09/05
A113: =IFERROR(VLOOKUP(D113,'Master sheet (Clientes)'!A$6:D$747,2,0)," ") -> NJ | B113: =IFERROR(VLOOKUP(D113,'Master sheet (Clientes)'!A$6:D$747,3,0)," ") -> C/O Realty | C113: =IFERROR(VLOOKUP(D113,'Master sheet (Clientes)'!A$6:D$747,4,0)," ") -> N-O | D113: Pacific at Newport 25 River Dr S, Jersey City, NJ 07310 | E113: 1409 | F113: 2BDR | G113: Vacant | H113: Continue Full laundry room build-up: Framing | I113: Cuxil group Demetrio Semeya | J113: PO Pending | K113: Estimate 17169
A114: =IFERROR(VLOOKUP(D114,'Master sheet (Clientes)'!A$6:D$747,2,0)," ") -> NJ | B114: =IFERROR(VLOOKUP(D114,'Master sheet (Clientes)'!A$6:D$747,3,0)," ") -> C/O Realty | C114: =IFERROR(VLOOKUP(D114,'Master sheet (Clientes)'!A$6:D$747,4,0)," ") -> N-O | D114: Aquablu at Newport 110 River Dr S, Jersey City, NJ 07310 | E114: 5th floor hallway near unit 527 | H114: Continue Drywall Demo+Repairs: Demo drywall on ceiling to allow plumbing work.\ Size of the opening: 8 ft x 4 ft and 2 ft x 8 ft.\ Remove and save an existing door access panel.\ Once plumbing repairs are completed by others, install new drywall to seal the demo area.\ Tape, spackle, sand, and prime newly installed drywall.\ Paint repaired ceiling areas using flat white paint.\ Use property-provided paint to perform touch-up painting on walls as needed. | I114: Cuxil Group / Sanai Plaibility | J114: PO Pending | K114: Estimate 17317 | M114: We will return 09/02 in the afternoon to begin sealing demo areas once their plumber has completed their work. | N114: Cancelled Plumber working
A115: =IFERROR(VLOOKUP(D115,'Master sheet (Clientes)'!A$6:D$747,2,0)," ") -> NJ | B115: =IFERROR(VLOOKUP(D115,'Master sheet (Clientes)'!A$6:D$747,3,0)," ") -> C/O Realty | C115: =IFERROR(VLOOKUP(D115,'Master sheet (Clientes)'!A$6:D$747,4,0)," ") -> N-O | D115: Pacific at Newport 25 River Dr S, Jersey City, NJ 07310 | E115: 2007 | F115: 1BDR | G115: Vacant | H115: Continue Renovation: Popcorn ceiling removal / renovation Bathroom / install kitchen backsplash / Paint unit | I115: Cuxil Group / Sanai Plaibility Juan Garcia | J115: PO Pending
A116: =IFERROR(VLOOKUP(D116,'Master sheet (Clientes)'!A$6:D$747,2,0)," ") -> NJ | B116: =IFERROR(VLOOKUP(D116,'Master sheet (Clientes)'!A$6:D$747,3,0)," ") -> C/O Realty | C116: =IFERROR(VLOOKUP(D116,'Master sheet (Clientes)'!A$6:D$747,4,0)," ") -> N-O | D116: Pacific at Newport 25 River Dr S, Jersey City, NJ 07310 | E116: 2504 | G116: Vacant | H116: 1 handyman for 1 day make ready at 8:00am | I116: Sanai Plaibility Elmer Morales | J116: PO Pending
A117: =IFERROR(VLOOKUP(D117,'Master sheet (Clientes)'!A$6:D$747,2,0)," ") -> NJ | B117: =IFERROR(VLOOKUP(D117,'Master sheet (Clientes)'!A$6:D$747,3,0)," ") -> C/O Realty | C117: =IFERROR(VLOOKUP(D117,'Master sheet (Clientes)'!A$6:D$747,4,0)," ") -> N-O | D117: Riverside at Newport 1 River Ct, Jersey City, NJ 07310 | H117: Provide (2) full-time painters for (3) days to assist the property with painter's tasks.Wednesday 09/02/26 through Friday 09/04/26 | I117: Cuxil Group Yovanny Olgadez / Sanai Pliability Josue Olgadez | J117: PO Pending | K117: Estimate 17304 | M117: Until Fri 09/04
A118: =IFERROR(VLOOKUP(D118,'Master sheet (Clientes)'!A$6:D$747,2,0)," ") -> NJ | B118: =IFERROR(VLOOKUP(D118,'Master sheet (Clientes)'!A$6:D$747,3,0)," ") -> C/O Realty | C118: =IFERROR(VLOOKUP(D118,'Master sheet (Clientes)'!A$6:D$747,4,0)," ") -> N-O | D118: Southampton at Newport 20 River Ct, Jersey City, NJ 07310 | E118: 1207 | G118: Vacant | H118: one (1) handyman tomorrow 09/02/26 for make ready Please send Lorenz | I118: Sanai Pliability Sergio Chex | J118: PO Pending
A119: =IFERROR(VLOOKUP(D119,'Master sheet (Clientes)'!A$6:D$747,2,0)," ") -> NJ | B119: =IFERROR(VLOOKUP(D119,'Master sheet (Clientes)'!A$6:D$747,3,0)," ") -> C/O Realty | C119: =IFERROR(VLOOKUP(D119,'Master sheet (Clientes)'!A$6:D$747,4,0)," ") -> N-O | D119: Atlantic at Newport 31 River Ct, Jersey City, NJ 07310 | E119: 2503 | F119: 2BDR | G119: Vacant | H119: Popcorn ceiling removal / renovation Bathroom / install kitchen backsplash / Paint entire unit incluiding ceiling | I119: Cuxil Group David Pineda / Sanai Pliability Santiago Chanchavac / Luis Garcia | J119: PO Pending
A120: =IFERROR(VLOOKUP(D120,'Master sheet (Clientes)'!A$6:D$747,2,0)," ") -> NJ | B120: =IFERROR(VLOOKUP(D120,'Master sheet (Clientes)'!A$6:D$747,3,0)," ") -> C/O Realty | C120: =IFERROR(VLOOKUP(D120,'Master sheet (Clientes)'!A$6:D$747,4,0)," ") -> N-O | D120: Pacific at Newport 25 River Dr S, Jersey City, NJ 07310 | E120: 610 | F120: 2BDR | G120: Vacant | H120: Continue Renovation: Popcorn ceiling removal / renovation Bathroom / install kitchen backsplash / Paint entire unit incluiding ceiling | I120: Cuxil Group / Sanai Pliability | J120: PO Pending | N120: Cancelled floor no ready
A121: =IFERROR(VLOOKUP(D121,'Master sheet (Clientes)'!A$6:D$747,2,0)," ") -> NJ | B121: =IFERROR(VLOOKUP(D121,'Master sheet (Clientes)'!A$6:D$747,3,0)," ") -> C/O Realty | C121: =IFERROR(VLOOKUP(D121,'Master sheet (Clientes)'!A$6:D$747,4,0)," ") -> N-O | D121: Pacific at Newport 25 River Dr S, Jersey City, NJ 07310 | E121: 610 | F121: 2BDR | G121: Vacant | H121: Continue Full Laundry build-up: Framing | I121: Cuxil Group / Sanai Pliability | J121: PO Pending | K121: Estimate 17172 | N121: Cancelled floor no ready
A122: =IFERROR(VLOOKUP(D122,'Master sheet (Clientes)'!A$6:D$747,2,0)," ") -> NJ | B122: =IFERROR(VLOOKUP(D122,'Master sheet (Clientes)'!A$6:D$747,3,0)," ") -> C/O Realty | C122: =IFERROR(VLOOKUP(D122,'Master sheet (Clientes)'!A$6:D$747,4,0)," ") -> N-O | D122: Riverside at Newport 1 River Ct, Jersey City, NJ 07310 | E122: 2905 | F122: ??? | G122: Vacant | H122: Continue 1 Handymam for Make ready | I122: Cuxil Group / Sanai Pliability Eddy Cumes | J122: PO Pending
A123: =IFERROR(VLOOKUP(D123,'Master sheet (Clientes)'!A$6:D$747,2,0)," ") -> NJ | B123: =IFERROR(VLOOKUP(D123,'Master sheet (Clientes)'!A$6:D$747,3,0)," ") -> C/O Realty | C123: =IFERROR(VLOOKUP(D123,'Master sheet (Clientes)'!A$6:D$747,4,0)," ") -> N-O | D123: Aquablu at Newport 110 River Dr S, Jersey City, NJ 07310 | E123: 3208 | F123: ??? | G123: Vacant | H123: Continue 1 Handymam for Make ready | I123: Cuxil Group / Sanai Pliability Lorenzo Vaquiax | J123: PO Pending
A124: =IFERROR(VLOOKUP(D124,'Master sheet (Clientes)'!A$6:D$747,2,0)," ") -> NJ | B124: =IFERROR(VLOOKUP(D124,'Master sheet (Clientes)'!A$6:D$747,3,0)," ") -> C/O Realty | C124: =IFERROR(VLOOKUP(D124,'Master sheet (Clientes)'!A$6:D$747,4,0)," ") -> N-O | D124: Atlantic at Newport 31 River Ct, Jersey City, NJ 07310 | E124: 2609 | F124: ??? | G124: Vacant | H124: 1 Handymam for Make ready | I124: Sanai Pliability Jairo Cuxil | J124: PO Pending
A126: State | B126: MANAGEMENT | C126: BC CLERK | D126: BUILDING / ADDRESS | E126: UNIT / AREA | F126: SIZE | G126: WORKSITE STATUS | H126: JOB DESCRIPTION | I126: JOB AWARDED TO: / TECHS QUANTITY: | J126: REQUEST / P.O / WTN / W.O | K126: BC WORK ORDER / BC ESTIMATE | L126: EXTRAS | M126: SPECIAL NOTES / SEQUENCE | N126: VENDORS DAILY STATUS REPORT
A127: =IFERROR(VLOOKUP(D127,'Master sheet (Clientes)'!A$6:D$747,2,0)," ") -> NJ | B127: =IFERROR(VLOOKUP(D127,'Master sheet (Clientes)'!A$6:D$747,3,0)," ") -> C/O Realty | C127: =IFERROR(VLOOKUP(D127,'Master sheet (Clientes)'!A$6:D$747,4,0)," ") -> N-O | D127: Southampton at Newport 20 River Ct, Jersey City, NJ 07310 | E127: 3405 | F127: 2BDR | G127: Occupied | H127: Continue Karhs floor repair near ac unit in living room - Size of repair 48sqft at 9am Scope will be UPDATED: Due to an active water leak, approximately 200 sqft. of Kahrs flooring was removed, and the subfloor was left exposed to dry. | I127: M&J Flooring | J127: PO Pending | K127: Estimate pending | N127: Done
A128: =IFERROR(VLOOKUP(D128,'Master sheet (Clientes)'!A$6:D$747,2,0)," ") -> NJ | B128: =IFERROR(VLOOKUP(D128,'Master sheet (Clientes)'!A$6:D$747,3,0)," ") -> C/O Realty | C128: =IFERROR(VLOOKUP(D128,'Master sheet (Clientes)'!A$6:D$747,4,0)," ") -> N-O | D128: Bisby at Newport 30 Park Lane North Jersey City, NJ 07310 | E128: 3202 | H128: Continue Floor Repair and Refinish: -Replace water damaged floor located in: kitchen- 8ft x 18ft -Sand approximately 730 square feet of existing flooring in: - entrance hallway - entire living room and kitchen - entire left side bedroom including closet - right side bedroom in front of closet -Smooth out any scratches left after sanding process to ensure a more even final appearance. -Apply one (1) coat of stain to area, match | I128: M&J Flooring | J128: PO Pending | K128: Estimate 17397 | N128: Done
...

Sheet Fri, Sep 04
A1: BuildCare SCHEDULE FRIDAY, SEPTEMBER 04 / 2026
A3: SUPERVISOR ON CALL NJ: Sebastian Lopez (551) 202-4443 jlopez@build-care.com
A4: CREWS ASSIGNED BY DEFAULT ON CALL: DVM - Atlas Techs / Atlas Cleaning - HG Services
A5: CREWS CONFIRMED BY THE ON CALL: ????
A6: BC MEMBERS OFF/VACATIONS: Alejandro Lopez - Schedule Dept.
A7: CREW MEMBERS OFF/VACATIONS: Alluda Juan Lopez
D10: STATE OF NEW JERSEY
D12: WATERFRONT AREA (Fort Lee - Edgewater - Cliffside Park - Fairview - North Bergen - West New York - Weehawken - North Hoboken "8th Street Up" )
D13: BC SUPERVISOR: Carlos Perez (862) 383-3884 cperez@build-care.com BC SUPERVISOR/RUNNER: Juan Zapata (551) 202-4443 jzapata@build-care.com
A15: State | B15: MANAGEMENT | C15: BC CLERK | D15: BUILDING / ADDRESS | E15: UNIT / AREA | F15: SIZE | G15: WORKSITE STATUS | H15: JOB DESCRIPTION | I15: JOB AWARDED TO: / TECHS QUANTITY: | J15: REQUEST / P.O / WTN / W.O | K15: BC WORK ORDER / BC ESTIMATE | L15: EXTRAS | M15: SPECIAL NOTES / SEQUENCE | N15: VENDORS DAILY STATUS REPORT
A16: =IFERROR(VLOOKUP(D16,'Master sheet (Clientes)'!A$6:D$747,2,0)," ") -> NJ | B16: =IFERROR(VLOOKUP(D16,'Master sheet (Clientes)'!A$6:D$747,3,0)," ") -> Vivmark Residential | C16: =IFERROR(VLOOKUP(D16,'Master sheet (Clientes)'!A$6:D$747,4,0)," ") -> N-O | D16: Avalon at Edgewater I Old Building (River Mews). | E16: 426 | G16: Occupied | H16: Continue Make opening in guest bedroom 3x3 to reinstall loose Hvac vent, close opening, spackle, sand and paint NOTE: Bc to provide carpet film, plastic drop, spackle, mesh tape, trash bags, sanding sponge, blue tape and all other materials and labor needed to complete the job. / For access, please call Christian 201-705-0879 or Alex 201-713-8719 update the scope of work. Two more openings of 2x4 were required to see where ducts weren't connected. After the ducts were taped with duct tape, there still wasn't air flow. The building asked to please just temporarily close openings so they can do their own investigation tomorrow to see where the problem is. Once they determine and fix it, they will let us know so we can close all openings properly. | I16: AJ Canas Solutions Javier | J16: Email
A17: =IFERROR(VLOOKUP(D17,'Master sheet (Clientes)'!A$6:D$747,2,0)," ") -> NJ | B17: =IFERROR(VLOOKUP(D17,'Master sheet (Clientes)'!A$6:D$747,3,0)," ") -> Vivmark Residential | C17: =IFERROR(VLOOKUP(D17,'Master sheet (Clientes)'!A$6:D$747,4,0)," ") -> N-O | D17: Avalon at Edgewater II New Building (Russell). | E17: 151 | G17: Occupied | H17: Continue Make opening in bedroom ceiling to try to determine where leak is coming from once repaired, close opening, plaster, sand and paint ceiling at 9am The building will provide the paint Bc to provide all other materials and labor needed to complete the job. For access, please call Christian 201-705-0879 or Alex 201-713-8719 | I17: AJ Canas Solutions Ricardo | J17: Email
A18: =IFERROR(VLOOKUP(D18,'Master sheet (Clientes)'!A$6:D$747,2,0)," ") -> NJ | B18: =IFERROR(VLOOKUP(D18,'Master sheet (Clientes)'!A$6:D$747,3,0)," ") -> Skylight | C18: =IFERROR(VLOOKUP(D18,'Master sheet (Clientes)'!A$6:D$747,4,0)," ") -> N-O | D18: The Sterling 2055 Center Ave, Fort Lee, NJ 07024 | E18: 11F | G18: Occupied | H18: Repair openings made by others at 9am For access, please call Steve (646) 299-5888 or Jeffery 929-218-9732 | I18: AJ Canas Solutions Send photo | J18: Email
A19: =IFERROR(VLOOKUP(D19,'Master sheet (Clientes)'!A$6:D$747,2,0)," ") -> NJ | B19: =IFERROR(VLOOKUP(D19,'Master sheet (Clientes)'!A$6:D$747,3,0)," ") -> Vivmark Residential | C19: =IFERROR(VLOOKUP(D19,'Master sheet (Clientes)'!A$6:D$747,4,0)," ") -> N-O | D19: Avalon Hoboken 800 Madison St, Hoboken, NJ 07030. | E19: 420 | G19: Occupied | H19: Come back to close it up , tape. Spackle, sand, prime, and paint the damaged areas. At 9:00am Requested by Ian:+1 (201) 467-9749 Build care provides all, property provides the paint. | I19: AJ Canas Solutions Vinicio | J19: Email
A21: State | B21: MANAGEMENT | C21: BC CLERK | D21: BUILDING / ADDRESS | E21: UNIT / AREA | F21: SIZE | G21: WORKSITE STATUS | H21: JOB DESCRIPTION | I21: JOB AWARDED TO: / TECHS QUANTITY: | J21: REQUEST / P.O / WTN / W.O | K21: BC WORK ORDER / BC ESTIMATE | L21: EXTRAS | M21: SPECIAL NOTES / SEQUENCE | N21: VENDORS DAILY STATUS REPORT
A22: =IFERROR(VLOOKUP(D22,'Master sheet (Clientes)'!A$6:D$747,2,0)," ") -> NJ | B22: =IFERROR(VLOOKUP(D22,'Master sheet (Clientes)'!A$6:D$747,3,0)," ") -> Greystar | C22: =IFERROR(VLOOKUP(D22,'Master sheet (Clientes)'!A$6:D$747,4,0)," ") -> A-V | D22: Twenty50 2050 Central Rd, Fort Lee, NJ 07024 | E22: 520 / 515 / 720 | F22: 1BDR + Den | G22: Vacant | H22: Make ready at 8:00 am NOTE: For access call Willie:+1 (386) 518-9413 | I22: Alluda Anibal Yojero | J22: Email | M22: Cleaning
